Workbook
Name david: Equipment!$N$19:$P$21
Name david: 'Screen Inventory'!$P$19:$R$21
Name Header: [1]IFE!$B$3:$AK$3
Name Header: #REF!
Name Header: #REF!
Name Header: [1]IFE!$B$3:$AK$3
Name mine: Equipment!$M$18:$O$18
Name mine: 'Screen Inventory'!$O$18:$Q$18

Sheet Menu
A1: ONE-TRAX Report Menu
A2: * Click Run First Before Viewing, Printing or Saving Reports
A37: Author | B37: IFE Team
A38: Modified By | B38: D. Wilson / D. Ekas
A39: Date Modified | B39: 17 February, 2005
A40: Special Notes | B40: The "Run First" button must be clicked to sort the equipment information for the reports in this template. This template contains mud reporting, mud inventory, equipment, and screen inventory templates.
B41: The Save Final Report macro saves the worksheets as values and removes the links.
B42: The Mud Volume Info sheet was added by Ronnie Primeaux.
B43: The Solids Equipment & Screen costs were added to the mud checks by David Ekas.

Sheet WBM Check
J2: WATER-BASED MUD REPORT No. 16
A3: Operator : | B3: Cardon IV | D3: Field/Area : | E3: Golfo de Venezuela | H3: Depth/TVD : | I3: 2888 ft / | J3: 2888 ft
A4: Report For : | B4: KYLE MORRIS/ JOHNY QUINTERO | D4: Description : | E4: Exploratory | H4: Date : | I4: 39996
A5: Well Name : | B5: Perla-1X | D5: Location : | E5: Offshore | H5: Spud Date : | I5: 39981
A6: Contractor: | B6: Ensco | D6: Water Depth : | E6: 202 ft | H6: Mud Type : | I6: FLUIDO HI VIS
A7: Report For : | B7: WADE HARPER | D7: Rig Name : | E7: 68 | H7: Activity : | I7: POOH-W/CASING
A8: DRILLING ASSEMBLY | C8: CASING | E8: MUD VOLUME (bbl) | G8: CIRCULATION DATA
A9: 1849 ft, 20.-in DP | C9: 30.-in @563 ft (563 TVD) | E9: Hole | F9: Active Pits | H9: Pump Make | I9: NATIONAL 12P-160 | J9: NATIONAL 12P-160
A10: ft, -in | C10: 0 | E10: 1867 | F10: 681 | H10: Pump Liner x Stk | I10: 6,5x12 in | J10: 6,5x12 in
A11: ft, -in | C11: 0 | E11: Total Circulating Volume | H11: Pump Capacity gal/stk | I11: 5.016 | J11: 5.016
A12: ft, -in | C12: 0 | E12: 1866 | H12: Pump stk/min | I12: 65@97% | J12: 65@97%
A13: ft, -in | C13: 0 | E13: Depth Drilled Last 24 hr | H13: Flow Rate | I13: 652 | J13: gal/min
A14: ft, -in | C14: 0 | E14: 0 | F14: ft | H14: Pump Pressure | I14: 650 | J14: psi
A15: Nozzles 0 1/32" | C15: 0 | E15: Volume Drilled Last 24 hr | H15: Bottoms Up | I15: 35.7 min 4646 stk
A16: Bit 26-in 0 | C16: 0 | E16: 0 | F16: bbl | H16: Total Circulation | I16: 120.2 min 15624 stk
A17: MUD PROPERTIES | G17: PRODUCTS USED Last 24 hr
A18: Sample From | C18: TK 2 20:00 | D18: TK 2 1200. | G18: Products | I18: Size | J18: Amount
A19: FlowLine Temp | B19: °F | C19: 0 | D19: 0 | G19: POLYPAC R | I19: 50. LB BG | J19: 17
A20: Depth/TVD | B20: ft | C20: 2880/2880 | D20: 2880/2880 | G20: ENGINEERING SERVICE | I20: 1. EA | J20: 2
A21: Mud Weight /Temp | B21: lb/gal | C21: 10@85 | D21: 10@85 | G21: CAUSTIC SODA | I21: 25. KG BG | J21: 7
A22: Funnel Viscosity | B22: s/qt | C22: 40 | D22: 38 | G22: DUO-VIS | I22: 25. KG BG | J22: 8
A23: Rheology Temp | B23: °F | C23: 120 | D23: 120 | G23: 0 | I23: 0 | J23: 0
A24: R600/R300 | C24: 34/24 | D24: 34/24 | G24: 0 | I24: 0 | J24: 0
A25: R200/R100 | C25: 20/16 | D25: 21/15 | G25: 0 | I25: 0 | J25: 0
A26: R6/R3 | C26: 6/5 | D26: 6/5 | G26: 0 | I26: 0 | J26: 0
A27: PV | B27: cP | C27: 10 | D27: 10 | G27: 0 | I27: 0 | J27: 0
A28: YP | B28: lb/100ft² | C28: 14 | D28: 14 | G28: 0 | I28: 0 | J28: 0
A29: 10s/10m/30m Gel | B29: lb/100ft² | C29: 5/12/16 | D29: 5/12/14 | G29: 0 | I29: 0 | J29: 0
A30: API Fluid Loss | B30: cc/30min | C30: 18 | D30: 18 | G30: 0 | I30: 0 | J30: 0
A31: HTHP Fluid Loss | B31: cc/30min | C31: 0@ | D31: 0@ | G31: 0 | I31: 0 | J31: 0
A32: Cake APT/HT | B32: 1/32" | C32: 1/ | D32: 1/ | G32: 0 | I32: 0 | J32: 0
A33: Solids | B33: %Vol | C33: 8 | D33: 8 | G33: 0 | I33: 0 | J33: 0
A34: Oil/Water | B34: %Vol | C34: /92 | D34: /92 | G34: SOLIDS CONTROL EQUIPMENT Last 24 hr
A35: Sand | B35: %Vol | C35: 0.25 | D35: 0.25 | G35: Type | I35: Model/Size | J35: Hrs Used
A36: MBT | B36: lb/bbl | C36: 15 | D36: 15 | G36: DERRICK SHEKER 1 | I36: 4 X 170 | J36: 7
A37: pH / Temp | C37: 9@85 | D37: 9@85 | G37: DERRICK SHAKER 2 | I37: 2X140 2X100 | J37: 7
A38: Alkal Mud (Pm) | C38: 0.8 | D38: 0.8 | G38: DERRICK SHAKER 3 | I38: 4X170 | J38: 24
A39: Pf/Mf | B39: 0 | C39: 00/00 | D39: 00/00 | G39: MOD 312 / 10T2 w/o pump | I39: 4 X 200 | J39: 24
A40: Chlorides | B40: mg/L | C40: 18000 | D40: 18000 | G40: 0 | I40: 0 | J40: 0
A41: Hardness (Ca++) | C41: 100 | D41: 100 | G41: 0 | I41: 0 | J41: 0
A42: 0 | B42: 0 | C42: 0 | D42: 0 | G42: 0 | I42: 0 | J42: 0
A43: 0 | B43: 0 | C43: 0 | D43: 0 | G43: 0 | I43: 0 | J43: 0
A44: 0 | B44: 0 | C44: 0 | D44: 0 | E44: 0 | F44: 0 | G44: 0 | I44: 0 | J44: 0
A45: 0 | B45: 0 | C45: 0 | D45: 0 | E45: 0 | F45: 0 | G45: 0 | I45: 0 | J45: 0
A46: 0 | B46: 0 | C46: 0 | D46: 0 | E46: 0 | F46: 0 | G46: 0 | I46: 0 | J46: 0
A47: 0 | B47: 0 | C47: 0 | D47: 0 | E47: 0 | F47: 0 | G47: MUD PROPERTY SPECS | J47: Actual
A48: 0 | B48: 0 | C48: 0 | D48: 0 | E48: 0 | F48: 0 | G48: Weight | H48: 10 | J48: 10
A49: 0 | B49: 0 | C49: 0 | D49: 0 | E49: 0 | F49: 0 | G49: Viscosity | H49: 40 | J49: 40
A50: Reserve Volume | B50: bbl | C50: 333 | G50: Filtrate | H50: N/C | J50: 18
A51: REMARKS AND TREATMENT | E51: REMARKS
A52: Run 20" csng, stuck at 1951 ft, circulate, work pipe, when free, start POOH to lay down casing. Added some polymer adjust mud properties, and some pac for fluid loss control. Mixed and pumpe 2 sweeps while circulating through casing. Rcvd 805 bbls of Versaclean mud, store on rig tank. Will report entered on next mud report. | E52: After circulating casing, still not free, pull with a lot of tension, and slowly came free, POOH, and lay down casing, will RIH and clean hole
A53: TIME DISTRIBUTION Last 24 hrs | C53: MUD VOL ACCTG (bbl) | E53: SOLIDS ANALYSIS (%/lb/bbl) | H53: RHEOLOGY & HYDRAULICS
A54: Rig Up/Service | B54: 0 | C54: Oil Added | D54: 0 | E54: NaCl | G54: 0,8/ 9,6 | H54: np/na | J54: 0,503/0,332
A55: Drilling | B55: 0 | C55: Water Added | D55: 37 | E55: KCl | G55: 0,/ 0, | H55: Kp/Ka | J55: 1,115/3,106
A56: Tripping | B56: 0 | C56: Mud Received | D56: 0 | E56: Low Gravity | G56: 2,5/ 23,2 | H56: Bit Pressure Loss % | J56: / 0.
A57: Non-Productive Time | B57: 0 | C57: Mud Returned | D57: 0 | E57: Bentonite | G57: 1,5/ 13,3 | H57: Bit HHP/HSI | J57: / 0.
A58: Running Casing | B58: 0 | C58: Shakers | D58: 35 | E58: Drill Solids | G58: 0,9/ 7,6 | H58: Jet Velocity | J58: 0
A59: 0 | B59: 0 | C59: Left in Hole | D59: 19 | E59: Weight Material | G59: 4,6/ 68, | H59: Va Pipe | J59: 41.6
A60: 0 | B60: 0 | C60: Other | D60: 0 | E60: Chemical Conc | G60: - / 2,4 | H60: Va Collars | J60: 57.9
A61: 0 | B61: 0 | C61: Desplazamiento | D61: 0 | E61: Inert/React | G61: 0,3875 | H61: Cva Pipe | J61: 244
A62: 0 | B62: 0 | C62: Humectacion | D62: 0 | E62: Average SG | G62: 3,53 | H62: Cva Collars | J62: 258
A63: 0 | B63: 0 | C63: Desechado | D63: 75 | E63: 0 | G63: 0 | H63: ECD at Shoe | J63: 10.08
C64: Viaje | D64: 0 | H64: ECD at TD | J64: 10.12
C65: 0 | D65: 0
C66: 0 | D66: 0 | G66: DAILY COST | I66: CUMULATIVE COST
C67: 0 | D67: 0 | F67: Drlg Fluids | G67: 10960.5 | I67: 160863.84
A68: M-I ENGR / PHONE | C68: RIG PHONE | D68: WAREHOUSE PHONE | F68: S.R.E. & Engr. | G68: 0 | I68: 0
A69: Jesus Villarroel | C69: 0 | D69: 0 | F69: Screens | G69: 0 | I69: 0
A70: 0 | F70: TOTALS | G70: 10960.5 | I70: 160863.84

Sheet CALDRIL Check
J2: ="CALDRIL MUD REPORT No. "&[1]IFE!B166&" " -> CALDRIL MUD REPORT No. 9
A3: Operator : | B3: =[1]IFE!B6 -> Cardon IV | D3: Field/Area : | E3: =[1]IFE!B9 -> Golfo de Venezuela | H3: Depth/TVD : | I3: =[1]IFE!B120&" "&[1]IFE!B30&" /" -> 563 pies / | J3: =[1]IFE!B121&" "&[1]IFE!B30 -> 563 pies
A4: Report For : | B4: =[1]IFE!B125 -> Gerrit Ham / Jhony Quintero | D4: Description : | E4: =[1]IFE!B10 -> Exploratory | H4: Date : | I4: =[1]IFE!B119 -> 39989
A5: Well Name : | B5: =[1]IFE!B8 -> Perla-1X | D5: Location : | E5: =[1]IFE!B11 -> Offshore | H5: Spud Date : | I5: =[1]IFE!B5 -> 39981
A6: Contractor: | B6: =[1]IFE!B15 -> Ensco | D6: Water Depth : | E6: =[1]IFE!B16&" "&[1]IFE!B30 -> 202 pies | H6: Mud Type : | I6: =[1]IFE!B124 -> Agua de mar / HI VIS
A7: Report For : | B7: =[1]IFE!B126 -> Ricky Otwell | D7: Rig Name : | E7: =[1]IFE!Z981 -> 68 | H7: Activity : | I7: =[1]IFE!B123 -> Bajando Tuberia
A8: DRILLING ASSEMBLY | C8: CASING | E8: ="MUD VOLUME" & " ("& [1]IFE!B32&")" -> MUD VOLUME (bbl) | G8: CIRCULATION DATA
A9: =[1]IFE!B167 -> pies, 5.5-plg DP | C9: =[1]IFE!B173 -> 30.-plg @563 pies (563 TVD) | E9: Hole | F9: Active Pits | H9: Pump Make | I9: =[1]IFE!B161 -> NATIONAL 12P-160 | J9: =[1]IFE!B162 -> NATIONAL 12P-160
A10: =[1]IFE!B168 -> 372 pies, 5.5-plg HWDP | C10: =[1]IFE!B174 -> 0 | E10: =[1]IFE!B177 -> 429 | F10: =[1]IFE!B178 -> 0 | H10: Pump Liner x Stk | I10: =[1]IFE!C161&"x"&[1]IFE!D161&" "&[1]IFE!B31 -> 6,5x12 plg | J10: =[1]IFE!C162&"x"&[1]IFE!D162&" "&[1]IFE!B31 -> 6,5x12 plg
A11: =[1]IFE!B169 -> 65 pies, 8.-plg DC | C11: =[1]IFE!B175 -> 0 | E11: Total Circulating Volume | H11: ="Pump Capacity "&[1]IFE!B57 -> Pump Capacity gal/emb | I11: =[1]IFE!B182 -> 5.016 | J11: =[1]IFE!B183 -> 5.016
A12: =[1]IFE!B170 -> 34 pies, 8.-plg JAR | C12: =[1]IFE!B176 -> 0 | E12: =[1]IFE!$B$179 -> 0 | H12: Pump stk/min | I12: =[1]IFE!G161&"@"&[1]IFE!F161&"%" -> 0@97% | J12: =[1]IFE!G162&"@"&[1]IFE!F162&"%" -> 0@97%
A13: =[1]IFE!B171 -> 96 pies, 8.-plg DC | C13: =[1]IFE!D173 -> 0 | E13: Depth Drilled Last 24hr | H13: Flow Rate | I13: =[1]IFE!B150 -> 0 | J13: =[1]IFE!B33 -> gal/min
A14: =[1]IFE!B172 -> 31 pies, 9.5-plg DC | C14: =[1]IFE!D174 -> 0 | E14: =[1]IFE!$BE$86 -> 0 | F14: =[1]IFE!$B$30 -> pies | H14: Pump Pressure | I14: =[1]IFE!B152 -> 0 | J14: =[1]IFE!B36 -> psi
A15: ="Nozzles "&[1]IFE!B139&IF([1]IFE!B142=0,"","x"&[1]IFE!B142)&IF([1]IFE!B140=0,"","/"&[1]IFE!B140&IF([1]IFE!B143=0,"","x"&[1]IFE!B143))&IF([1]IFE!B141=0,"", "/"&[1]IFE!B141&IF([1]IFE!B144=0,"","x"&[1]IFE!B144))&" "&[1]IFE!B34 -> Nozzles 0 1/32 plg | C15: =[1]IFE!D175 -> 0 | E15: Volume Drilled Last 24hr | H15: Bottoms Up | I15: =[1]IFE!B186 -> 0
A16: ="Bit "&[1]IFE!B136 & "-" & [1]IFE!B31&" "&[1]IFE!B137 -> Bit 26-plg 0 | C16: =[1]IFE!D176 -> 0 | E16: =[1]IFE!$D$148 -> 0 | F16: =[1]IFE!$B$32 -> bbl | H16: Total Circulation | I16: =[1]IFE!B187 -> 0
A17: MUD PROPERTIES | G17: PRODUCTS USED Last 24 hr
A18: Sample From | C18: =CONCATENATE(TEXT([1]IFE!C77," ")&" "&TEXT([1]IFE!C78,"H:MM")) -> TK 1 12:00 | D18: =CONCATENATE(TEXT([1]IFE!D77," ")&" "&TEXT([1]IFE!D78,"H:MM")) -> 0:00 | E18: =CONCATENATE(TEXT([1]IFE!E77," ")&" "&TEXT([1]IFE!E78,"H:MM")) -> TK 3 12:00 | F18: =CONCATENATE(TEXT([1]IFE!F77," ")&" "&TEXT([1]IFE!F78,"H:MM")) -> TK 3 0:00 | G18: Products | I18: Size | J18: Amount
A19: FlowLine Temp | B19: =[1]IFE!B40 -> °F | C19: =[1]IFE!C79 -> 0 | D19: =[1]IFE!D79 -> 0 | E19: =[1]IFE!E79 -> 0 | F19: =[1]IFE!F79 -> 0 | G19: =[1]IFE!B313 -> ENGINEERING SERVICE | I19: =[1]IFE!C313 -> 1. EA | J19: =[1]IFE!D313 -> 2
A20: Depth/TVD | B20: =[1]IFE!B30 -> pies | C20: =CONCATENATE(TEXT([1]IFE!C80,"#")&"/"&TEXT([1]IFE!C81,"#")) -> 563/563 | D20: =CONCATENATE(TEXT([1]IFE!D80,"#")&"/"&TEXT([1]IFE!D81,"#")) -> 563/563 | E20: =CONCATENATE(TEXT([1]IFE!E80,"#")&"/"&TEXT([1]IFE!E81,"#")) -> 563/563 | F20: =CONCATENATE(TEXT([1]IFE!F80,"#")&"/"&TEXT([1]IFE!F81,"#")) -> 563/563 | G20: =[1]IFE!B314 -> BENTONITE WYOMING | I20: =[1]IFE!C314 -> 100. LB BG | J20: =[1]IFE!D314 -> 1
A21: Mud Weight /Temp | B21: =[1]IFE!B39 -> lb/gal | C21: =CONCATENATE(TEXT([1]IFE!C82,"#.0")&"@"&TEXT([1]IFE!C83,"#")) -> 9.1@85 | D21: =CONCATENATE(TEXT([1]IFE!D82,"#.0")&"@"&TEXT([1]IFE!D83,"#")) -> 9.1@85 | E21: =CONCATENATE(TEXT([1]IFE!E82,"#.0")&"@"&TEXT([1]IFE!E83,"#")) -> 14.0@85 | F21: =CONCATENATE(TEXT([1]IFE!F82,"#.0")&"@"&TEXT([1]IFE!F83,"#")) -> 14.0@85 | G21: =[1]IFE!B315 -> DUO-VIS | I21: =[1]IFE!C315 -> 25. KG BG | J21: =[1]IFE!D315 -> 5
A22: Funnel Viscosity | B22: =[1]IFE!B43 -> s/ct | C22: =[1]IFE!C84 -> 55 | D22: =[1]IFE!D84 -> 55 | E22: =[1]IFE!E84 -> 80 | F22: =[1]IFE!F84 -> 80 | G22: =[1]IFE!B316 -> 0 | I22: =[1]IFE!C316 -> 0 | J22: =[1]IFE!D316 -> 0
A23: Rheology Temp | B23: =[1]IFE!B40 -> °F | C23: =[1]IFE!C85 -> 120 | D23: =[1]IFE!D85 -> 120 | E23: =[1]IFE!E85 -> 120 | F23: =[1]IFE!F85 -> 120 | G23: =[1]IFE!B317 -> 0 | I23: =[1]IFE!C317 -> 0 | J23: =[1]IFE!D317 -> 0
A24: R600/R300 | C24: =CONCATENATE(TEXT([1]IFE!C86,"#")&"/"&TEXT([1]IFE!C87,"#")) -> 38/27 | D24: =CONCATENATE(TEXT([1]IFE!D86,"#")&"/"&TEXT([1]IFE!D87,"#")) -> 38/27 | E24: =CONCATENATE(TEXT([1]IFE!E86,"#")&"/"&TEXT([1]IFE!E87,"#")) -> 130/81 | F24: =CONCATENATE(TEXT([1]IFE!F86,"#")&"/"&TEXT([1]IFE!F87,"#")) -> 130/81 | G24: =[1]IFE!B318 -> 0 | I24: =[1]IFE!C318 -> 0 | J24: =[1]IFE!D318 -> 0
A25: R200/R100 | C25: =CONCATENATE(TEXT([1]IFE!C88,"#")&"/"&TEXT([1]IFE!C89,"#")) -> 23/18 | D25: =CONCATENATE(TEXT([1]IFE!D88,"#")&"/"&TEXT([1]IFE!D89,"#")) -> 23/18 | E25: =CONCATENATE(TEXT([1]IFE!E88,"#")&"/"&TEXT([1]IFE!E89,"#")) -> 61/39 | F25: =CONCATENATE(TEXT([1]IFE!F88,"#")&"/"&TEXT([1]IFE!F89,"#")) -> 61/39 | G25: =[1]IFE!B319 -> 0 | I25: =[1]IFE!C319 -> 0 | J25: =[1]IFE!D319 -> 0
A26: R6/R3 | C26: =CONCATENATE(TEXT([1]IFE!C90,"#")&"/"&TEXT([1]IFE!C91,"#")) -> 11/10 | D26: =CONCATENATE(TEXT([1]IFE!D90,"#")&"/"&TEXT([1]IFE!D91,"#")) -> 11/10 | E26: =CONCATENATE(TEXT([1]IFE!E90,"#")&"/"&TEXT([1]IFE!E91,"#")) -> 10/8 | F26: =CONCATENATE(TEXT([1]IFE!F90,"#")&"/"&TEXT([1]IFE!F91,"#")) -> 10/8 | G26: =[1]IFE!B320 -> 0 | I26: =[1]IFE!C320 -> 0 | J26: =[1]IFE!D320 -> 0
A27: PV | B27: =[1]IFE!B41 -> cP | C27: =[1]IFE!C92 -> 11 | D27: =[1]IFE!D92 -> 11 | E27: =[1]IFE!E92 -> 49 | F27: =[1]IFE!F92 -> 49 | G27: =[1]IFE!B321 -> 0 | I27: =[1]IFE!C321 -> 0 | J27: =[1]IFE!D321 -> 0
A28: YP | B28: =[1]IFE!B42 -> lb/100p² | C28: =[1]IFE!C93 -> 16 | D28: =[1]IFE!D93 -> 16 | E28: =[1]IFE!E93 -> 32 | F28: =[1]IFE!F93 -> 32 | G28: =[1]IFE!B322 -> 0 | I28: =[1]IFE!C322 -> 0 | J28: =[1]IFE!D322 -> 0
A29: 10s/10m/30m Gel | B29: =[1]IFE!B42 -> lb/100p² | C29: =CONCATENATE(TEXT([1]IFE!C94,"#")&"/"&(TEXT([1]IFE!C95,"#")&"/"&TEXT([1]IFE!C96,"#"))) -> 11/15/ | D29: =CONCATENATE(TEXT([1]IFE!D94,"#")&"/"&(TEXT([1]IFE!D95,"#")&"/"&TEXT([1]IFE!D96,"#"))) -> 11/15/ | E29: =CONCATENATE(TEXT([1]IFE!E94,"#")&"/"&(TEXT([1]IFE!E95,"#")&"/"&TEXT([1]IFE!E96,"#"))) -> 12/18/ | F29: =CONCATENATE(TEXT([1]IFE!F94,"#")&"/"&(TEXT([1]IFE!F95,"#")&"/"&TEXT([1]IFE!F96,"#"))) -> 12/18/ | G29: =[1]IFE!B323 -> 0 | I29: =[1]IFE!C323 -> 0 | J29: =[1]IFE!D323 -> 0
A30: API Fluid Loss | B30: =[1]IFE!D57 -> cc/30min | C30: =[1]IFE!C97 -> 0 | D30: =[1]IFE!D97 -> 0 | E30: =[1]IFE!E97 -> 0 | F30: =[1]IFE!F97 -> 0 | G30: =[1]IFE!B324 -> 0 | I30: =[1]IFE!C324 -> 0 | J30: =[1]IFE!D324 -> 0
A31: HTHP Fluid Loss | B31: =[1]IFE!D57 -> cc/30min | C31: =CONCATENATE(TEXT([1]IFE!Z538,"#.0")&"@"&TEXT([1]IFE!C99,"#")) -> .0@ | D31: =CONCATENATE(TEXT([1]IFE!D98,"#.0")&"@"&TEXT([1]IFE!D99,"#")) -> .0@ | E31: =CONCATENATE(TEXT([1]IFE!E98,"#.0")&"@"&TEXT([1]IFE!E99,"#")) -> .0@ | F31: =CONCATENATE(TEXT([1]IFE!Z661,"#.0")&"@"&TEXT([1]IFE!F99,"#")) -> .0@ | G31: =[1]IFE!B325 -> 0 | I31: =[1]IFE!C325 -> 0 | J31: =[1]IFE!D325 -> 0
A32: Cake APT/HT | B32: =[1]IFE!B34 -> 1/32 plg | C32: =CONCATENATE(TEXT([1]IFE!C100,"#")&"/"&TEXT([1]IFE!Z541,"#")) -> / | D32: =CONCATENATE(TEXT([1]IFE!D100,"#")&"/"&TEXT([1]IFE!D101,"#")) -> / | E32: =CONCATENATE(TEXT([1]IFE!E100,"#")&"/"&TEXT([1]IFE!E101,"#")) -> / | F32: =CONCATENATE(TEXT([1]IFE!F100,"#")&"/"&TEXT([1]IFE!Z664,"#")) -> / | G32: =[1]IFE!B326 -> 0 | I32: =[1]IFE!C326 -> 0 | J32: =[1]IFE!D326 -> 0
A33: Solids | B33: =[1]IFE!D59 -> %Vol | C33: =[1]IFE!C102 -> 4.2 | D33: =[1]IFE!D102 -> 4.2 | E33: =[1]IFE!E102 -> 22 | F33: =[1]IFE!F102 -> 22 | G33: =[1]IFE!B327 -> 0 | I33: =[1]IFE!C327 -> 0 | J33: =[1]IFE!D327 -> 0
A34: Oil/Water | B34: =[1]IFE!D59 -> %Vol | C34: =CONCATENATE(TEXT([1]IFE!C103,"#")&"/"&TEXT([1]IFE!C104,"#")) -> /96 | D34: =CONCATENATE(TEXT([1]IFE!D103,"#")&"/"&TEXT([1]IFE!D104,"#")) -> /96 | E34: =CONCATENATE(TEXT([1]IFE!E103,"#")&"/"&TEXT([1]IFE!E104,"#")) -> /78 | F34: =CONCATENATE(TEXT([1]IFE!F103,"#")&"/"&TEXT([1]IFE!F104,"#")) -> /78 | G34: SOLIDS CONTROL EQUIPMENT Last 24 hr
A35: Sand | B35: =[1]IFE!D59 -> %Vol | C35: =[1]IFE!C105 -> 0 | D35: =[1]IFE!D105 -> 0 | E35: =[1]IFE!E105 -> 0 | F35: =[1]IFE!F105 -> 0 | G35: Type | I35: Model/Size | J35: Hrs Used
A36: MBT | B36: =[1]IFE!B44 -> lb/bbl | C36: =[1]IFE!C106 -> 20 | D36: =[1]IFE!D106 -> 20 | E36: =[1]IFE!E106 -> 15 | F36: =[1]IFE!F106 -> 15 | G36: =[1]IFE!$B220 -> DERRICK SHEKER 1 | I36: =[1]IFE!$C220 -> 2X100 - 2X140 | J36: =[1]IFE!$D220 -> 0
A37: pH / Temp | C37: =CONCATENATE(TEXT([1]IFE!C107,"#.0")&"@"&TEXT([1]IFE!C108,"#")) -> 10.0@85 | D37: =CONCATENATE(TEXT([1]IFE!D107,"#.0")&"@"&TEXT([1]IFE!D108,"#")) -> 10.0@85 | E37: =CONCATENATE(TEXT([1]IFE!E107,"#.0")&"@"&TEXT([1]IFE!E108,"#")) -> 10.5@85 | F37: =CONCATENATE(TEXT([1]IFE!F107,"#.0")&"@"&TEXT([1]IFE!F108,"#")) -> 10.5@85 | G37: =[1]IFE!$B221 -> DERRICK SHAKER 2 | I37: =[1]IFE!$C221 -> 2X100 - 2X140 | J37: =[1]IFE!$D221 -> 0
A38: Alkal Mud (Pm) | C38: =[1]IFE!C109 -> 0.8 | D38: =[1]IFE!D109 -> 0.8 | E38: =[1]IFE!E109 -> 0 | F38: =[1]IFE!F109 -> 0 | G38: =[1]IFE!$B222 -> DERRICK SHAKER 3 | I38: =[1]IFE!$C222 -> 2X100 - 2X140 | J38: =[1]IFE!$D222 -> 0
A39: Pf/Mf | B39: =[1]IFE!D31 -> 0 | C39: =CONCATENATE(TEXT([1]IFE!C110,"#.00"),"/",TEXT([1]IFE!C111,"#.00")) -> .20/.60 | D39: =CONCATENATE(TEXT([1]IFE!D110,"#.00"),"/",TEXT([1]IFE!D111,"#.00")) -> .20/.60 | E39: =CONCATENATE(TEXT([1]IFE!E110,"#.00")&"/"&TEXT([1]IFE!E111,"#.00")) -> .00/.00 | F39: =CONCATENATE(TEXT([1]IFE!F110,"#.00")&"/"&TEXT([1]IFE!F111,"#.00")) -> .00/.00 | G39: =[1]IFE!$B223 -> MOD 312 / 10T2 w/o pump | I39: =[1]IFE!$C223 -> 4 X 200 | J39: =[1]IFE!$D223 -> 0
A40: Chlorides | B40: =[1]IFE!D58 -> mg/L | C40: =[1]IFE!C112 -> 0 | D40: =[1]IFE!D112 -> 0 | E40: =[1]IFE!E112 -> 0 | F40: =[1]IFE!F112 -> 0 | G40: =[1]IFE!$B224 -> 0 | I40: =[1]IFE!$C224 -> 0 | J40: =[1]IFE!$D224 -> 0
A41: Hardness (Ca++) | C41: =[1]IFE!C113 -> 80 | D41: =[1]IFE!D113 -> 80 | E41: =[1]IFE!E113 -> 0 | F41: =[1]IFE!F113 -> 0 | G41: =[1]IFE!$B225 -> 0 | I41: =[1]IFE!$C225 -> 0 | J41: =[1]IFE!$D225 -> 0
A42: =[1]IFE!A114 -> 0 | B42: =[1]IFE!I114 -> 0 | C42: =[1]IFE!C114 -> 0 | D42: =[1]IFE!D114 -> 0 | E42: =[1]IFE!E114 -> 0 | F42: =[1]IFE!F114 -> 0 | G42: =[1]IFE!$B226 -> 0 | I42: =[1]IFE!$C226 -> 0 | J42: =[1]IFE!$D226 -> 0
A43: =[1]IFE!A115 -> 0 | B43: =[1]IFE!I115 -> 0 | C43: =[1]IFE!C115 -> 0 | D43: =[1]IFE!D115 -> 0 | E43: =[1]IFE!E115 -> 0 | F43: =[1]IFE!F115 -> 0 | G43: =[1]IFE!$B227 -> 0 | I43: =[1]IFE!$C227 -> 0 | J43: =[1]IFE!$D227 -> 0
A44: =[1]IFE!A116 -> 0 | B44: =[1]IFE!I116 -> 0 | C44: =[1]IFE!C116 -> 0 | D44: =[1]IFE!D116 -> 0 | E44: =[1]IFE!E116 -> 0 | F44: =[1]IFE!F116 -> 0 | G44: =[1]IFE!$B228 -> 0 | I44: =[1]IFE!$C228 -> 0 | J44: =[1]IFE!$D228 -> 0
A45: =[1]IFE!A117 -> 0 | B45: =[1]IFE!I117 -> 0 | C45: =[1]IFE!C117 -> 0 | D45: =[1]IFE!D117 -> 0 | E45: =[1]IFE!E117 -> 0 | F45: =[1]IFE!F117 -> 0 | G45: =[1]IFE!$B229 -> 0 | I45: =[1]IFE!$C229 -> 0 | J45: =[1]IFE!$D229 -> 0
A46: =[1]IFE!G382 -> 0 | B46: =[1]IFE!H382 -> 0 | C46: =[1]IFE!A382 -> 0 | D46: =[1]IFE!B382 -> 0 | E46: =[1]IFE!C382 -> 0 | F46: =[1]IFE!D382 -> 0 | G46: =[1]IFE!$G220 -> 0 | I46: =[1]IFE!$H220 -> 0 | J46: =[1]IFE!$I220 -> 0
A47: =[1]IFE!G383 -> 0 | B47: =[1]IFE!H383 -> 0 | C47: =[1]IFE!A383 -> 0 | D47: =[1]IFE!B383 -> 0 | E47: =[1]IFE!C383 -> 0 | F47: =[1]IFE!D383 -> 0 | G47: MUD PROPERTY SPECS | J47: Actual
A48: =[1]IFE!G384 -> 0 | B48: =[1]IFE!H384 -> 0 | C48: =[1]IFE!A384 -> 0 | D48: =[1]IFE!B384 -> 0 | E48: =[1]IFE!C384 -> 0 | F48: =[1]IFE!D384 -> 0 | G48: Weight | H48: =[1]IFE!B153 -> 9,1 | J48: =[1]IFE!C82 -> 9.1
A49: =[1]IFE!G385 -> 0 | B49: =[1]IFE!H385 -> 0 | C49: =[1]IFE!A385 -> 0 | D49: =[1]IFE!B385 -> 0 | E49: =[1]IFE!C385 -> 0 | F49: =[1]IFE!D385 -> 0 | G49: Viscosity | H49: =[1]IFE!B154 -> 55 | J49: =[1]IFE!C84 -> 55
A50: Reserve Volume | B50: =[1]IFE!$B$32 -> bbl | C50: =[1]IFE!$BH$210+[1]IFE!$BH$211 -> 1418 | G50: Filtrate | H50: =[1]IFE!B155 -> 0 | J50: =[1]IFE!C97 -> 0
A51: REMARKS AND TREATMENT | E51: REMARKS
A52: =[1]IFE!B157 -> Realizó chequeo a fluido y ajustó viscosidad. no se logro recibir barita debido a que el mal tiempo no permitio que el barco se pegara al equipo y luego debió volver a muelle. Actualmente esperando el barco con Barita. Realizó correccion de presentacion del producto DUOVIS, ya que el mismo estaba reportado de 50 libras y el usado es de 25 kg. | E52: =[1]IFE!B158 -> Terminó de instalar equipo de pozo, probo el mismo OK. bajo sarta de perforacion hasta tope de cemento, probó equipo ok.
A53: TIME DISTRIBUTION Last 24 hrs | C53: ="MUD VOL ACCTG " &"("&[1]IFE!B32&")" -> MUD VOL ACCTG (bbl) | E53: ="SOILDS ANALYSIS" -> SOILDS ANALYSIS | H53: RHEOLOGY & HYDRAULICS
A54: =[1]IFE!B270 -> Armado / Mantenimiento | B54: =[1]IFE!C270 -> 0 | C54: Oil Added | D54: =[1]IFE!$E$331 -> 0 | E54: ="Calcium Chloride " &"("&[1]IFE!B44&")" -> Calcium Chloride (lb/bbl) | G54: =[1]IFE!$A$404 -> 0, | H54: np/na | J54: =[1]IFE!B243 -> 0
A55: =[1]IFE!B271 -> Perforación | B55: =[1]IFE!C271 -> 0 | C55: Water Added | D55: =[1]IFE!$E$332 -> 0 | E55: Calcium Chloride (wt %) | G55: =[1]IFE!$A$405 -> 0, | H55: Kp/Ka | J55: =[1]IFE!B244 -> 0
A56: =[1]IFE!B272 -> Viajes | B56: =[1]IFE!C272 -> 0 | C56: Mud Received | D56: =[1]IFE!$E$336 -> 0 | E56: Brine Specific Gravity | G56: =[1]IFE!$A$406 -> 0, | H56: Bit Pressure Loss % | J56: =[1]IFE!B245 -> 0
A57: =[1]IFE!B273 -> Tiempo No Productivo | B57: =[1]IFE!C273 -> 0 | C57: Mud Returned | D57: =[1]IFE!$E$337 -> 0 | E57: Corrected Solids (%) | G57: =[1]IFE!$A$407 -> 0, | H57: Bit HHP/HSI | J57: =[1]IFE!B246 -> 0
A58: =[1]IFE!B274 -> 0 | B58: =[1]IFE!C274 -> 0 | C58: =[1]IFE!$A$261 -> Shakers | D58: =[1]IFE!$B$261 -> 0 | E58: Average SG of Solids | G58: =[1]IFE!$A$408 -> 2,3 | H58: Jet Velocity | J58: =[1]IFE!B247 -> 0
A59: =[1]IFE!B275 -> 0 | B59: =[1]IFE!C275 -> 0 | C59: =[1]IFE!$A$262 -> Evaporation | D59: =[1]IFE!$B$262 -> 0 | E59: Low Gravity Solids (%) | G59: =[1]IFE!$A$409 -> 20,6 | H59: Va Pipe | J59: =[1]IFE!B248 -> 0
A60: =[1]IFE!B276 -> 0 | B60: =[1]IFE!C276 -> 0 | C60: =[1]IFE!$A$263 -> Centrifuge | D60: =[1]IFE!$B$263 -> 0 | E60: ="Low Gravity Solids " &"("&[1]IFE!B44&")" -> Low Gravity Solids (lb/bbl) | G60: =[1]IFE!$A$410 -> 2,2 | H60: Va Collars | J60: =[1]IFE!B249 -> 0
A61: =[1]IFE!B277 -> 0 | B61: =[1]IFE!C277 -> 0 | C61: =[1]IFE!$A$264 -> Formation | D61: =[1]IFE!$B$264 -> 0 | E61: High Gravity Solids (%) | G61: =[1]IFE!$A$411 -> 20, | H61: Cva Pipe | J61: =[1]IFE!B250 -> 0
A62: =[1]IFE!B278 -> 0 | B62: =[1]IFE!C278 -> 0 | C62: =[1]IFE!$A$265 -> Left in Hole | D62: =[1]IFE!$B$265 -> 0 | E62: ="High Gravity Solids " &"("&[1]IFE!B44&")" -> High Gravity Solids (lb/bbl) | G62: =[1]IFE!$A$412 -> 0, | H62: Cva Collars | J62: =[1]IFE!B251 -> 0
A63: =[1]IFE!B279 -> 0 | B63: =[1]IFE!C279 -> 0 | C63: =[1]IFE!$A$266 -> Other | D63: =[1]IFE!$B$266 -> 0 | H63: ECD at Shoe | J63: =[1]IFE!B252 -> 0
C64: =[1]IFE!$A$267 -> Discharged | D64: =[1]IFE!$B$267 -> 0 | H64: ECD at TD | J64: =[1]IFE!B253 -> 0
C65: =[1]IFE!$C$261 -> Pit Cleaning | D65: =[1]IFE!$D$261 -> 0
C66: =[1]IFE!$C$262 -> 0 | D66: =[1]IFE!$D$262 -> 0 | G66: DAILY COST | I66: CUMULATIVE COST
C67: =[1]IFE!$C$263 -> 0 | D67: =[1]IFE!$D$263 -> 0 | F67: Drlg Fluids | G67: =[1]IFE!$B$134 -> 5749.32 | I67: =[1]IFE!$B$135 -> 89939.53
A68: M-I ENGR / PHONE | C68: RIG PHONE | D68: WAREHOUSE PHONE | F68: S.R.E. & Engr. | G68: =[1]IFE!$D$138+[1]IFE!$D$142 -> 0 | I68: =[1]IFE!$D$139+[1]IFE!$D$143 -> 0
A69: =[1]IFE!$B$127 -> Jesus Villarroel | C69: =[1]IFE!$D$131 -> 0 | D69: =[1]IFE!$B$133 -> 0 | F69: Screens | G69: =[1]IFE!$D$136 -> 0 | I69: =[1]IFE!$D$137 -> 0
A70: =[1]IFE!$B$129 -> 0 | F70: TOTALS | G70: =SUM(G67:H69) -> 5749.32 | I70: =SUM(I67:J69) -> 89939.53

Sheet Synthetic-Based Mud
J2: ="SYNTHETIC-BASED MUD REPORT No. "&[1]IFE!B166&" " -> SYNTHETIC-BASED MUD REPORT No. 9
A3: Operator : | B3: =[1]IFE!B6 -> Cardon IV | D3: Field/Area : | E3: =[1]IFE!B9 -> Golfo de Venezuela | H3: Depth/TVD : | I3: =[1]IFE!B120&" "&[1]IFE!B30&" /" -> 563 pies / | J3: =[1]IFE!B121&" "&[1]IFE!B30 -> 563 pies
A4: Report For : | B4: =[1]IFE!B125 -> Gerrit Ham / Jhony Quintero | D4: Description : | E4: =[1]IFE!B10 -> Exploratory | H4: Date : | I4: =[1]IFE!B119 -> 39989
A5: Well Name : | B5: =[1]IFE!B8 -> Perla-1X | D5: Location : | E5: =[1]IFE!B11 -> Offshore | H5: Spud Date : | I5: =[1]IFE!B5 -> 39981
A6: Contractor: | B6: =[1]IFE!B15 -> Ensco | D6: Water Depth : | E6: =[1]IFE!B16&" "&[1]IFE!B30 -> 202 pies | H6: Mud Type : | I6: =[1]IFE!B124 -> Agua de mar / HI VIS
A7: Report For : | B7: =[1]IFE!B126 -> Ricky Otwell | D7: Rig Name : | E7: =[1]IFE!Z981 -> 68 | H7: Activity : | I7: =[1]IFE!B123 -> Bajando Tuberia
A8: DRILLING ASSEMBLY | C8: CASING (*TVD) | E8: ="MUD VOLUME" & " ("& [1]IFE!B32&")" -> MUD VOLUME (bbl) | G8: CIRCULATION DATA
A9: =[1]IFE!B167 -> pies, 5.5-plg DP | C9: =[1]IFE!B173 -> 30.-plg @563 pies (563 TVD) | E9: Hole | F9: Active Pits | H9: Pump Make | I9: =[1]IFE!B161 -> NATIONAL 12P-160 | J9: =[1]IFE!B162 -> NATIONAL 12P-160
A10: =[1]IFE!B168 -> 372 pies, 5.5-plg HWDP | C10: =[1]IFE!B174 -> 0 | E10: =[1]IFE!B177 -> 429 | F10: =[1]IFE!B178 -> 0 | H10: Pump Liner x Stk | I10: =[1]IFE!C161&"x"&[1]IFE!D161&" "&[1]IFE!B31 -> 6,5x12 plg | J10: =[1]IFE!C162&"x"&[1]IFE!D162&" "&[1]IFE!B31 -> 6,5x12 plg
A11: =[1]IFE!B169 -> 65 pies, 8.-plg DC | C11: =[1]IFE!B175 -> 0 | E11: Total Circulating Volume | H11: ="Pump Capacity "&[1]IFE!B57 -> Pump Capacity gal/emb | I11: =[1]IFE!B182 -> 5.016 | J11: =[1]IFE!B183 -> 5.016
A12: =[1]IFE!B170 -> 34 pies, 8.-plg JAR | C12: =[1]IFE!B176 -> 0 | E12: =[1]IFE!$B$179 -> 0 | H12: Pump stk/min | I12: =[1]IFE!G161&"@"&[1]IFE!F161&"%" -> 0@97% | J12: =[1]IFE!G162&"@"&[1]IFE!F162&"%" -> 0@97%
A13: =[1]IFE!B171 -> 96 pies, 8.-plg DC | C13: =[1]IFE!D173 -> 0 | E13: Depth Drilled Last 24hr | H13: Flow Rate | I13: =[1]IFE!B150 -> 0 | J13: =[1]IFE!B33 -> gal/min
A14: =[1]IFE!B172 -> 31 pies, 9.5-plg DC | C14: =[1]IFE!D174 -> 0 | E14: =[1]IFE!$BE$86 -> 0 | F14: =[1]IFE!$B$30 -> pies | H14: Pump Pressure | I14: =[1]IFE!B152 -> 0 | J14: =[1]IFE!B36 -> psi
A15: ="Nozzles "&[1]IFE!B139&IF([1]IFE!B142=0,"","x"&[1]IFE!B142)&IF([1]IFE!B140=0,"","/"&[1]IFE!B140&IF([1]IFE!B143=0,"","x"&[1]IFE!B143))&IF([1]IFE!B141=0,"", "/"&[1]IFE!B141&IF([1]IFE!B144=0,"","x"&[1]IFE!B144))&" "&[1]IFE!B34 -> Nozzles 0 1/32 plg | C15: =[1]IFE!D175 -> 0 | E15: Volume Drilled Last 24hr | H15: Bottoms Up | I15: =[1]IFE!B186 -> 0
A16: ="Bit "&[1]IFE!B136 & "-" & [1]IFE!B31&" "&[1]IFE!B137 -> Bit 26-plg 0 | C16: =[1]IFE!D176 -> 0 | E16: =[1]IFE!$D$148 -> 0 | F16: =[1]IFE!$B$32 -> bbl | H16: Total Circulation | I16: =[1]IFE!B187 -> 0
A17: MUD PROPERTIES | G17: PRODUCTS USED Last 24 hr
A18: Sample From | C18: =CONCATENATE(TEXT([1]IFE!C77," ")&" "&TEXT([1]IFE!C78,"H:MM")) -> TK 1 12:00 | D18: =CONCATENATE(TEXT([1]IFE!D77," ")&" "&TEXT([1]IFE!D78,"H:MM")) -> 0:00 | E18: =CONCATENATE(TEXT([1]IFE!E77," ")&" "&TEXT([1]IFE!E78,"H:MM")) -> TK 3 12:00 | F18: =CONCATENATE(TEXT([1]IFE!F77," ")&" "&TEXT([1]IFE!F78,"H:MM")) -> TK 3 0:00 | G18: Products | I18: Size | J18: Amount
A19: FlowLine Temp | B19: =[1]IFE!B40 -> °F | C19: =[1]IFE!C79 -> 0 | D19: =[1]IFE!D79 -> 0 | E19: =[1]IFE!E79 -> 0 | F19: =[1]IFE!F79 -> 0 | G19: =[1]IFE!B313 -> ENGINEERING SERVICE | I19: =[1]IFE!C313 -> 1. EA | J19: =[1]IFE!D313 -> 2
A20: Depth/TVD | B20: =[1]IFE!B30 -> pies | C20: =CONCATENATE(TEXT([1]IFE!C80,"#")&"/"&TEXT([1]IFE!C81,"#")) -> 563/563 | D20: =CONCATENATE(TEXT([1]IFE!D80,"#")&"/"&TEXT([1]IFE!D81,"#")) -> 563/563 | E20: =CONCATENATE(TEXT([1]IFE!E80,"#")&"/"&TEXT([1]IFE!E81,"#")) -> 563/563 | F20: =CONCATENATE(TEXT([1]IFE!F80,"#")&"/"&TEXT([1]IFE!F81,"#")) -> 563/563 | G20: =[1]IFE!B314 -> BENTONITE WYOMING | I20: =[1]IFE!C314 -> 100. LB BG | J20: =[1]IFE!D314 -> 1
A21: Mud Weight | B21: =[1]IFE!B39 -> lb/gal | C21: =CONCATENATE(TEXT([1]IFE!C82,"#.0")&"@"&TEXT([1]IFE!C83,"#")) -> 9.1@85 | D21: =CONCATENATE(TEXT([1]IFE!D82,"#.0")&"@"&TEXT([1]IFE!D83,"#")) -> 9.1@85 | E21: =CONCATENATE(TEXT([1]IFE!E82,"#.0")&"@"&TEXT([1]IFE!E83,"#")) -> 14.0@85 | F21: =CONCATENATE(TEXT([1]IFE!F82,"#.0")&"@"&TEXT([1]IFE!F83,"#")) -> 14.0@85 | G21: =[1]IFE!B315 -> DUO-VIS | I21: =[1]IFE!C315 -> 25. KG BG | J21: =[1]IFE!D315 -> 5
A22: Funnel Viscosity | B22: =[1]IFE!B43 -> s/ct | C22: =[1]IFE!C84 -> 55 | D22: =[1]IFE!D84 -> 55 | E22: =[1]IFE!E84 -> 80 | F22: =[1]IFE!F84 -> 80 | G22: =[1]IFE!B316 -> 0 | I22: =[1]IFE!C316 -> 0 | J22: =[1]IFE!D316 -> 0
A23: Rheology Temp | B23: =[1]IFE!B40 -> °F | C23: =[1]IFE!C85 -> 120 | D23: =[1]IFE!D85 -> 120 | E23: =[1]IFE!E85 -> 120 | F23: =[1]IFE!F85 -> 120 | G23: =[1]IFE!B317 -> 0 | I23: =[1]IFE!C317 -> 0 | J23: =[1]IFE!D317 -> 0
A24: R600/R300 | C24: =CONCATENATE(TEXT([1]IFE!C86,"#")&"/"&TEXT([1]IFE!C87,"#")) -> 38/27 | D24: =CONCATENATE(TEXT([1]IFE!D86,"#")&"/"&TEXT([1]IFE!D87,"#")) -> 38/27 | E24: =CONCATENATE(TEXT([1]IFE!E86,"#")&"/"&TEXT([1]IFE!E87,"#")) -> 130/81 | F24: =CONCATENATE(TEXT([1]IFE!F86,"#")&"/"&TEXT([1]IFE!F87,"#")) -> 130/81 | G24: =[1]IFE!B318 -> 0 | I24: =[1]IFE!C318 -> 0 | J24: =[1]IFE!D318 -> 0
A25: R200/R100 | C25: =CONCATENATE(TEXT([1]IFE!C88,"#")&"/"&TEXT([1]IFE!C89,"#")) -> 23/18 | D25: =CONCATENATE(TEXT([1]IFE!D88,"#")&"/"&TEXT([1]IFE!D89,"#")) -> 23/18 | E25: =CONCATENATE(TEXT([1]IFE!E88,"#")&"/"&TEXT([1]IFE!E89,"#")) -> 61/39 | F25: =CONCATENATE(TEXT([1]IFE!F88,"#")&"/"&TEXT([1]IFE!F89,"#")) -> 61/39 | G25: =[1]IFE!B319 -> 0 | I25: =[1]IFE!C319 -> 0 | J25: =[1]IFE!D319 -> 0
A26: R6/R3 | C26: =CONCATENATE(TEXT([1]IFE!C90,"#")&"/"&TEXT([1]IFE!C91,"#")) -> 11/10 | D26: =CONCATENATE(TEXT([1]IFE!D90,"#")&"/"&TEXT([1]IFE!D91,"#")) -> 11/10 | E26: =CONCATENATE(TEXT([1]IFE!E90,"#")&"/"&TEXT([1]IFE!E91,"#")) -> 10/8 | F26: =CONCATENATE(TEXT([1]IFE!F90,"#")&"/"&TEXT([1]IFE!F91,"#")) -> 10/8 | G26: =[1]IFE!B320 -> 0 | I26: =[1]IFE!C320 -> 0 | J26: =[1]IFE!D320 -> 0
A27: PV | B27: =[1]IFE!B41 -> cP | C27: =[1]IFE!C92 -> 11 | D27: =[1]IFE!D92 -> 11 | E27: =[1]IFE!E92 -> 49 | F27: =[1]IFE!F92 -> 49 | G27: =[1]IFE!B321 -> 0 | I27: =[1]IFE!C321 -> 0 | J27: =[1]IFE!D321 -> 0
A28: YP | B28: =[1]IFE!B42 -> lb/100p² | C28: =[1]IFE!C93 -> 16 | D28: =[1]IFE!D93 -> 16 | E28: =[1]IFE!E93 -> 32 | F28: =[1]IFE!F93 -> 32 | G28: =[1]IFE!B322 -> 0 | I28: =[1]IFE!C322 -> 0 | J28: =[1]IFE!D322 -> 0
A29: 10s/10m/30m Gel | B29: =[1]IFE!B42 -> lb/100p² | C29: =CONCATENATE(TEXT([1]IFE!C94,"#")&"/"&(TEXT([1]IFE!C95,"#")&"/"&TEXT([1]IFE!C96,"#"))) -> 11/15/ | D29: =CONCATENATE(TEXT([1]IFE!D94,"#")&"/"&(TEXT([1]IFE!D95,"#")&"/"&TEXT([1]IFE!D96,"#"))) -> 11/15/ | E29: =CONCATENATE(TEXT([1]IFE!E94,"#")&"/"&(TEXT([1]IFE!E95,"#")&"/"&TEXT([1]IFE!E96,"#"))) -> 12/18/ | F29: =CONCATENATE(TEXT([1]IFE!F94,"#")&"/"&(TEXT([1]IFE!F95,"#")&"/"&TEXT([1]IFE!F96,"#"))) -> 12/18/ | G29: =[1]IFE!B323 -> 0 | I29: =[1]IFE!C323 -> 0 | J29: =[1]IFE!D323 -> 0
A30: API Fluid Loss | B30: =[1]IFE!D57 -> cc/30min | C30: =[1]IFE!C97 -> 0 | D30: =[1]IFE!D97 -> 0 | E30: =[1]IFE!E97 -> 0 | F30: =[1]IFE!F97 -> 0 | G30: =[1]IFE!B324 -> 0 | I30: =[1]IFE!C324 -> 0 | J30: =[1]IFE!D324 -> 0
A31: HTHP Fluid Loss | B31: =[1]IFE!D57 -> cc/30min | C31: =CONCATENATE(TEXT([1]IFE!C98,"#.0")&"@"&TEXT([1]IFE!C99,"#")) -> .0@ | D31: =CONCATENATE(TEXT([1]IFE!D98,"#.0")&"@"&TEXT([1]IFE!D99,"#")) -> .0@ | E31: =CONCATENATE(TEXT([1]IFE!E98,"#.0")&"@"&TEXT([1]IFE!E99,"#")) -> .0@ | F31: =CONCATENATE(TEXT([1]IFE!F98,"#.0")&"@"&TEXT([1]IFE!F99,"#")) -> .0@ | G31: =[1]IFE!B325 -> 0 | I31: =[1]IFE!C325 -> 0 | J31: =[1]IFE!D325 -> 0
A32: Cake APT/HT | B32: =[1]IFE!B34 -> 1/32 plg | C32: =CONCATENATE(TEXT([1]IFE!C100,"#")&"/"&TEXT([1]IFE!C101,"#")) -> / | D32: =CONCATENATE(TEXT([1]IFE!D100,"#")&"/"&TEXT([1]IFE!D101,"#")) -> / | E32: =CONCATENATE(TEXT([1]IFE!E100,"#")&"/"&TEXT([1]IFE!E101,"#")) -> / | F32: =CONCATENATE(TEXT([1]IFE!F100,"#")&"/"&TEXT([1]IFE!F101,"#")) -> / | G32: =[1]IFE!B326 -> 0 | I32: =[1]IFE!C326 -> 0 | J32: =[1]IFE!D326 -> 0
A33: Unc Ret Solids | B33: =[1]IFE!D59 -> %Vol | C33: =[1]IFE!C102 -> 4.2 | D33: =[1]IFE!D102 -> 4.2 | E33: =[1]IFE!E102 -> 22 | F33: =[1]IFE!F102 -> 22 | G33: =[1]IFE!B327 -> 0 | I33: =[1]IFE!C327 -> 0 | J33: =[1]IFE!D327 -> 0
A34: Correct Solids | B34: =[1]IFE!D59 -> %Vol | C34: =[1]IFE!C103 -> 0 | D34: =[1]IFE!D103 -> 0 | E34: =[1]IFE!E103 -> 0 | F34: =[1]IFE!F103 -> 0 | G34: SOLIDS CONTROL EQUIPMENT Last 24 hr
A35: Synthetic | B35: =[1]IFE!D59 -> %Vol | C35: =[1]IFE!C104 -> 95.8 | D35: =[1]IFE!D104 -> 95.8 | E35: =[1]IFE!E104 -> 78 | F35: =[1]IFE!F104 -> 78 | G35: Type | I35: Model/Size | J35: Hrs Used
A36: Uncorr Water | B36: =[1]IFE!D59 -> %Vol | C36: =[1]IFE!C105 -> 0 | D36: =[1]IFE!D105 -> 0 | E36: =[1]IFE!E105 -> 0 | F36: =[1]IFE!F105 -> 0 | G36: =[1]IFE!$B220 -> DERRICK SHEKER 1 | I36: =[1]IFE!$C220 -> 2X100 - 2X140 | J36: =[1]IFE!$D220 -> 0
A37: Synthetic/Water Ratio | C37: =CONCATENATE(TEXT([1]IFE!C106,"#")&"/"&TEXT([1]IFE!C107,"#")) -> 20/10 | D37: =CONCATENATE(TEXT([1]IFE!D106,"#")&"/"&TEXT([1]IFE!D107,"#")) -> 20/10 | E37: =CONCATENATE(TEXT([1]IFE!E106,"#")&"/"&TEXT([1]IFE!E107,"#")) -> 15/11 | F37: =CONCATENATE(TEXT([1]IFE!F106,"#")&"/"&TEXT([1]IFE!F107,"#")) -> 15/11 | G37: =[1]IFE!$B221 -> DERRICK SHAKER 2 | I37: =[1]IFE!$C221 -> 2X100 - 2X140 | J37: =[1]IFE!$D221 -> 0
A38: Alkal Mud (Psm) | C38: =[1]IFE!C108 -> 85 | D38: =[1]IFE!D108 -> 85 | E38: =[1]IFE!E108 -> 85 | F38: =[1]IFE!F108 -> 85 | G38: =[1]IFE!$B222 -> DERRICK SHAKER 3 | I38: =[1]IFE!$C222 -> 2X100 - 2X140 | J38: =[1]IFE!$D222 -> 0
A39: Cl- Whole Mud | B39: =[1]IFE!D58 -> mg/L | C39: =[1]IFE!C109 -> 0.8 | D39: =[1]IFE!D109 -> 0.8 | E39: =[1]IFE!E109 -> 0 | F39: =[1]IFE!F109 -> 0 | G39: =[1]IFE!$B223 -> MOD 312 / 10T2 w/o pump | I39: =[1]IFE!$C223 -> 4 X 200 | J39: =[1]IFE!$D223 -> 0
A40: Salt | B40: =[1]IFE!D60 -> %Wt | C40: =[1]IFE!C110 -> 0.2 | D40: =[1]IFE!D110 -> 0.2 | E40: =[1]IFE!E110 -> 0 | F40: =[1]IFE!F110 -> 0 | G40: =[1]IFE!$B224 -> 0 | I40: =[1]IFE!$C224 -> 0 | J40: =[1]IFE!$D224 -> 0
A41: Lime | B41: =[1]IFE!B44 -> lb/bbl | C41: =[1]IFE!C111 -> 0.6 | D41: =[1]IFE!D111 -> 0.6 | E41: =[1]IFE!E111 -> 0 | F41: =[1]IFE!F111 -> 0 | G41: =[1]IFE!$B225 -> 0 | I41: =[1]IFE!$C225 -> 0 | J41: =[1]IFE!$D225 -> 0
A42: Emul Stability | C42: =[1]IFE!C112 -> 0 | D42: =[1]IFE!D112 -> 0 | E42: =[1]IFE!E112 -> 0 | F42: =[1]IFE!F112 -> 0 | G42: =[1]IFE!$B226 -> 0 | I42: =[1]IFE!$C226 -> 0 | J42: =[1]IFE!$D226 -> 0
A43: =[1]IFE!B114 -> 0 | B43: =[1]IFE!J114 -> 0 | C43: =[1]IFE!C114 -> 0 | D43: =[1]IFE!D114 -> 0 | E43: =[1]IFE!E114 -> 0 | F43: =[1]IFE!F114 -> 0 | G43: =[1]IFE!$B227 -> 0 | I43: =[1]IFE!$C227 -> 0 | J43: =[1]IFE!$D227 -> 0
A44: =[1]IFE!B115 -> 0 | B44: =[1]IFE!J115 -> 0 | C44: =[1]IFE!C115 -> 0 | D44: =[1]IFE!D115 -> 0 | E44: =[1]IFE!E115 -> 0 | F44: =[1]IFE!F115 -> 0 | G44: =[1]IFE!$B228 -> 0 | I44: =[1]IFE!$C228 -> 0 | J44: =[1]IFE!$D228 -> 0
A45: =[1]IFE!B116 -> 0 | B45: =[1]IFE!J116 -> 0 | C45: =[1]IFE!C116 -> 0 | D45: =[1]IFE!D116 -> 0 | E45: =[1]IFE!E116 -> 0 | F45: =[1]IFE!F116 -> 0 | G45: =[1]IFE!$B229 -> 0 | I45: =[1]IFE!$C229 -> 0 | J45: =[1]IFE!$D229 -> 0
A46: =[1]IFE!B117 -> 0 | B46: =[1]IFE!J117 -> 0 | C46: =[1]IFE!C117 -> 0 | D46: =[1]IFE!D117 -> 0 | E46: =[1]IFE!E117 -> 0 | F46: =[1]IFE!F117 -> 0 | G46: =[1]IFE!$G220 -> 0 | I46: =[1]IFE!$H220 -> 0 | J46: =[1]IFE!$I220 -> 0
A47: =[1]IFE!I382 -> 0 | B47: =[1]IFE!J382 -> 0 | C47: =[1]IFE!A382 -> 0 | D47: =[1]IFE!B382 -> 0 | E47: =[1]IFE!C382 -> 0 | F47: =[1]IFE!D382 -> 0 | G47: MUD PROPERTY SPECS | J47: Actual
A48: =[1]IFE!I383 -> 0 | B48: =[1]IFE!J383 -> 0 | C48: =[1]IFE!A383 -> 0 | D48: =[1]IFE!B383 -> 0 | E48: =[1]IFE!C383 -> 0 | F48: =[1]IFE!D383 -> 0 | G48: Weight | H48: =[1]IFE!B153 -> 9,1 | J48: =[1]IFE!C82 -> 9.1
A49: =[1]IFE!I384 -> 0 | B49: =[1]IFE!J384 -> 0 | C49: =[1]IFE!A384 -> 0 | D49: =[1]IFE!B384 -> 0 | E49: =[1]IFE!C384 -> 0 | F49: =[1]IFE!D384 -> 0 | G49: Viscosity | H49: =[1]IFE!B154 -> 55 | J49: =[1]IFE!C84 -> 55
A50: =[1]IFE!I385 -> 0 | B50: =[1]IFE!J385 -> 0 | C50: =[1]IFE!A385 -> 0 | D50: =[1]IFE!B385 -> 0 | E50: =[1]IFE!C385 -> 0 | F50: =[1]IFE!D385 -> 0 | G50: Filtrate | H50: =[1]IFE!B155 -> 0 | J50: =[1]IFE!C98 -> 0
A51: Reserve Volume | B51: =[1]IFE!$B$32 -> bbl | C51: =[1]IFE!$BH$210+[1]IFE!$BH$211 -> 1418
A52: REMARKS AND TREATMENT | E52: REMARKS
A53: =[1]IFE!B157 -> Realizó chequeo a fluido y ajustó viscosidad. no se logro recibir barita debido a que el mal tiempo no permitio que el barco se pegara al equipo y luego debió volver a muelle. Actualmente esperando el barco con Barita. Realizó correccion de presentacion del producto DUOVIS, ya que el mismo estaba reportado de 50 libras y el usado es de 25 kg. | E53: =[1]IFE!B158 -> Terminó de instalar equipo de pozo, probo el mismo OK. bajo sarta de perforacion hasta tope de cemento, probó equipo ok.
A54: TIME DISTRIBUTION Last 24 hrs | C54: ="MUD VOL ACCTG " &"("&[1]IFE!B32&")" -> MUD VOL ACCTG (bbl) | E54: SOLIDS ANALYSIS | H54: RHEOLOGY & HYDRAULICS
A55: =[1]IFE!B270 -> Armado / Mantenimiento | B55: =[1]IFE!C270 -> 0 | C55: Synthetic Added | D55: =[1]IFE!$E$331 -> 0 | E55: Salt Wt% | G55: =[1]IFE!C202 -> 0,/ 0, | H55: np/na | J55: =[1]IFE!B243 -> 0
A56: =[1]IFE!B271 -> Perforación | B56: =[1]IFE!C271 -> 0 | C56: Water Added | D56: =[1]IFE!$E$332 -> 0 | E56: Salt Conc | G56: =[1]IFE!C203 -> 0,/ 0, | H56: Kp/Ka | J56: =[1]IFE!B244 -> 0
A57: =[1]IFE!B272 -> Viajes | B57: =[1]IFE!C272 -> 0 | C57: Mud Received | D57: =[1]IFE!$E$336 -> 0 | E57: Adjusted Solids | G57: =[1]IFE!C204 -> 2,3/ 20,6 | H57: Bit Pressure Loss/% | J57: =[1]IFE!B245 -> 0
A58: =[1]IFE!B273 -> Tiempo No Productivo | B58: =[1]IFE!C273 -> 0 | C58: Mud Returned | D58: =[1]IFE!$E$337 -> 0 | E58: Synthetic/Water Ratio | G58: =[1]IFE!C205 -> 2,2/ 20, | H58: Bit HHP/HSI | J58: =[1]IFE!B246 -> 0
A59: =[1]IFE!B274 -> 0 | B59: =[1]IFE!C274 -> 0 | C59: =[1]IFE!$A$261 -> Shakers | D59: =[1]IFE!$B$261 -> 0 | E59: Average SG Solids | G59: =[1]IFE!C206 -> 0,/ 0, | H59: Jet Velocity | J59: =[1]IFE!B247 -> 0
A60: =[1]IFE!B275 -> 0 | B60: =[1]IFE!C275 -> 0 | C60: =[1]IFE!$A$262 -> Evaporation | D60: =[1]IFE!$B$262 -> 0 | E60: Low Gravity % | G60: =[1]IFE!C207 -> 1,9/ 28,9 | H60: Va Pipe | J60: =[1]IFE!B248 -> 0
A61: =[1]IFE!B276 -> 0 | B61: =[1]IFE!C276 -> 0 | C61: =[1]IFE!$A$263 -> Centrifuge | D61: =[1]IFE!$B$263 -> 0 | E61: Low Gravity Wt. | G61: =[1]IFE!C208 -> - / 0,6 | H61: Va Collars | J61: =[1]IFE!B249 -> 0
A62: =[1]IFE!B277 -> 0 | B62: =[1]IFE!C277 -> 0 | C62: =[1]IFE!$A$264 -> Formation | D62: =[1]IFE!$B$264 -> 0 | E62: High Gravity % | G62: =[1]IFE!C209 -> -0,0019 | H62: Cva Pipe | J62: =[1]IFE!B250 -> 0
A63: =[1]IFE!B278 -> 0 | B63: =[1]IFE!C278 -> 0 | C63: =[1]IFE!$A$265 -> Left in Hole | D63: =[1]IFE!$B$265 -> 0 | E63: High Gravity Wt. | G63: =[1]IFE!C210 -> 3,2 | H63: Cva Collars | J63: =[1]IFE!B251 -> 0
A64: =[1]IFE!B279 -> 0 | B64: =[1]IFE!C279 -> 0 | C64: =[1]IFE!$A$266 -> Other | D64: =[1]IFE!$B$266 -> 0 | E64: =[1]IFE!AD13 -> 0 | G64: =[1]IFE!C211 -> 0 | H64: ECD at Shoe | J64: =[1]IFE!B252 -> 0
C65: =[1]IFE!$A$267 -> Discharged | D65: =[1]IFE!$B$267 -> 0 | H65: ECD at TD | J65: =[1]IFE!B253 -> 0
C66: =[1]IFE!$C$261 -> Pit Cleaning | D66: =[1]IFE!$D$261 -> 0
C67: =[1]IFE!$C$262 -> 0 | D67: =[1]IFE!$D$262 -> 0 | G67: DAILY COST | I67: CUMULATIVE COST
C68: =[1]IFE!$C$263 -> 0 | D68: =[1]IFE!$D$263 -> 0 | F68: Drlg Fluids | G68: =[1]IFE!$B$134 -> 5749.32 | I68: =[1]IFE!$B$135 -> 89939.53
A69: M-I ENGR / PHONE | C69: RIG PHONE | D69: WAREHOUSE PHONE | F69: S.R.E. & Engr. | G69: =[1]IFE!$D$138+[1]IFE!$D$142 -> 0 | I69: =[1]IFE!$D$139+[1]IFE!$D$143 -> 0
A70: =[1]IFE!$B$127 -> Jesus Villarroel | C70: =[1]IFE!$D$131 -> 0 | D70: =[1]IFE!$B$133 -> 0 | F70: Screens | G70: =[1]IFE!$D$136 -> 0 | I70: =[1]IFE!$D$137 -> 0
A71: =[1]IFE!$B$129 -> 0 | F71: TOTALS | G71: =SUM(G68:H70) -> 5749.32 | I71: =SUM(I68:J70) -> 89939.53

Sheet OBM Check
J2: ="OIL-BASED MUD REPORT No. "&[1]IFE!B166&" " -> OIL-BASED MUD REPORT No. 9
A3: Operator : | B3: =[1]IFE!B6 -> Cardon IV | D3: Field/Area : | E3: =[1]IFE!B9 -> Golfo de Venezuela | H3: Depth/TVD : | I3: =[1]IFE!B120&" "&[1]IFE!B30&" /" -> 563 pies / | J3: =[1]IFE!B121&" "&[1]IFE!B30 -> 563 pies
A4: Report For : | B4: =[1]IFE!B125 -> Gerrit Ham / Jhony Quintero | D4: Description : | E4: =[1]IFE!B10 -> Exploratory | H4: Date : | I4: =[1]IFE!B119 -> 39989
A5: Well Name : | B5: =[1]IFE!B8 -> Perla-1X | D5: Location : | E5: =[1]IFE!B11 -> Offshore | H5: Spud Date : | I5: =[1]IFE!B5 -> 39981
A6: Contractor: | B6: =[1]IFE!B15 -> Ensco | D6: Water Depth : | E6: =[1]IFE!B16&" "&[1]IFE!B30 -> 202 pies | H6: Mud Type : | I6: =[1]IFE!B124 -> Agua de mar / HI VIS
A7: Report For : | B7: =[1]IFE!B126 -> Ricky Otwell | D7: Rig Name : | E7: =[1]IFE!Z981 -> 68 | H7: Activity : | I7: =[1]IFE!B123 -> Bajando Tuberia
A8: DRILLING ASSEMBLY | C8: CASING (*TVD) | E8: ="MUD VOLUME" & " ("& [1]IFE!B32&")" -> MUD VOLUME (bbl) | G8: CIRCULATION DATA
A9: =[1]IFE!B167 -> pies, 5.5-plg DP | C9: =[1]IFE!B173 -> 30.-plg @563 pies (563 TVD) | E9: Hole | F9: Active Pits | H9: Pump Make | I9: =[1]IFE!B161 -> NATIONAL 12P-160 | J9: =[1]IFE!B162 -> NATIONAL 12P-160
A10: =[1]IFE!B168 -> 372 pies, 5.5-plg HWDP | C10: =[1]IFE!B174 -> 0 | E10: =[1]IFE!B177 -> 429 | F10: =[1]IFE!B178 -> 0 | H10: Pump Liner x Stk | I10: =[1]IFE!C161&"x"&[1]IFE!D161&" "&[1]IFE!B31 -> 6,5x12 plg | J10: =[1]IFE!C162&"x"&[1]IFE!D162&" "&[1]IFE!B31 -> 6,5x12 plg
A11: =[1]IFE!B169 -> 65 pies, 8.-plg DC | C11: =[1]IFE!B175 -> 0 | E11: Total Circulating Volume | H11: ="Pump Capacity "&[1]IFE!B57 -> Pump Capacity gal/emb | I11: =[1]IFE!B182 -> 5.016 | J11: =[1]IFE!B183 -> 5.016
A12: =[1]IFE!B170 -> 34 pies, 8.-plg JAR | C12: =[1]IFE!B176 -> 0 | E12: =[1]IFE!$B$179 -> 0 | H12: Pump stk/min | I12: =[1]IFE!G161&"@"&[1]IFE!F161&"%" -> 0@97% | J12: =[1]IFE!G162&"@"&[1]IFE!F162&"%" -> 0@97%
A13: =[1]IFE!B171 -> 96 pies, 8.-plg DC | C13: =[1]IFE!D173 -> 0 | E13: Depth Drilled Last 24hr | H13: Flow Rate | I13: =[1]IFE!B150 -> 0 | J13: =[1]IFE!B33 -> gal/min
A14: =[1]IFE!B172 -> 31 pies, 9.5-plg DC | C14: =[1]IFE!D174 -> 0 | E14: =[1]IFE!$BE$86 -> 0 | F14: =[1]IFE!$B$30 -> pies | H14: Pump Pressure | I14: =[1]IFE!B152 -> 0 | J14: =[1]IFE!B36 -> psi
A15: ="Nozzles "&[1]IFE!B139&IF([1]IFE!B142=0,"","x"&[1]IFE!B142)&IF([1]IFE!B140=0,"","/"&[1]IFE!B140&IF([1]IFE!B143=0,"","x"&[1]IFE!B143))&IF([1]IFE!B141=0,"", "/"&[1]IFE!B141&IF([1]IFE!B144=0,"","x"&[1]IFE!B144))&" "&[1]IFE!B34 -> Nozzles 0 1/32 plg | C15: =[1]IFE!D175 -> 0 | E15: Volume Drilled Last 24hr | H15: Bottoms Up | I15: =[1]IFE!B186 -> 0
A16: ="Bit "&[1]IFE!B136 & "-" & [1]IFE!B31&" "&[1]IFE!B137 -> Bit 26-plg 0 | C16: =[1]IFE!D176 -> 0 | E16: =[1]IFE!$D$148 -> 0 | F16: =[1]IFE!$B$32 -> bbl | H16: Total Circulation | I16: =[1]IFE!B187 -> 0
A17: MUD PROPERTIES | G17: PRODUCTS USED Last 24 hr
A18: Sample From | C18: =CONCATENATE(TEXT([1]IFE!C77," ")&" "&TEXT([1]IFE!C78,"H:MM")) -> TK 1 12:00 | D18: =CONCATENATE(TEXT([1]IFE!D77," ")&" "&TEXT([1]IFE!D78,"H:MM")) -> 0:00 | E18: =CONCATENATE(TEXT([1]IFE!E77," ")&" "&TEXT([1]IFE!E78,"H:MM")) -> TK 3 12:00 | F18: =CONCATENATE(TEXT([1]IFE!F77," ")&" "&TEXT([1]IFE!F78,"H:MM")) -> TK 3 0:00 | G18: Products | I18: Size | J18: Amount
A19: FlowLine Temp | B19: =[1]IFE!B40 -> °F | C19: =[1]IFE!C79 -> 0 | D19: =[1]IFE!D79 -> 0 | E19: =[1]IFE!E79 -> 0 | F19: =[1]IFE!F79 -> 0 | G19: =[1]IFE!B313 -> ENGINEERING SERVICE | I19: =[1]IFE!C313 -> 1. EA | J19: =[1]IFE!D313 -> 2
A20: Depth/TVD | B20: =[1]IFE!B30 -> pies | C20: =CONCATENATE(TEXT([1]IFE!C80,"#")&"/"&TEXT([1]IFE!C81,"#")) -> 563/563 | D20: =CONCATENATE(TEXT([1]IFE!D80,"#")&"/"&TEXT([1]IFE!D81,"#")) -> 563/563 | E20: =CONCATENATE(TEXT([1]IFE!E80,"#")&"/"&TEXT([1]IFE!E81,"#")) -> 563/563 | F20: =CONCATENATE(TEXT([1]IFE!F80,"#")&"/"&TEXT([1]IFE!F81,"#")) -> 563/563 | G20: =[1]IFE!B314 -> BENTONITE WYOMING | I20: =[1]IFE!C314 -> 100. LB BG | J20: =[1]IFE!D314 -> 1
A21: Mud Weight | B21: =[1]IFE!B39 -> lb/gal | C21: =CONCATENATE(TEXT([1]IFE!C82,"#.0")&"@"&TEXT([1]IFE!C83,"#")) -> 9.1@85 | D21: =CONCATENATE(TEXT([1]IFE!D82,"#.0")&"@"&TEXT([1]IFE!D83,"#")) -> 9.1@85 | E21: =CONCATENATE(TEXT([1]IFE!E82,"#.0")&"@"&TEXT([1]IFE!E83,"#")) -> 14.0@85 | F21: =CONCATENATE(TEXT([1]IFE!F82,"#.0")&"@"&TEXT([1]IFE!F83,"#")) -> 14.0@85 | G21: =[1]IFE!B315 -> DUO-VIS | I21: =[1]IFE!C315 -> 25. KG BG | J21: =[1]IFE!D315 -> 5
A22: Funnel Viscosity | B22: =[1]IFE!B43 -> s/ct | C22: =[1]IFE!C84 -> 55 | D22: =[1]IFE!D84 -> 55 | E22: =[1]IFE!E84 -> 80 | F22: =[1]IFE!F84 -> 80 | G22: =[1]IFE!B316 -> 0 | I22: =[1]IFE!C316 -> 0 | J22: =[1]IFE!D316 -> 0
A23: Rheology Temp | B23: =[1]IFE!B40 -> °F | C23: =[1]IFE!C85 -> 120 | D23: =[1]IFE!D85 -> 120 | E23: =[1]IFE!E85 -> 120 | F23: =[1]IFE!F85 -> 120 | G23: =[1]IFE!B317 -> 0 | I23: =[1]IFE!C317 -> 0 | J23: =[1]IFE!D317 -> 0
A24: R600/R300 | C24: =CONCATENATE(TEXT([1]IFE!C86,"#")&"/"&TEXT([1]IFE!C87,"#")) -> 38/27 | D24: =CONCATENATE(TEXT([1]IFE!D86,"#")&"/"&TEXT([1]IFE!D87,"#")) -> 38/27 | E24: =CONCATENATE(TEXT([1]IFE!E86,"#")&"/"&TEXT([1]IFE!E87,"#")) -> 130/81 | F24: =CONCATENATE(TEXT([1]IFE!F86,"#")&"/"&TEXT([1]IFE!F87,"#")) -> 130/81 | G24: =[1]IFE!B318 -> 0 | I24: =[1]IFE!C318 -> 0 | J24: =[1]IFE!D318 -> 0
A25: R200/R100 | C25: =CONCATENATE(TEXT([1]IFE!C88,"#")&"/"&TEXT([1]IFE!C89,"#")) -> 23/18 | D25: =CONCATENATE(TEXT([1]IFE!D88,"#")&"/"&TEXT([1]IFE!D89,"#")) -> 23/18 | E25: =CONCATENATE(TEXT([1]IFE!E88,"#")&"/"&TEXT([1]IFE!E89,"#")) -> 61/39 | F25: =CONCATENATE(TEXT([1]IFE!F88,"#")&"/"&TEXT([1]IFE!F89,"#")) -> 61/39 | G25: =[1]IFE!B319 -> 0 | I25: =[1]IFE!C319 -> 0 | J25: =[1]IFE!D319 -> 0
A26: R6/R3 | C26: =CONCATENATE(TEXT([1]IFE!C90,"#")&"/"&TEXT([1]IFE!C91,"#")) -> 11/10 | D26: =CONCATENATE(TEXT([1]IFE!D90,"#")&"/"&TEXT([1]IFE!D91,"#")) -> 11/10 | E26: =CONCATENATE(TEXT([1]IFE!E90,"#")&"/"&TEXT([1]IFE!E91,"#")) -> 10/8 | F26: =CONCATENATE(TEXT([1]IFE!F90,"#")&"/"&TEXT([1]IFE!F91,"#")) -> 10/8 | G26: =[1]IFE!B320 -> 0 | I26: =[1]IFE!C320 -> 0 | J26: =[1]IFE!D320 -> 0
A27: PV | B27: =[1]IFE!B41 -> cP | C27: =[1]IFE!C92 -> 11 | D27: =[1]IFE!D92 -> 11 | E27: =[1]IFE!E92 -> 49 | F27: =[1]IFE!F92 -> 49 | G27: =[1]IFE!B321 -> 0 | I27: =[1]IFE!C321 -> 0 | J27: =[1]IFE!D321 -> 0
A28: YP | B28: =[1]IFE!B42 -> lb/100p² | C28: =[1]IFE!C93 -> 16 | D28: =[1]IFE!D93 -> 16 | E28: =[1]IFE!E93 -> 32 | F28: =[1]IFE!F93 -> 32 | G28: =[1]IFE!B322 -> 0 | I28: =[1]IFE!C322 -> 0 | J28: =[1]IFE!D322 -> 0
A29: 10s/10m/30m Gel | B29: =[1]IFE!B42 -> lb/100p² | C29: =CONCATENATE(TEXT([1]IFE!C94,"#")&"/"&(TEXT([1]IFE!C95,"#")&"/"&TEXT([1]IFE!C96,"#"))) -> 11/15/ | D29: =CONCATENATE(TEXT([1]IFE!D94,"#")&"/"&(TEXT([1]IFE!D95,"#")&"/"&TEXT([1]IFE!D96,"#"))) -> 11/15/ | E29: =CONCATENATE(TEXT([1]IFE!E94,"#")&"/"&(TEXT([1]IFE!E95,"#")&"/"&TEXT([1]IFE!E96,"#"))) -> 12/18/ | F29: =CONCATENATE(TEXT([1]IFE!F94,"#")&"/"&(TEXT([1]IFE!F95,"#")&"/"&TEXT([1]IFE!F96,"#"))) -> 12/18/ | G29: =[1]IFE!B323 -> 0 | I29: =[1]IFE!C323 -> 0 | J29: =[1]IFE!D323 -> 0
A30: API Fluid Loss | B30: =[1]IFE!D57 -> cc/30min | C30: =[1]IFE!C97 -> 0 | D30: =[1]IFE!D97 -> 0 | E30: =[1]IFE!E97 -> 0 | F30: =[1]IFE!F97 -> 0 | G30: =[1]IFE!B324 -> 0 | I30: =[1]IFE!C324 -> 0 | J30: =[1]IFE!D324 -> 0
A31: HTHP Fluid Loss | B31: =[1]IFE!D57 -> cc/30min | C31: =CONCATENATE(TEXT([1]IFE!C98,"#.0")&"@"&TEXT([1]IFE!C99,"#")) -> .0@ | D31: =CONCATENATE(TEXT([1]IFE!D98,"#.0")&"@"&TEXT([1]IFE!D99,"#")) -> .0@ | E31: =CONCATENATE(TEXT([1]IFE!E98,"#.0")&"@"&TEXT([1]IFE!E99,"#")) -> .0@ | F31: =CONCATENATE(TEXT([1]IFE!F98,"#.0")&"@"&TEXT([1]IFE!F99,"#")) -> .0@ | G31: =[1]IFE!B325 -> 0 | I31: =[1]IFE!C325 -> 0 | J31: =[1]IFE!D325 -> 0
A32: Cake APT/HT | B32: =[1]IFE!B34 -> 1/32 plg | C32: =CONCATENATE(TEXT([1]IFE!C100,"#")&"/"&TEXT([1]IFE!C101,"#")) -> / | D32: =CONCATENATE(TEXT([1]IFE!D100,"#")&"/"&TEXT([1]IFE!D101,"#")) -> / | E32: =CONCATENATE(TEXT([1]IFE!E100,"#")&"/"&TEXT([1]IFE!E101,"#")) -> / | F32: =CONCATENATE(TEXT([1]IFE!F100,"#")&"/"&TEXT([1]IFE!F101,"#")) -> / | G32: =[1]IFE!B326 -> 0 | I32: =[1]IFE!C326 -> 0 | J32: =[1]IFE!D326 -> 0
A33: Unc Ret Solids | B33: =[1]IFE!D59 -> %Vol | C33: =[1]IFE!C102 -> 4.2 | D33: =[1]IFE!D102 -> 4.2 | E33: =[1]IFE!E102 -> 22 | F33: =[1]IFE!F102 -> 22 | G33: =[1]IFE!B327 -> 0 | I33: =[1]IFE!C327 -> 0 | J33: =[1]IFE!D327 -> 0
A34: Correct Solids | B34: =[1]IFE!D59 -> %Vol | C34: =[1]IFE!C103 -> 0 | D34: =[1]IFE!D103 -> 0 | E34: =[1]IFE!E103 -> 0 | F34: =[1]IFE!F103 -> 0 | G34: SOLIDS CONTROL EQUIPMENT Last 24 hr
A35: Oil | B35: =[1]IFE!D59 -> %Vol | C35: =[1]IFE!C104 -> 95.8 | D35: =[1]IFE!D104 -> 95.8 | E35: =[1]IFE!E104 -> 78 | F35: =[1]IFE!F104 -> 78 | G35: Type | I35: Model/Size | J35: Hrs Used
A36: Uncorr Water | B36: =[1]IFE!D59 -> %Vol | C36: =[1]IFE!C105 -> 0 | D36: =[1]IFE!D105 -> 0 | E36: =[1]IFE!E105 -> 0 | F36: =[1]IFE!F105 -> 0 | G36: =[1]IFE!$B220 -> DERRICK SHEKER 1 | I36: =[1]IFE!$C220 -> 2X100 - 2X140 | J36: =[1]IFE!$D220 -> 0
A37: Oil/Water Ratio | C37: =CONCATENATE(TEXT([1]IFE!C106,"#")&"/"&TEXT([1]IFE!C107,"#")) -> 20/10 | D37: =CONCATENATE(TEXT([1]IFE!D106,"#")&"/"&TEXT([1]IFE!D107,"#")) -> 20/10 | E37: =CONCATENATE(TEXT([1]IFE!E106,"#")&"/"&TEXT([1]IFE!E107,"#")) -> 15/11 | F37: =CONCATENATE(TEXT([1]IFE!F106,"#")&"/"&TEXT([1]IFE!F107,"#")) -> 15/11 | G37: =[1]IFE!$B221 -> DERRICK SHAKER 2 | I37: =[1]IFE!$C221 -> 2X100 - 2X140 | J37: =[1]IFE!$D221 -> 0
A38: Alkal Mud (Pom) | C38: =[1]IFE!C108 -> 85 | D38: =[1]IFE!D108 -> 85 | E38: =[1]IFE!E108 -> 85 | F38: =[1]IFE!F108 -> 85 | G38: =[1]IFE!$B222 -> DERRICK SHAKER 3 | I38: =[1]IFE!$C222 -> 2X100 - 2X140 | J38: =[1]IFE!$D222 -> 0
A39: Cl- Whole Mud | B39: =[1]IFE!D58 -> mg/L | C39: =[1]IFE!C109 -> 0.8 | D39: =[1]IFE!D109 -> 0.8 | E39: =[1]IFE!E109 -> 0 | F39: =[1]IFE!F109 -> 0 | G39: =[1]IFE!$B223 -> MOD 312 / 10T2 w/o pump | I39: =[1]IFE!$C223 -> 4 X 200 | J39: =[1]IFE!$D223 -> 0
A40: Salt | B40: =[1]IFE!D60 -> %Wt | C40: =[1]IFE!C110 -> 0.2 | D40: =[1]IFE!D110 -> 0.2 | E40: =[1]IFE!E110 -> 0 | F40: =[1]IFE!F110 -> 0 | G40: =[1]IFE!$B224 -> 0 | I40: =[1]IFE!$C224 -> 0 | J40: =[1]IFE!$D224 -> 0
A41: Lime | B41: =[1]IFE!B44 -> lb/bbl | C41: =[1]IFE!C111 -> 0.6 | D41: =[1]IFE!D111 -> 0.6 | E41: =[1]IFE!E111 -> 0 | F41: =[1]IFE!F111 -> 0 | G41: =[1]IFE!$B225 -> 0 | I41: =[1]IFE!$C225 -> 0 | J41: =[1]IFE!$D225 -> 0
A42: Emul Stability | C42: =[1]IFE!C112 -> 0 | D42: =[1]IFE!D112 -> 0 | E42: =[1]IFE!E112 -> 0 | F42: =[1]IFE!F112 -> 0 | G42: =[1]IFE!$B226 -> 0 | I42: =[1]IFE!$C226 -> 0 | J42: =[1]IFE!$D226 -> 0
A43: =[1]IFE!B114 -> 0 | B43: =[1]IFE!J114 -> 0 | C43: =[1]IFE!C114 -> 0 | D43: =[1]IFE!D114 -> 0 | E43: =[1]IFE!E114 -> 0 | F43: =[1]IFE!F114 -> 0 | G43: =[1]IFE!$B227 -> 0 | I43: =[1]IFE!$C227 -> 0 | J43: =[1]IFE!$D227 -> 0
A44: =[1]IFE!B115 -> 0 | B44: =[1]IFE!J115 -> 0 | C44: =[1]IFE!C115 -> 0 | D44: =[1]IFE!D115 -> 0 | E44: =[1]IFE!E115 -> 0 | F44: =[1]IFE!F115 -> 0 | G44: =[1]IFE!$B228 -> 0 | I44: =[1]IFE!$C228 -> 0 | J44: =[1]IFE!$D228 -> 0
A45: =[1]IFE!B116 -> 0 | B45: =[1]IFE!J116 -> 0 | C45: =[1]IFE!C116 -> 0 | D45: =[1]IFE!D116 -> 0 | E45: =[1]IFE!E116 -> 0 | F45: =[1]IFE!F116 -> 0 | G45: =[1]IFE!$B229 -> 0 | I45: =[1]IFE!$C229 -> 0 | J45: =[1]IFE!$D229 -> 0
A46: =[1]IFE!B117 -> 0 | B46: =[1]IFE!J117 -> 0 | C46: =[1]IFE!C117 -> 0 | D46: =[1]IFE!D117 -> 0 | E46: =[1]IFE!E117 -> 0 | F46: =[1]IFE!F117 -> 0 | G46: =[1]IFE!$G220 -> 0 | I46: =[1]IFE!$H220 -> 0 | J46: =[1]IFE!$I220 -> 0
A47: =[1]IFE!I382 -> 0 | B47: =[1]IFE!J382 -> 0 | C47: =[1]IFE!A382 -> 0 | D47: =[1]IFE!B382 -> 0 | E47: =[1]IFE!C382 -> 0 | F47: =[1]IFE!D382 -> 0 | G47: MUD PROPERTY SPECS | J47: Actual
A48: =[1]IFE!I383 -> 0 | B48: =[1]IFE!J383 -> 0 | C48: =[1]IFE!A383 -> 0 | D48: =[1]IFE!B383 -> 0 | E48: =[1]IFE!C383 -> 0 | F48: =[1]IFE!D383 -> 0 | G48: Weight | H48: =[1]IFE!B153 -> 9,1 | J48: =[1]IFE!C82 -> 9.1
A49: =[1]IFE!I384 -> 0 | B49: =[1]IFE!J384 -> 0 | C49: =[1]IFE!A384 -> 0 | D49: =[1]IFE!B384 -> 0 | E49: =[1]IFE!C384 -> 0 | F49: =[1]IFE!D384 -> 0 | G49: Viscosity | H49: =[1]IFE!B154 -> 55 | J49: =[1]IFE!C84 -> 55
A50: =[1]IFE!I385 -> 0 | B50: =[1]IFE!J385 -> 0 | C50: =[1]IFE!A385 -> 0 | D50: =[1]IFE!B385 -> 0 | E50: =[1]IFE!C385 -> 0 | F50: =[1]IFE!D385 -> 0 | G50: Filtrate | H50: =[1]IFE!B155 -> 0 | J50: =[1]IFE!C98 -> 0
A51: Reserve Volume | B51: =[1]IFE!$B$32 -> bbl | C51: =[1]IFE!$BH$210+[1]IFE!$BH$211 -> 1418
A52: REMARKS AND TREATMENT | E52: REMARKS
A53: =[1]IFE!B157 -> Realizó chequeo a fluido y ajustó viscosidad. no se logro recibir barita debido a que el mal tiempo no permitio que el barco se pegara al equipo y luego debió volver a muelle. Actualmente esperando el barco con Barita. Realizó correccion de presentacion del producto DUOVIS, ya que el mismo estaba reportado de 50 libras y el usado es de 25 kg. | E53: =[1]IFE!B158 -> Terminó de instalar equipo de pozo, probo el mismo OK. bajo sarta de perforacion hasta tope de cemento, probó equipo ok.
A54: TIME DISTRIBUTION Last 24 hrs | C54: ="MUD VOL ACCTG " &"("&[1]IFE!B32&")" -> MUD VOL ACCTG (bbl) | E54: SOLIDS ANALYSIS | H54: RHEOLOGY & HYDRAULICS
A55: =[1]IFE!B270 -> Armado / Mantenimiento | B55: =[1]IFE!C270 -> 0 | C55: Oil Added | D55: =[1]IFE!$E$331 -> 0 | E55: Salt Wt% | G55: =[1]IFE!C202 -> 0,/ 0, | H55: np/na | J55: =[1]IFE!B243 -> 0
A56: =[1]IFE!B271 -> Perforación | B56: =[1]IFE!C271 -> 0 | C56: Water Added | D56: =[1]IFE!$E$332 -> 0 | E56: Salt Conc | G56: =[1]IFE!C203 -> 0,/ 0, | H56: Kp/Ka | J56: =[1]IFE!B244 -> 0
A57: =[1]IFE!B272 -> Viajes | B57: =[1]IFE!C272 -> 0 | C57: Mud Received | D57: =[1]IFE!$E$336 -> 0 | E57: Adjusted Solids | G57: =[1]IFE!C204 -> 2,3/ 20,6 | H57: Bit Pressure Loss/% | J57: =[1]IFE!B245 -> 0
A58: =[1]IFE!B273 -> Tiempo No Productivo | B58: =[1]IFE!C273 -> 0 | C58: Mud Returned | D58: =[1]IFE!$E$337 -> 0 | E58: Oil/Water Ratio | G58: =[1]IFE!C205 -> 2,2/ 20, | H58: Bit HHP/HSI | J58: =[1]IFE!B246 -> 0
A59: =[1]IFE!B274 -> 0 | B59: =[1]IFE!C274 -> 0 | C59: =[1]IFE!$A$261 -> Shakers | D59: =[1]IFE!$B$261 -> 0 | E59: Average SG Solids | G59: =[1]IFE!C206 -> 0,/ 0, | H59: Jet Velocity | J59: =[1]IFE!B247 -> 0
A60: =[1]IFE!B275 -> 0 | B60: =[1]IFE!C275 -> 0 | C60: =[1]IFE!$A$262 -> Evaporation | D60: =[1]IFE!$B$262 -> 0 | E60: Low Gravity % | G60: =[1]IFE!C207 -> 1,9/ 28,9 | H60: Va Pipe | J60: =[1]IFE!B248 -> 0
A61: =[1]IFE!B276 -> 0 | B61: =[1]IFE!C276 -> 0 | C61: =[1]IFE!$A$263 -> Centrifuge | D61: =[1]IFE!$B$263 -> 0 | E61: Low Gravity Wt. | G61: =[1]IFE!C208 -> - / 0,6 | H61: Va Collars | J61: =[1]IFE!B249 -> 0
A62: =[1]IFE!B277 -> 0 | B62: =[1]IFE!C277 -> 0 | C62: =[1]IFE!$A$264 -> Formation | D62: =[1]IFE!$B$264 -> 0 | E62: High Gravity % | G62: =[1]IFE!C209 -> -0,0019 | H62: Cva Pipe | J62: =[1]IFE!B250 -> 0
A63: =[1]IFE!B278 -> 0 | B63: =[1]IFE!C278 -> 0 | C63: =[1]IFE!$A$265 -> Left in Hole | D63: =[1]IFE!$B$265 -> 0 | E63: High Gravity Wt. | G63: =[1]IFE!C210 -> 3,2 | H63: Cva Collars | J63: =[1]IFE!B251 -> 0
A64: =[1]IFE!B279 -> 0 | B64: =[1]IFE!C279 -> 0 | C64: =[1]IFE!$A$266 -> Other | D64: =[1]IFE!$B$266 -> 0 | E64: =[1]IFE!AD13 -> 0 | G64: =[1]IFE!C211 -> 0 | H64: ECD at Shoe | J64: =[1]IFE!B252 -> 0
C65: =[1]IFE!$A$267 -> Discharged | D65: =[1]IFE!$B$267 -> 0 | H65: ECD at TD | J65: =[1]IFE!B253 -> 0
C66: =[1]IFE!$C$261 -> Pit Cleaning | D66: =[1]IFE!$D$261 -> 0
C67: =[1]IFE!$C$262 -> 0 | D67: =[1]IFE!$D$262 -> 0 | G67: DAILY COST | I67: CUMULATIVE COST
C68: =[1]IFE!$C$263 -> 0 | D68: =[1]IFE!$D$263 -> 0 | F68: Drlg Fluids | G68: =[1]IFE!$B$134 -> 5749.32 | I68: =[1]IFE!$B$135 -> 89939.53
A69: M-I ENGR / PHONE | C69: RIG PHONE | D69: WAREHOUSE PHONE | F69: S.R.E. & Engr. | G69: =[1]IFE!$D$138+[1]IFE!$D$142 -> 0 | I69: =[1]IFE!$D$139+[1]IFE!$D$143 -> 0
A70: =[1]IFE!$B$127 -> Jesus Villarroel | C70: =[1]IFE!$D$131 -> 0 | D70: =[1]IFE!$B$133 -> 0 | F70: Screens | G70: =[1]IFE!$D$136 -> 0 | I70: =[1]IFE!$D$137 -> 0
A71: =[1]IFE!$B$129 -> 0 | F71: TOTALS | G71: =SUM(G68:H70) -> 5749.32 | I71: =SUM(I68:J70) -> 89939.53

Sheet Extra WBM Labels
J2: ="EXTRA WBM PROPERTIES REPORT No. "&[1]IFE!B166&" " -> EXTRA WBM PROPERTIES REPORT No. 9
A3: Operator : | B3: =[1]IFE!B6 -> Cardon IV | D3: Field/Area : | E3: =[1]IFE!B9 -> Golfo de Venezuela | H3: Depth/TVD : | I3: =[1]IFE!B120&" "&[1]IFE!B30&" /" -> 563 pies / | J3: =[1]IFE!B121&" "&[1]IFE!B30 -> 563 pies
A4: Report For : | B4: =[1]IFE!B125 -> Gerrit Ham / Jhony Quintero | D4: Description : | E4: =[1]IFE!B10 -> Exploratory | H4: Date : | I4: =[1]IFE!B119 -> 39989
A5: Well Name : | B5: =[1]IFE!B8 -> Perla-1X | D5: Location : | E5: =[1]IFE!B11 -> Offshore | H5: Spud Date : | I5: =[1]IFE!B5 -> 39981
A6: Contractor: | B6: =[1]IFE!B15 -> Ensco | D6: Water Depth : | E6: =[1]IFE!B16&" "&[1]IFE!B30 -> 202 pies | H6: Mud Type : | I6: =[1]IFE!B124 -> Agua de mar / HI VIS
A7: Report For : | B7: =[1]IFE!B126 -> Ricky Otwell | D7: Rig Name : | E7: =[1]IFE!Z981 -> 68 | H7: Activity : | I7: =[1]IFE!B123 -> Bajando Tuberia
A8: EXTRA PROPERTIES
A9: Sample From | C9: =CONCATENATE(TEXT([1]IFE!C77," ")&" "&TEXT([1]IFE!C78,"H:MM")) -> TK 1 12:00 | D9: =CONCATENATE(TEXT([1]IFE!D77," ")&" "&TEXT([1]IFE!D78,"H:MM")) -> 0:00 | E9: =CONCATENATE(TEXT([1]IFE!E77," ")&" "&TEXT([1]IFE!E78,"H:MM")) -> TK 3 12:00 | F9: =CONCATENATE(TEXT([1]IFE!F77," ")&" "&TEXT([1]IFE!F78,"H:MM")) -> TK 3 0:00
A10: =[1]IFE!H2801 -> 0 | B10: =[1]IFE!I2801 -> 0 | C10: =[1]IFE!B2801 -> 0 | D10: =[1]IFE!C2801 -> 0 | E10: =[1]IFE!D2801 -> 0 | F10: =[1]IFE!E2801 -> 0
A11: =[1]IFE!H2802 -> 0 | B11: =[1]IFE!I2802 -> 0 | C11: =[1]IFE!B2802 -> 0 | D11: =[1]IFE!C2802 -> 0 | E11: =[1]IFE!D2802 -> 0 | F11: =[1]IFE!E2802 -> 0
A12: =[1]IFE!H2803 -> 0 | B12: =[1]IFE!I2803 -> 0 | C12: =[1]IFE!B2803 -> 0 | D12: =[1]IFE!C2803 -> 0 | E12: =[1]IFE!D2803 -> 0 | F12: =[1]IFE!E2803 -> 0
A13: =[1]IFE!H2804 -> 0 | B13: =[1]IFE!I2804 -> 0 | C13: =[1]IFE!B2804 -> 0 | D13: =[1]IFE!C2804 -> 0 | E13: =[1]IFE!D2804 -> 0 | F13: =[1]IFE!E2804 -> 0
A14: =[1]IFE!H2805 -> 0 | B14: =[1]IFE!I2805 -> 0 | C14: =[1]IFE!B2805 -> 0 | D14: =[1]IFE!C2805 -> 0 | E14: =[1]IFE!D2805 -> 0 | F14: =[1]IFE!E2805 -> 0
A15: =[1]IFE!H2806 -> 0 | B15: =[1]IFE!I2806 -> 0 | C15: =[1]IFE!B2806 -> 0 | D15: =[1]IFE!C2806 -> 0 | E15: =[1]IFE!D2806 -> 0 | F15: =[1]IFE!E2806 -> 0
A16: =[1]IFE!H2807 -> 0 | B16: =[1]IFE!I2807 -> 0 | C16: =[1]IFE!B2807 -> 0 | D16: =[1]IFE!C2807 -> 0 | E16: =[1]IFE!D2807 -> 0 | F16: =[1]IFE!E2807 -> 0
A17: =[1]IFE!H2808 -> 0 | B17: =[1]IFE!I2808 -> 0 | C17: =[1]IFE!B2808 -> 0 | D17: =[1]IFE!C2808 -> 0 | E17: =[1]IFE!D2808 -> 0 | F17: =[1]IFE!E2808 -> 0
A18: =[1]IFE!H2809 -> 0 | B18: =[1]IFE!I2809 -> 0 | C18: =[1]IFE!B2809 -> 0 | D18: =[1]IFE!C2809 -> 0 | E18: =[1]IFE!D2809 -> 0 | F18: =[1]IFE!E2809 -> 0
A19: =[1]IFE!H2810 -> 0 | B19: =[1]IFE!I2810 -> 0 | C19: =[1]IFE!B2810 -> 0 | D19: =[1]IFE!C2810 -> 0 | E19: =[1]IFE!D2810 -> 0 | F19: =[1]IFE!E2810 -> 0
A20: =[1]IFE!H2811 -> 0 | B20: =[1]IFE!I2811 -> 0 | C20: =[1]IFE!B2811 -> 0 | D20: =[1]IFE!C2811 -> 0 | E20: =[1]IFE!D2811 -> 0 | F20: =[1]IFE!E2811 -> 0
A21: =[1]IFE!H2812 -> 0 | B21: =[1]IFE!I2812 -> 0 | C21: =[1]IFE!B2812 -> 0 | D21: =[1]IFE!C2812 -> 0 | E21: =[1]IFE!D2812 -> 0 | F21: =[1]IFE!E2812 -> 0
... A61: =[1]IFE!H2852 -> 0 | B61: =[1]IFE!I2852 -> 0 | C61: =[1]IFE!B2852 -> 0 | D61: =[1]IFE!C2852 -> 0 | E61: =[1]IFE!D2852 -> 0 | F61: =[1]IFE!E2852 -> 0
A62: M-I ENGR / PHONE | C62: RIG PHONE | E62: WAREHOUSE PHONE | G62: DAILY COST | I62: CUMULATIVE COST
A63: =[1]IFE!$B$127&" "&[1]IFE!$B$129 -> Jesus Villarroel 0
A64: =[1]IFE!$B$128 -> Nelson Marcano | C64: =[1]IFE!$D$131 -> 0 | E64: =[1]IFE!B133 -> 0 | G64: =[1]IFE!B134 -> 5749.32 | I64: =[1]IFE!B135 -> 89939.53

Sheet Extra OBM-SBM Labels
J2: ="EXTRA OBM-SBM PROPERTIES REPORT No. "&[1]IFE!B166&" " -> EXTRA OBM-SBM PROPERTIES REPORT No. 9
A3: Operator : | B3: =[1]IFE!B6 -> Cardon IV | D3: Field/Area : | E3: =[1]IFE!B9 -> Golfo de Venezuela | H3: Depth/TVD : | I3: =[1]IFE!B120&" "&[1]IFE!B30&" /" -> 563 pies / | J3: =[1]IFE!B121&" "&[1]IFE!B30 -> 563 pies
A4: Report For : | B4: =[1]IFE!B125 -> Gerrit Ham / Jhony Quintero | D4: Description : | E4: =[1]IFE!B10 -> Exploratory | H4: Date : | I4: =[1]IFE!B119 -> 39989
A5: Well Name : | B5: =[1]IFE!B8 -> Perla-1X | D5: Location : | E5: =[1]IFE!B11 -> Offshore | H5: Spud Date : | I5: =[1]IFE!B5 -> 39981
A6: Contractor: | B6: =[1]IFE!B15 -> Ensco | D6: Water Depth : | E6: =[1]IFE!B16&" "&[1]IFE!B30 -> 202 pies | H6: Mud Type : | I6: =[1]IFE!B124 -> Agua de mar / HI VIS
A7: Report For : | B7: =[1]IFE!B126 -> Ricky Otwell | D7: Rig Name : | E7: =[1]IFE!Z981 -> 68 | H7: Activity : | I7: =[1]IFE!B123 -> Bajando Tuberia
A8: EXTRA PROPERTIES
A9: Sample From | C9: =CONCATENATE(TEXT([1]IFE!C77," ")&" "&TEXT([1]IFE!C78,"H:MM")) -> TK 1 12:00 | D9: =CONCATENATE(TEXT([1]IFE!D77," ")&" "&TEXT([1]IFE!D78,"H:MM")) -> 0:00 | E9: =CONCATENATE(TEXT([1]IFE!E77," ")&" "&TEXT([1]IFE!E78,"H:MM")) -> TK 3 12:00 | F9: =CONCATENATE(TEXT([1]IFE!F77," ")&" "&TEXT([1]IFE!F78,"H:MM")) -> TK 3 0:00
A10: =[1]IFE!J2801 -> 0 | B10: =[1]IFE!K2801 -> 0 | C10: =[1]IFE!B2801 -> 0 | D10: =[1]IFE!C2801 -> 0 | E10: =[1]IFE!D2801 -> 0 | F10: =[1]IFE!E2801 -> 0
A11: =[1]IFE!J2802 -> 0 | B11: =[1]IFE!K2802 -> 0 | C11: =[1]IFE!B2802 -> 0 | D11: =[1]IFE!C2802 -> 0 | E11: =[1]IFE!D2802 -> 0 | F11: =[1]IFE!E2802 -> 0
A12: =[1]IFE!J2803 -> 0 | B12: =[1]IFE!K2803 -> 0 | C12: =[1]IFE!B2803 -> 0 | D12: =[1]IFE!C2803 -> 0 | E12: =[1]IFE!D2803 -> 0 | F12: =[1]IFE!E2803 -> 0
A13: =[1]IFE!J2804 -> 0 | B13: =[1]IFE!K2804 -> 0 | C13: =[1]IFE!B2804 -> 0 | D13: =[1]IFE!C2804 -> 0 | E13: =[1]IFE!D2804 -> 0 | F13: =[1]IFE!E2804 -> 0
A14: =[1]IFE!J2805 -> 0 | B14: =[1]IFE!K2805 -> 0 | C14: =[1]IFE!B2805 -> 0 | D14: =[1]IFE!C2805 -> 0 | E14: =[1]IFE!D2805 -> 0 | F14: =[1]IFE!E2805 -> 0
A15: =[1]IFE!J2806 -> 0 | B15: =[1]IFE!K2806 -> 0 | C15: =[1]IFE!B2806 -> 0 | D15: =[1]IFE!C2806 -> 0 | E15: =[1]IFE!D2806 -> 0 | F15: =[1]IFE!E2806 -> 0
A16: =[1]IFE!J2807 -> 0 | B16: =[1]IFE!K2807 -> 0 | C16: =[1]IFE!B2807 -> 0 | D16: =[1]IFE!C2807 -> 0 | E16: =[1]IFE!D2807 -> 0 | F16: =[1]IFE!E2807 -> 0
A17: =[1]IFE!J2808 -> 0 | B17: =[1]IFE!K2808 -> 0 | C17: =[1]IFE!B2808 -> 0 | D17: =[1]IFE!C2808 -> 0 | E17: =[1]IFE!D2808 -> 0 | F17: =[1]IFE!E2808 -> 0
A18: =[1]IFE!J2809 -> 0 | B18: =[1]IFE!K2809 -> 0 | C18: =[1]IFE!B2809 -> 0 | D18: =[1]IFE!C2809 -> 0 | E18: =[1]IFE!D2809 -> 0 | F18: =[1]IFE!E2809 -> 0
A19: =[1]IFE!J2810 -> 0 | B19: =[1]IFE!K2810 -> 0 | C19: =[1]IFE!B2810 -> 0 | D19: =[1]IFE!C2810 -> 0 | E19: =[1]IFE!D2810 -> 0 | F19: =[1]IFE!E2810 -> 0
A20: =[1]IFE!J2811 -> 0 | B20: =[1]IFE!K2811 -> 0 | C20: =[1]IFE!B2811 -> 0 | D20: =[1]IFE!C2811 -> 0 | E20: =[1]IFE!D2811 -> 0 | F20: =[1]IFE!E2811 -> 0
A21: =[1]IFE!J2812 -> 0 | B21: =[1]IFE!K2812 -> 0 | C21: =[1]IFE!B2812 -> 0 | D21: =[1]IFE!C2812 -> 0 | E21: =[1]IFE!D2812 -> 0 | F21: =[1]IFE!E2812 -> 0
... A61: =[1]IFE!J2852 -> 0 | B61: =[1]IFE!K2852 -> 0 | C61: =[1]IFE!B2852 -> 0 | D61: =[1]IFE!C2852 -> 0 | E61: =[1]IFE!D2852 -> 0 | F61: =[1]IFE!E2852 -> 0
A62: M-I ENGR / PHONE | C62: RIG PHONE | E62: WAREHOUSE PHONE | G62: DAILY COST | I62: CUMULATIVE COST
A63: =[1]IFE!$B$127&" "&[1]IFE!$B$129 -> Jesus Villarroel 0
A64: =[1]IFE!$B$128 -> Nelson Marcano | C64: =[1]IFE!$D$131 -> 0 | E64: =[1]IFE!B133 -> 0 | G64: =[1]IFE!B134 -> 5749.32 | I64: =[1]IFE!B135 -> 89939.53

Sheet Vol. Info
F1: MUD VOLUME ACCOUNTING
F2: Daily Report
A5: Operator : | B5: =[1]IFE!B6 -> Cardon IV | E5: Date : | F5: =SUM([1]IFE!$B$119) -> 39989
A6: Well Name: | B6: =[1]IFE!B8 -> Perla-1X | E6: Report No.: | F6: =SUM([1]IFE!$B$166) -> 9
A8: TANK | B8: CAPACITY | C8: WEIGHT | D8: VOLUME | E8: REMARKS | F8: CLASS | G8: SUM PIT VOLUMES
B9: =[1]IFE!$B$32 -> bbl | C9: =[1]IFE!$B$39 -> lb/gal | D9: =[1]IFE!$B$32 -> bbl
A10: =[1]IFE!$BN$3 -> Pit # 3 | B10: =[1]IFE!$BN$423 -> 586 | C10: =[1]IFE!$BN$63 -> 0 | D10: =[1]IFE!$BN$93 -> 420 | E10: =[1]IFE!BN343 -> 0 | F10: =[1]IFE!$BN$33 -> Reserve | G10: MUD VOLUME | H10: =[1]IFE!$B$32 -> bbl
A11: =[1]IFE!$BN$4 -> Trip tank # 1 | B11: =[1]IFE!$BN$424 -> 40 | C11: =[1]IFE!$BN$64 -> 0 | D11: =[1]IFE!$BN$94 -> 0 | E11: =[1]IFE!BN344 -> 0 | F11: =[1]IFE!$BN$34 -> Reserve | G11: Active | H11: =[1]IFE!$BH$209 -> 0
A12: =[1]IFE!$BN$5 -> Trip tank # 2 | B12: =[1]IFE!$BN$425 -> 40 | C12: =[1]IFE!$BN$65 -> 0 | D12: =[1]IFE!$BN$95 -> 0 | E12: =[1]IFE!BN345 -> 0 | F12: =[1]IFE!$BN$35 -> Reserve | G12: Reserve | H12: =[1]IFE!$BH$210 -> 1418
A13: =[1]IFE!$BN$6 -> Pit # 1 | B13: =[1]IFE!$BN$426 -> 512 | C13: =[1]IFE!$BN$66 -> 0 | D13: =[1]IFE!$BN$96 -> 501 | E13: =[1]IFE!BN346 -> 0 | F13: =[1]IFE!$BN$36 -> Reserve | G13: Premix | H13: =[1]IFE!$BH$211 -> 0
A14: =[1]IFE!$BN$7 -> Pit # 2 | B14: =[1]IFE!$BN$427 -> 586 | C14: =[1]IFE!$BN$67 -> 0 | D14: =[1]IFE!$BN$97 -> 497 | E14: =[1]IFE!BN347 -> 0 | F14: =[1]IFE!$BN$37 -> Reserve | G14: OTHER VOLUME
A15: =[1]IFE!$BN$8 -> Slug Pit | B15: =[1]IFE!$BN$428 -> 75 | C15: =[1]IFE!$BN$68 -> 0 | D15: =[1]IFE!$BN$98 -> 0 | E15: =[1]IFE!BN348 -> 0 | F15: =[1]IFE!$BN$38 -> Reserve | G15: =[1]IFE!$BG$213 -> Base Oil | H15: =[1]IFE!$BH$213 -> 0
A16: =[1]IFE!$BN$9 -> Sand Traps | B16: =[1]IFE!$BN$429 -> 170 | C16: =[1]IFE!$BN$69 -> 0 | D16: =[1]IFE!$BN$99 -> 0 | E16: =[1]IFE!BN349 -> 0 | F16: =[1]IFE!$BN$39 -> Reserve | G16: =[1]IFE!$BG$214 -> Brine | H16: =[1]IFE!$BH$214 -> 0
A17: =[1]IFE!$BN$10 -> 0 | B17: =[1]IFE!$BN$430 -> 0 | C17: =[1]IFE!$BN$70 -> 0 | D17: =[1]IFE!$BN$100 -> 0 | E17: =[1]IFE!BN350 -> 0 | F17: =[1]IFE!$BN$40 -> 0 | G17: =[1]IFE!$BG$215 -> Hole | H17: =[1]IFE!$BH$215 -> 0
A18: =[1]IFE!$BN$11 -> 0 | B18: =[1]IFE!$BN$431 -> 0 | C18: =[1]IFE!$BN$71 -> 0 | D18: =[1]IFE!$BN$101 -> 0 | E18: =[1]IFE!BN351 -> 0 | F18: =[1]IFE!$BN$41 -> 0 | G18: =[1]IFE!$BG$216 -> 0 | H18: =[1]IFE!$BH$216 -> 0
A19: =[1]IFE!$BN$12 -> 0 | B19: =[1]IFE!$BN$432 -> 0 | C19: =[1]IFE!$BN$72 -> 0 | D19: =[1]IFE!$BN$102 -> 0 | E19: =[1]IFE!BN352 -> 0 | F19: =[1]IFE!$BN$42 -> 0 | G19: =[1]IFE!$BG$217 -> 0 | H19: =[1]IFE!$BH$217 -> 0
A20: =[1]IFE!$BN$13 -> 0 | B20: =[1]IFE!$BN$433 -> 0 | C20: =[1]IFE!$BN$73 -> 0 | D20: =[1]IFE!$BN$103 -> 0 | E20: =[1]IFE!BN353 -> 0 | F20: =[1]IFE!$BN$43 -> 0 | G20: =[1]IFE!$BG$218 -> 0 | H20: =[1]IFE!$BH$218 -> 0
A21: =[1]IFE!$BN$14 -> 0 | B21: =[1]IFE!$BN$434 -> 0 | C21: =[1]IFE!$BN$74 -> 0 | D21: =[1]IFE!$BN$104 -> 0 | E21: =[1]IFE!BN354 -> 0 | F21: =[1]IFE!$BN$44 -> 0 | G21: =[1]IFE!$BG$219 -> 0 | H21: =[1]IFE!$BH$219 -> 0
A22: =[1]IFE!$BN$15 -> 0 | B22: =[1]IFE!$BN$435 -> 0 | C22: =[1]IFE!$BN$75 -> 0 | D22: =[1]IFE!$BN$105 -> 0 | E22: =[1]IFE!BN355 -> 0 | F22: =[1]IFE!$BN$45 -> 0 | G22: =[1]IFE!$BG$220 -> 0 | H22: =[1]IFE!$BH$220 -> 0
A23: =[1]IFE!$BN$16 -> 0 | B23: =[1]IFE!$BN$436 -> 0 | C23: =[1]IFE!$BN$76 -> 0 | D23: =[1]IFE!$BN$106 -> 0 | E23: =[1]IFE!BN356 -> 0 | F23: =[1]IFE!$BN$46 -> 0 | G23: =[1]IFE!$BG$221 -> 0 | H23: =[1]IFE!$BH$221 -> 0
A24: =[1]IFE!$BN$17 -> 0 | B24: =[1]IFE!$BN$437 -> 0 | C24: =[1]IFE!$BN$77 -> 0 | D24: =[1]IFE!$BN$107 -> 0 | E24: =[1]IFE!BN357 -> 0 | F24: =[1]IFE!$BN$47 -> 0 | G24: =[1]IFE!$BG$222 -> 0 | H24: =[1]IFE!$BH$222 -> 0
A25: =[1]IFE!$BN$18 -> 0 | B25: =[1]IFE!$BN$438 -> 0 | C25: =[1]IFE!$BN$78 -> 0 | D25: =[1]IFE!$BN$108 -> 0 | E25: =[1]IFE!BN358 -> 0 | F25: =[1]IFE!$BN$48 -> 0 | G25: =[1]IFE!$BG$223 -> 0 | H25: =[1]IFE!$BH$223 -> 0
A26: =[1]IFE!$BN$19 -> 0 | B26: =[1]IFE!$BN$439 -> 0 | C26: =[1]IFE!$BN$79 -> 0 | D26: =[1]IFE!$BN$109 -> 0 | E26: =[1]IFE!BN359 -> 0 | F26: =[1]IFE!$BN$49 -> 0 | G26: =[1]IFE!$BG$224 -> 0 | H26: =[1]IFE!$BH$224 -> 0
A27: =[1]IFE!$BN$20 -> 0 | B27: =[1]IFE!$BN$440 -> 0 | C27: =[1]IFE!$BN$80 -> 0 | D27: =[1]IFE!$BN$110 -> 0 | E27: =[1]IFE!BN360 -> 0 | F27: =[1]IFE!$BN$50 -> 0 | G27: =[1]IFE!$BG$225 -> 0 | H27: =[1]IFE!$BH$225 -> 0
A28: =[1]IFE!$BN$21 -> 0 | B28: =[1]IFE!$BN$441 -> 0 | C28: =[1]IFE!$BN$81 -> 0 | D28: =[1]IFE!$BN$111 -> 0 | E28: =[1]IFE!BN361 -> 0 | F28: =[1]IFE!$BN$51 -> 0 | G28: =[1]IFE!$BG$226 -> 0 | H28: =[1]IFE!$BH$226 -> 0
A29: =[1]IFE!$BN$22 -> 0 | B29: =[1]IFE!$BN$442 -> 0 | C29: =[1]IFE!$BN$82 -> 0 | D29: =[1]IFE!$BN$112 -> 0 | E29: =[1]IFE!BN362 -> 0 | F29: =[1]IFE!$BN$52 -> 0
A30: =[1]IFE!$BN$23 -> 0 | B30: =[1]IFE!$BN$443 -> 0 | C30: =[1]IFE!$BN$83 -> 0 | D30: =[1]IFE!$BN$113 -> 0 | E30: =[1]IFE!BN363 -> 0 | F30: =[1]IFE!$BN$53 -> 0
A31: =[1]IFE!$BN$24 -> 0 | B31: =[1]IFE!$BN$444 -> 0 | C31: =[1]IFE!$BN$84 -> 0 | D31: =[1]IFE!$BN$114 -> 0 | E31: =[1]IFE!BN364 -> 0 | F31: =[1]IFE!$BN$54 -> 0
A32: =[1]IFE!$BN$25 -> 0 | B32: =[1]IFE!$BN$445 -> 0 | C32: =[1]IFE!$BN$85 -> 0 | D32: =[1]IFE!$BN$115 -> 0 | E32: =[1]IFE!BN365 -> 0 | F32: =[1]IFE!$BN$55 -> 0
A33: =[1]IFE!$BN26 -> 0 | B33: =[1]IFE!$BN446 -> 0 | C33: =[1]IFE!$BN86 -> 0 | D33: =[1]IFE!$BN116 -> 0 | E33: =[1]IFE!BN366 -> 0 | F33: =[1]IFE!$BN56 -> 0
A34: =[1]IFE!$BN27 -> 0 | B34: =[1]IFE!$BN447 -> 0 | C34: =[1]IFE!$BN87 -> 0 | D34: =[1]IFE!$BN117 -> 0 | E34: =[1]IFE!BN367 -> 0 | F34: =[1]IFE!$BN57 -> 0
A35: =[1]IFE!$BN28 -> 0 | B35: =[1]IFE!$BN448 -> 0 | C35: =[1]IFE!$BN88 -> 0 | D35: =[1]IFE!$BN118 -> 0 | E35: =[1]IFE!BN368 -> 0 | F35: =[1]IFE!$BN58 -> 0
A36: =[1]IFE!$BN29 -> 0 | B36: =[1]IFE!$BN449 -> 0 | C36: =[1]IFE!$BN89 -> 0 | D36: =[1]IFE!$BN119 -> 0 | E36: =[1]IFE!BN369 -> 0 | F36: =[1]IFE!$BN59 -> 0
A37: =[1]IFE!$BN30 -> 0 | B37: =[1]IFE!$BN450 -> 0 | C37: =[1]IFE!$BN90 -> 0 | D37: =[1]IFE!$BN120 -> 0 | E37: =[1]IFE!BN370 -> 0 | F37: =[1]IFE!$BN60 -> 0
A38: =[1]IFE!$BN31 -> 0 | B38: =[1]IFE!$BN451 -> 0 | C38: =[1]IFE!$BN91 -> 0 | D38: =[1]IFE!$BN121 -> 0 | E38: =[1]IFE!BN371 -> 0 | F38: =[1]IFE!$BN61 -> 0
A39: =[1]IFE!$BN32 -> 0 | B39: =[1]IFE!$BN452 -> 0 | C39: =[1]IFE!$BN92 -> 0 | D39: =[1]IFE!$BN122 -> 0 | E39: =[1]IFE!BN372 -> 0 | F39: =[1]IFE!$BN62 -> 0
C40: MUD IN HOLE (bbls)
A41: MUD IN HOLE: | B41: ANNULUS | C41: PIPE | E41: BELOW BIT | G41: TOTAL
A43: Total Hole Volume | B43: =[1]IFE!$BE$84 -> 0 | C43: =[1]IFE!$BE$83 -> 0 | E43: =[1]IFE!$BE$85 -> 429 | G43: =B43+C43+E43 -> 429
A44: Volume Not Mud | B44: =[1]IFE!$BE$36 -> 0 | C44: =[1]IFE!$BE$37 -> 0 | E44: =[1]IFE!$BE$38 -> 429 | G44: =B44+C44+E44 -> 429
A45: Mud Volume | B45: =B43-B44 -> 0 | C45: =C43-C44 -> 0 | E45: =E43-E44 -> 0 | G45: =G43-G44 -> 0
C47: VOLUME BALANCE (bbls) | G47: LOSS BREAKDOWN (bbls)
A48: IN/TO: | C48: ACTIVE | D48: RESERVE | E48: PREMIX | F48: TOTAL | G48: =[1]IFE!$BD$40 -> Shakers | H48: =[1]IFE!$BE$40 -> 0
G49: =[1]IFE!$BD$41 -> Evaporation | H49: =[1]IFE!$BE$41 -> 0
A50: Start Volume | C50: =[1]IFE!B330 -> 0 | D50: =[1]IFE!C330 -> 1419 | E50: =[1]IFE!D330 -> 0 | F50: =[1]IFE!E330 -> 1419 | G50: =[1]IFE!$BD$42 -> Centrifuge | H50: =[1]IFE!$BE$42 -> 0
A51: Oil Added | C51: =[1]IFE!B331 -> 0 | D51: =[1]IFE!C331 -> 0 | E51: =[1]IFE!D331 -> 0 | F51: =[1]IFE!E331 -> 0 | G51: =[1]IFE!$BD$43 -> Formation | H51: =[1]IFE!$BE$43 -> 0
A52: Water Added | C52: =[1]IFE!B332 -> 0 | D52: =[1]IFE!C332 -> 0 | E52: =[1]IFE!D332 -> 0 | F52: =[1]IFE!E332 -> 0 | G52: =[1]IFE!$BD$44 -> Left in Hole | H52: =[1]IFE!$BE$44 -> 0
A53: Vol Chem Added | C53: =[1]IFE!B333 -> 0 | D53: =[1]IFE!C333 -> 0 | E53: =[1]IFE!D333 -> 0 | F53: =[1]IFE!E333 -> 0 | G53: =[1]IFE!$BD$45 -> Other | H53: =[1]IFE!$BE$45 -> 0
A54: Chem Not For Mud | C54: =[1]IFE!B334 -> 0 | D54: =[1]IFE!C334 -> 0 | E54: =[1]IFE!D334 -> 0 | F54: =[1]IFE!E334 -> 0 | G54: =[1]IFE!$BD$46 -> Discharged | H54: =[1]IFE!$BE$46 -> 0
A55: Total Volume Built | C55: =[1]IFE!B335 -> 0 | D55: =[1]IFE!C335 -> 0 | E55: =[1]IFE!D335 -> 0 | F55: =[1]IFE!E335 -> 0 | G55: =[1]IFE!$BD$47 -> Pit Cleaning | H55: =[1]IFE!$BE$47 -> 0
A56: Received | C56: =[1]IFE!B336 -> 0 | D56: =[1]IFE!C336 -> 0 | E56: =[1]IFE!D336 -> 0 | F56: =[1]IFE!E336 -> 0 | G56: =[1]IFE!$BD$48 -> 0 | H56: =[1]IFE!$BE$48 -> 0
A57: Return | C57: =[1]IFE!B337 -> 0 | D57: =[1]IFE!C337 -> 0 | E57: =[1]IFE!D337 -> 0 | F57: =[1]IFE!E337 -> 0 | G57: =[1]IFE!$BD$49 -> 0 | H57: =[1]IFE!$BE$49 -> 0
A58: From Active To | D58: =[1]IFE!C338 -> 0 | E58: =[1]IFE!D338 -> 0 | F58: =[1]IFE!E338 -> 0
A59: From Reserve To | C59: =[1]IFE!B339 -> 0 | E59: =[1]IFE!D339 -> 0 | F59: =[1]IFE!E339 -> 0
A60: From Premix To | C60: =[1]IFE!B340 -> 0 | D60: =[1]IFE!C340 -> 0 | F60: =[1]IFE!E340 -> 0
A61: Daily Loss | C61: =[1]IFE!B341 -> 0 | D61: =[1]IFE!C341 -> 0 | E61: =[1]IFE!D341 -> 0 | F61: =[1]IFE!E341 -> 0
A62: Final Volume | C62: =[1]IFE!B342 -> 0 | D62: =[1]IFE!C342 -> 1419 | E62: =[1]IFE!D342 -> 0 | F62: =[1]IFE!E342 -> 1419 | G62: Total Loss | H62: =H48+H49+H50+H51+H52+H53+H54+H55+H56+H58 -> 0

Sheet Chem. Inv (DF)
G1: WELLSITE CHEMICAL INVENTORY
G2: Daily Report
B3: Operator : | C3: =[1]IFE!$B$6 -> Cardon IV | I3: Date : | J3: =[1]IFE!$B$119 -> 39989
B4: Well Name : | C4: =[1]IFE!$B$8 -> Perla-1X | I4: Report No: | J4: =[1]IFE!$B$166 -> 9
B5: Location: | C5: =[1]IFE!$B$11 -> Offshore | I5: Page | J5: 1
E6: Cost Summary
D7: Total Daily Cost: | F7: =[1]IFE!$B$134 -> 5749.32 | J7: Total Daily Tax: | K7: =SUM(F7)-R15 -> 0
D8: Cumulative Cost: | F8: =[1]IFE!$B$135 -> 89939.53
A9: Product | C9: Unit | D9: Unit | E9: Start | F9: Daily | G9: Cum | H9: Daily | I9: Cum | J9: Daily | K9: Cum. | L9: Final | M9: Daily | N9: Daily | O9: Cum.
C10: Size | D10: Price | E10: Amt. | F10: Used | G10: Used | H10: Rec'd | I10: Rec'd | J10: Return | K10: Return | L10: Stock | M10: Cost | N10: Cost | O10: Cost
A11: =[1]IFE!$AO$1 -> M-I BAR BULK | C11: =[1]IFE!$AO$2 -> 100. LB BG | D11: =[1]IFE!$AO$10 -> 20.25 | E11: =[1]IFE!$AO$4 -> 1153 | F11: =[1]IFE!$AO$3 -> 0 | G11: =[1]IFE!$AO$9 -> 2206 | H11: =[1]IFE!$AO$5 -> 0 | I11: =[1]IFE!$AQ2 -> 3359 | J11: =[1]IFE!$AO$6 -> 0 | K11: =[1]IFE!$AQ3 -> 0 | L11: =[1]IFE!$AO$7 -> 1153 | M11: =D11*F11 -> 0 | N11: =[1]IFE!$AO$48*F11 -> 0 | O11: =[1]IFE!$AO$48*G11 -> 40700.7
A12: =[1]IFE!$AO$11 -> SODA ASH | C12: =[1]IFE!$AO$12 -> 50. KG BG | D12: =[1]IFE!$AO$20 -> 55.51 | E12: =[1]IFE!$AO$14 -> 10 | F12: =[1]IFE!$AO$13 -> 0 | G12: =[1]IFE!$AO$19 -> 6 | H12: =[1]IFE!$AO$15 -> 0 | I12: =[1]IFE!$AQ12 -> 16 | J12: =[1]IFE!$AO$16 -> 0 | K12: =[1]IFE!$AQ13 -> 0 | L12: =[1]IFE!$AO$17 -> 10 | M12: =D12*F12 -> 0 | Q12: Before Taxes
A13: =[1]IFE!$AO$21 -> SODIUM BICARBONATE | C13: =[1]IFE!$AO$22 -> 50. LB BG | D13: =[1]IFE!$AO$30 -> 52.87 | E13: =[1]IFE!$AO$24 -> 27 | F13: =[1]IFE!$AO$23 -> 0 | G13: =[1]IFE!$AO$29 -> 0 | H13: =[1]IFE!$AO$25 -> 0 | I13: =[1]IFE!$AQ22 -> 27 | J13: =[1]IFE!$AO$26 -> 0 | K13: =[1]IFE!$AQ23 -> 0 | L13: =[1]IFE!$AO$27 -> 27 | M13: =D13*F13 -> 0 | R13: =SUM(M11:M60,M71:M120,M131:M180) -> 5749.32
A14: =[1]IFE!$AO$31 -> POLYPAC R | C14: =[1]IFE!$AO$32 -> 50. LB BG | D14: =[1]IFE!$AO$40 -> 184.5 | E14: =[1]IFE!$AO$34 -> 52 | F14: =[1]IFE!$AO$33 -> 0 | G14: =[1]IFE!$AO$39 -> 18 | H14: =[1]IFE!$AO$35 -> 0 | I14: =[1]IFE!$AQ32 -> 70 | J14: =[1]IFE!$AO$36 -> 0 | K14: =[1]IFE!$AQ33 -> 0 | L14: =[1]IFE!$AO$37 -> 52 | M14: =D14*F14 -> 0 | Q14: Before Taxes (Include Not Print Products)
A15: =[1]IFE!$AO$41 -> LOWA TECH 70/75 | C15: =[1]IFE!$AO$42 -> 50. LB BG | D15: =[1]IFE!$AO$50 -> 18.45 | E15: =[1]IFE!$AO$44 -> 112 | F15: =[1]IFE!$AO$43 -> 0 | G15: =[1]IFE!$AO$49 -> 0 | H15: =[1]IFE!$AO$45 -> 0 | I15: =[1]IFE!$AQ42 -> 224 | J15: =[1]IFE!$AO$46 -> 0 | K15: =[1]IFE!$AQ43 -> 112 | L15: =[1]IFE!$AO$47 -> 112 | M15: =D15*F15 -> 0 | R15: =SUMPRODUCT([1]IFE!$C$1201:$C$1340,[1]IFE!$N$1201:$N$1340) -> 5749.32
A16: =[1]IFE!$AO$51 -> CELL-U-SEAL FINE | C16: =[1]IFE!$AO$52 -> 30. LB BG | D16: =[1]IFE!$AO$60 -> 69.67 | E16: =[1]IFE!$AO$54 -> 114 | F16: =[1]IFE!$AO$53 -> 0 | G16: =[1]IFE!$AO$59 -> 0 | H16: =[1]IFE!$AO$55 -> 0 | I16: =[1]IFE!$AQ52 -> 114 | J16: =[1]IFE!$AO$56 -> 0 | K16: =[1]IFE!$AQ53 -> 0 | L16: =[1]IFE!$AO$57 -> 114 | M16: =D16*F16 -> 0 | N16: =[1]IFE!$AO$58*F16 -> 0 | O16: =[1]IFE!$AO$58*G16 -> 0
A17: =[1]IFE!$AO$61 -> CAUSTIC POTASH (POTASSIUM HYDROXIDE - KOH) | C17: =[1]IFE!$AO$62 -> 25. KG BG | D17: =[1]IFE!$AO$70 -> 113.32 | E17: =[1]IFE!$AO$64 -> 14 | F17: =[1]IFE!$AO$63 -> 0 | G17: =[1]IFE!$AO$69 -> 0 | H17: =[1]IFE!$AO$65 -> 0 | I17: =[1]IFE!$AQ62 -> 14 | J17: =[1]IFE!$AO$66 -> 0 | K17: =[1]IFE!$AQ63 -> 0 | L17: =[1]IFE!$AO$67 -> 14 | M17: =D17*F17 -> 0 | N17: =[1]IFE!$AO$68*F17 -> 0 | O17: =[1]IFE!$AO$68*G17 -> 0
A18: =[1]IFE!$AO$71 -> ENGINEERING SERVICE | C18: =[1]IFE!$AO$72 -> 1. EA | D18: =[1]IFE!$AO$80 -> 1485 | E18: =[1]IFE!$AO$74 -> 0 | F18: =[1]IFE!$AO$73 -> 2 | G18: =[1]IFE!$AO$79 -> 13 | H18: =[1]IFE!$AO$75 -> 0 | I18: =[1]IFE!$AQ72 -> 0 | J18: =[1]IFE!$AO$76 -> 0 | K18: =[1]IFE!$AQ73 -> 0 | L18: =[1]IFE!$AO$77 -> 2 | M18: =D18*F18 -> 2970 | N18: =[1]IFE!$AO$78*F18 -> 2970 | O18: =[1]IFE!$AO$78*G18 -> 19305
A19: =[1]IFE!$AO$81 -> BENTONITE WYOMING | C19: =[1]IFE!$AO$82 -> 100. LB BG | D19: =[1]IFE!$AO$90 -> 28.72 | E19: =[1]IFE!$AO$84 -> 58 | F19: =[1]IFE!$AO$83 -> 1 | G19: =[1]IFE!$AO$89 -> 443 | H19: =[1]IFE!$AO$85 -> 0 | I19: =[1]IFE!$AQ82 -> 500 | J19: =[1]IFE!$AO$86 -> 0 | K19: =[1]IFE!$AQ83 -> 0 | L19: =[1]IFE!$AO$87 -> 57 | M19: =D19*F19 -> 28.72 | N19: =[1]IFE!$AO$88*F19 -> 28.72 | O19: =[1]IFE!$AO$88*G19 -> 12722.96
A20: =[1]IFE!$AO$91 -> DUO-VIS | C20: =[1]IFE!$AO$92 -> 50. LB BG | D20: =[1]IFE!$AO$100 -> 550.12 | E20: =[1]IFE!$AO$94 -> 0 | F20: =[1]IFE!$AO$93 -> 0 | G20: =[1]IFE!$AO$99 -> 0 | H20: =[1]IFE!$AO$95 -> 0 | I20: =[1]IFE!$AQ92 -> 0 | J20: =[1]IFE!$AO$96 -> 0 | K20: =[1]IFE!$AQ93 -> 0 | L20: =[1]IFE!$AO$97 -> 0 | M20: =D20*F20 -> 0 | N20: =[1]IFE!$AO$98*F20 -> 0 | O20: =[1]IFE!$AO$98*G20 -> 0
A21: =[1]IFE!$AO$101 -> PIPE-LAX | C21: =[1]IFE!$AO$102 -> 55. GA DM | D21: =[1]IFE!$AO$110 -> 2385.02 | E21: =[1]IFE!$AO$104 -> 20 | F21: =[1]IFE!$AO$103 -> 0 | G21: =[1]IFE!$AO$109 -> 0 | H21: =[1]IFE!$AO$105 -> 0 | I21: =[1]IFE!$AQ102 -> 20 | J21: =[1]IFE!$AO$106 -> 0 | K21: =[1]IFE!$AQ103 -> 0 | L21: =[1]IFE!$AO$107 -> 20 | M21: =D21*F21 -> 0 | N21: =[1]IFE!$AO$108*F21 -> 0 | O21: =[1]IFE!$AO$108*G21 -> 0
A22: =[1]IFE!$AO$111 -> LIME | C22: =[1]IFE!$AO$112 -> 20. KG BG | D22: =[1]IFE!$AO$120 -> 37.43 | E22: =[1]IFE!$AO$114 -> 39 | F22: =[1]IFE!$AO$113 -> 0 | G22: =[1]IFE!$AO$119 -> 0 | H22: =[1]IFE!$AO$115 -> 0 | I22: =[1]IFE!$AQ112 -> 39 | J22: =[1]IFE!$AO$116 -> 0 | K22: =[1]IFE!$AQ113 -> 0 | L22: =[1]IFE!$AO$117 -> 39 | M22: =D22*F22 -> 0 | N22: =[1]IFE!$AO$118*F22 -> 0 | O22: =[1]IFE!$AO$118*G22 -> 0
A23: =[1]IFE!$AO$121 -> THINSMART | C23: =[1]IFE!$AO$122 -> 25. LB BG | D23: =[1]IFE!$AO$130 -> 119.83 | E23: =[1]IFE!$AO$124 -> 117 | F23: =[1]IFE!$AO$123 -> 0 | G23: =[1]IFE!$AO$129 -> 43 | H23: =[1]IFE!$AO$125 -> 0 | I23: =[1]IFE!$AQ122 -> 160 | J23: =[1]IFE!$AO$126 -> 0 | K23: =[1]IFE!$AQ123 -> 0 | L23: =[1]IFE!$AO$127 -> 117 | M23: =D23*F23 -> 0 | N23: =[1]IFE!$AO$128*F23 -> 0 | O23: =[1]IFE!$AO$128*G23 -> 5152.69
A24: =[1]IFE!$AO$131 -> CAUSTIC SODA | C24: =[1]IFE!$AO$132 -> 25. KG BG | D24: =[1]IFE!$AO$140 -> 64.72 | E24: =[1]IFE!$AO$134 -> 21 | F24: =[1]IFE!$AO$133 -> 0 | G24: =[1]IFE!$AO$139 -> 9 | H24: =[1]IFE!$AO$135 -> 0 | I24: =[1]IFE!$AQ132 -> 30 | J24: =[1]IFE!$AO$136 -> 0 | K24: =[1]IFE!$AQ133 -> 0 | L24: =[1]IFE!$AO$137 -> 21 | M24: =D24*F24 -> 0 | N24: =[1]IFE!$AO$138*F24 -> 0 | O24: =[1]IFE!$AO$138*G24 -> 582.48
A25: =[1]IFE!$AO$141 -> DRIL-KLEEN | C25: =[1]IFE!$AO$142 -> 5. GA CN | D25: =[1]IFE!$AO$150 -> 322.21 | E25: =[1]IFE!$AO$144 -> 45 | F25: =[1]IFE!$AO$143 -> 0 | G25: =[1]IFE!$AO$149 -> 0 | H25: =[1]IFE!$AO$145 -> 0 | I25: =[1]IFE!$AQ142 -> 45 | J25: =[1]IFE!$AO$146 -> 0 | K25: =[1]IFE!$AQ143 -> 0 | L25: =[1]IFE!$AO$147 -> 45 | M25: =D25*F25 -> 0 | N25: =[1]IFE!$AO$148*F25 -> 0 | O25: =[1]IFE!$AO$148*G24 -> 2899.89
A26: =[1]IFE!$AO$151 -> PECAN NUT PLUG CSE | C26: =[1]IFE!$AO$152 -> 50. LB BG | D26: =[1]IFE!$AO$160 -> 65.29 | E26: =[1]IFE!$AO$154 -> 25 | F26: =[1]IFE!$AO$153 -> 0 | G26: =[1]IFE!$AO$159 -> 0 | H26: =[1]IFE!$AO$155 -> 0 | I26: =[1]IFE!$AQ152 -> 25 | J26: =[1]IFE!$AO$156 -> 0 | K26: =[1]IFE!$AQ153 -> 0 | L26: =[1]IFE!$AO$157 -> 25 | M26: =D26*F26 -> 0 | N26: =[1]IFE!$AO$158*F26 -> 0 | O26: =[1]IFE!$AO$158*G25 -> 0
A27: =[1]IFE!$AO$161 -> G-SEAL PLUS | C27: =[1]IFE!$AO$162 -> 25. KG BG | D27: =[1]IFE!$AO$170 -> 178.41 | E27: =[1]IFE!$AO$164 -> 35 | F27: =[1]IFE!$AO$163 -> 0 | G27: =[1]IFE!$AO$169 -> 0 | H27: =[1]IFE!$AO$165 -> 0 | I27: =[1]IFE!$AQ162 -> 35 | J27: =[1]IFE!$AO$166 -> 0 | K27: =[1]IFE!$AQ163 -> 0 | L27: =[1]IFE!$AO$167 -> 35 | M27: =D27*F27 -> 0 | N27: =[1]IFE!$AO$168*F27 -> 0 | O27: =[1]IFE!$AO$168*G26 -> 0
A28: =[1]IFE!$AO$171 -> CALCIUM CARBONATE #6 | C28: =[1]IFE!$AO$172 -> 50. LB BG | D28: =[1]IFE!$AO$180 -> 18.45 | E28: =[1]IFE!$AO$174 -> 112 | F28: =[1]IFE!$AO$173 -> 0 | G28: =[1]IFE!$AO$179 -> 0 | H28: =[1]IFE!$AO$175 -> 0 | I28: =[1]IFE!$AQ172 -> 112 | J28: =[1]IFE!$AO$176 -> 0 | K28: =[1]IFE!$AQ173 -> 0 | L28: =[1]IFE!$AO$177 -> 112 | M28: =D28*F28 -> 0 | N28: =[1]IFE!$AO$178*F28 -> 0 | O28: =[1]IFE!$AO$178*G27 -> 0
A29: =[1]IFE!$AO$181 -> DUO-VIS | C29: =[1]IFE!$AO$182 -> 25. KG BG | D29: =[1]IFE!$AO$190 -> 550.12 | E29: =[1]IFE!$AO$184 -> 56 | F29: =[1]IFE!$AO$183 -> 5 | G29: =[1]IFE!$AO$189 -> 7 | H29: =[1]IFE!$AO$185 -> 0 | I29: =[1]IFE!$AQ182 -> 58 | J29: =[1]IFE!$AO$186 -> 0 | K29: =[1]IFE!$AQ183 -> 0 | L29: =[1]IFE!$AO$187 -> 51 | M29: =D29*F29 -> 2750.6 | N29: =[1]IFE!$AO$198*F29 -> 0 | O29: =[1]IFE!$AO$188*G28 -> 0
A30: =[1]IFE!$AO$191 -> 0 | C30: =[1]IFE!$AO$192 -> 0 | D30: =[1]IFE!$AO$200 -> 0 | E30: =[1]IFE!$AO$194 -> 0 | F30: =[1]IFE!$AO$193 -> 0 | G30: =[1]IFE!$AO$199 -> 0 | H30: =[1]IFE!$AO$195 -> 0 | I30: =[1]IFE!$AQ192 -> 0 | J30: =[1]IFE!$AO$196 -> 0 | K30: =[1]IFE!$AQ193 -> 0 | L30: =[1]IFE!$AO$197 -> 0 | M30: =D30*F30 -> 0 | N30: =[1]IFE!$AO$208*F30 -> 0 | O30: =[1]IFE!$AO$198*G29 -> 0
A31: =[1]IFE!$AO$201 -> 0 | C31: =[1]IFE!$AO$202 -> 0 | D31: =[1]IFE!$AO$210 -> 0 | E31: =[1]IFE!$AO$204 -> 0 | F31: =[1]IFE!$AO$203 -> 0 | G31: =[1]IFE!$AO$209 -> 0 | H31: =[1]IFE!$AO$205 -> 0 | I31: =[1]IFE!$AQ202 -> 0 | J31: =[1]IFE!$AO$206 -> 0 | K31: =[1]IFE!$AQ203 -> 0 | L31: =[1]IFE!$AO$207 -> 0 | M31: =D31*F31 -> 0 | N31: =[1]IFE!$AO$218*F31 -> 0 | O31: =[1]IFE!$AO$208*G30 -> 0
A32: =[1]IFE!$AO$211 -> 0 | C32: =[1]IFE!$AO$212 -> 0 | D32: =[1]IFE!$AO$220 -> 0 | E32: =[1]IFE!$AO$214 -> 0 | F32: =[1]IFE!$AO$213 -> 0 | G32: =[1]IFE!$AO$219 -> 0 | H32: =[1]IFE!$AO$215 -> 0 | I32: =[1]IFE!$AQ212 -> 0 | J32: =[1]IFE!$AO$216 -> 0 | K32: =[1]IFE!$AQ213 -> 0 | L32: =[1]IFE!$AO$217 -> 0 | M32: =D32*F32 -> 0 | N32: =[1]IFE!$AO$228*F32 -> 0 | O32: =[1]IFE!$AO$218*G31 -> 0
A33: =[1]IFE!$AO$221 -> 0 | C33: =[1]IFE!$AO$222 -> 0 | D33: =[1]IFE!$AO$230 -> 0 | E33: =[1]IFE!$AO$224 -> 0 | F33: =[1]IFE!$AO$223 -> 0 | G33: =[1]IFE!$AO$229 -> 0 | H33: =[1]IFE!$AO$225 -> 0 | I33: =[1]IFE!$AQ222 -> 0 | J33: =[1]IFE!$AO$226 -> 0 | K33: =[1]IFE!$AQ223 -> 0 | L33: =[1]IFE!$AO$227 -> 0 | M33: =D33*F33 -> 0 | N33: =[1]IFE!$AO$238*F33 -> 0 | O33: =[1]IFE!$AO$228*G32 -> 0
A34: =[1]IFE!$AO$231 -> 0 | C34: =[1]IFE!$AO$232 -> 0 | D34: =[1]IFE!$AO$240 -> 0 | E34: =[1]IFE!$AO$234 -> 0 | F34: =[1]IFE!$AO$233 -> 0 | G34: =[1]IFE!$AO$239 -> 0 | H34: =[1]IFE!$AO$235 -> 0 | I34: =[1]IFE!$AQ232 -> 0 | J34: =[1]IFE!$AO$236 -> 0 | K34: =[1]IFE!$AQ233 -> 0 | L34: =[1]IFE!$AO$237 -> 0 | M34: =D34*F34 -> 0 | N34: =[1]IFE!$AO$248*F34 -> 0 | O34: =[1]IFE!$AO$238*G33 -> 0
A35: =[1]IFE!$AO$241 -> 0 | C35: =[1]IFE!$AO$242 -> 0 | D35: =[1]IFE!$AO$250 -> 0 | E35: =[1]IFE!$AO$244 -> 0 | F35: =[1]IFE!$AO$243 -> 0 | G35: =[1]IFE!$AO$249 -> 0 | H35: =[1]IFE!$AO$245 -> 0 | I35: =[1]IFE!$AQ242 -> 0 | J35: =[1]IFE!$AO$246 -> 0 | K35: =[1]IFE!$AQ243 -> 0 | L35: =[1]IFE!$AO$247 -> 0 | M35: =D35*F35 -> 0 | N35: =[1]IFE!$AO$258*F35 -> 0 | O35: =[1]IFE!$AO$248*G34 -> 0
A36: =[1]IFE!$AO$251 -> 0 | C36: =[1]IFE!$AO$252 -> 0 | D36: =[1]IFE!$AO$260 -> 0 | E36: =[1]IFE!$AO$254 -> 0 | F36: =[1]IFE!$AO$253 -> 0 | G36: =[1]IFE!$AO$259 -> 0 | H36: =[1]IFE!$AO$255 -> 0 | I36: =[1]IFE!$AQ252 -> 0 | J36: =[1]IFE!$AO$256 -> 0 | K36: =[1]IFE!$AQ253 -> 0 | L36: =[1]IFE!$AO$257 -> 0 | M36: =D36*F36 -> 0 | N36: =[1]IFE!$AO$268*F36 -> 0 | O36: =[1]IFE!$AO$258*G35 -> 0
A37: =[1]IFE!$AO$261 -> 0 | C37: =[1]IFE!$AO$262 -> 0 | D37: =[1]IFE!$AO$270 -> 0 | E37: =[1]IFE!$AO$264 -> 0 | F37: =[1]IFE!$AO$263 -> 0 | G37: =[1]IFE!$AO$269 -> 0 | H37: =[1]IFE!$AO$265 -> 0 | I37: =[1]IFE!$AQ262 -> 0 | J37: =[1]IFE!$AO$266 -> 0 | K37: =[1]IFE!$AQ263 -> 0 | L37: =[1]IFE!$AO$267 -> 0 | M37: =D37*F37 -> 0 | N37: =[1]IFE!$AO$278*F37 -> 0 | O37: =[1]IFE!$AO$268*G36 -> 0
A38: =[1]IFE!$AO$271 -> 0 | C38: =[1]IFE!$AO$272 -> 0 | D38: =[1]IFE!$AO$280 -> 0 | E38: =[1]IFE!$AO$274 -> 0 | F38: =[1]IFE!$AO$273 -> 0 | G38: =[1]IFE!$AO$279 -> 0 | H38: =[1]IFE!$AO$275 -> 0 | I38: =[1]IFE!$AQ272 -> 0 | J38: =[1]IFE!$AO$276 -> 0 | K38: =[1]IFE!$AQ273 -> 0 | L38: =[1]IFE!$AO$277 -> 0 | M38: =D38*F38 -> 0 | N38: =[1]IFE!$AO$288*F38 -> 0 | O38: =[1]IFE!$AO$278*G37 -> 0
A39: =[1]IFE!$AO$281 -> 0 | C39: =[1]IFE!$AO$282 -> 0 | D39: =[1]IFE!$AO$290 -> 0 | E39: =[1]IFE!$AO$284 -> 0 | F39: =[1]IFE!$AO$283 -> 0 | G39: =[1]IFE!$AO$289 -> 0 | H39: =[1]IFE!$AO$285 -> 0 | I39: =[1]IFE!$AQ282 -> 0 | J39: =[1]IFE!$AO$286 -> 0 | K39: =[1]IFE!$AQ283 -> 0 | L39: =[1]IFE!$AO$287 -> 0 | M39: =D39*F39 -> 0 | N39: =[1]IFE!$AO$298*F39 -> 0 | O39: =[1]IFE!$AO$288*G38 -> 0
A40: =[1]IFE!$AO$291 -> 0 | C40: =[1]IFE!$AO$292 -> 0 | D40: =[1]IFE!$AO$300 -> 0 | E40: =[1]IFE!$AO$294 -> 0 | F40: =[1]IFE!$AO$293 -> 0 | G40: =[1]IFE!$AO$299 -> 0 | H40: =[1]IFE!$AO$295 -> 0 | I40: =[1]IFE!$AQ292 -> 0 | J40: =[1]IFE!$AO$296 -> 0 | K40: =[1]IFE!$AQ293 -> 0 | L40: =[1]IFE!$AO$297 -> 0 | M40: =D40*F40 -> 0 | N40: =[1]IFE!$AO$308*F40 -> 0 | O40: =[1]IFE!$AO$298*G39 -> 0
A41: =[1]IFE!$AO$301 -> 0 | C41: =[1]IFE!$AO$302 -> 0 | D41: =[1]IFE!$AO$310 -> 0 | E41: =[1]IFE!$AO$304 -> 0 | F41: =[1]IFE!$AO$303 -> 0 | G41: =[1]IFE!$AO$309 -> 0 | H41: =[1]IFE!$AO$305 -> 0 | I41: =[1]IFE!$AQ302 -> 0 | J41: =[1]IFE!$AO$306 -> 0 | K41: =[1]IFE!$AQ303 -> 0 | L41: =[1]IFE!$AO$307 -> 0 | M41: =D41*F41 -> 0 | N41: =[1]IFE!$AO$318*F41 -> 0 | O41: =[1]IFE!$AO$308*G40 -> 0
A42: =[1]IFE!$AO$311 -> 0 | C42: =[1]IFE!$AO$312 -> 0 | D42: =[1]IFE!$AO$320 -> 0 | E42: =[1]IFE!$AO$314 -> 0 | F42: =[1]IFE!$AO$313 -> 0 | G42: =[1]IFE!$AO$319 -> 0 | H42: =[1]IFE!$AO$315 -> 0 | I42: =[1]IFE!$AQ312 -> 0 | J42: =[1]IFE!$AO$316 -> 0 | K42: =[1]IFE!$AQ313 -> 0 | L42: =[1]IFE!$AO$317 -> 0 | M42: =D42*F42 -> 0 | N42: =[1]IFE!$AO$328*F42 -> 0 | O42: =[1]IFE!$AO$318*G41 -> 0
A43: =[1]IFE!$AO$321 -> 0 | C43: =[1]IFE!$AO$322 -> 0 | D43: =[1]IFE!$AO$330 -> 0 | E43: =[1]IFE!$AO$324 -> 0 | F43: =[1]IFE!$AO$323 -> 0 | G43: =[1]IFE!$AO$329 -> 0 | H43: =[1]IFE!$AO$325 -> 0 | I43: =[1]IFE!$AQ322 -> 0 | J43: =[1]IFE!$AO$326 -> 0 | K43: =[1]IFE!$AQ323 -> 0 | L43: =[1]IFE!$AO$327 -> 0 | M43: =D43*F43 -> 0 | N43: =[1]IFE!$AO$338*F43 -> 0 | O43: =[1]IFE!$AO$328*G42 -> 0
A44: =[1]IFE!$AO$331 -> 0 | C44: =[1]IFE!$AO$332 -> 0 | D44: =[1]IFE!$AO$340 -> 0 | E44: =[1]IFE!$AO$334 -> 0 | F44: =[1]IFE!$AO$333 -> 0 | G44: =[1]IFE!$AO$339 -> 0 | H44: =[1]IFE!$AO$335 -> 0 | I44: =[1]IFE!$AQ332 -> 0 | J44: =[1]IFE!$AO$336 -> 0 | K44: =[1]IFE!$AQ333 -> 0 | L44: =[1]IFE!$AO$337 -> 0 | M44: =D44*F44 -> 0 | N44: =[1]IFE!$AO$348*F44 -> 0 | O44: =[1]IFE!$AO$338*G43 -> 0
A45: =[1]IFE!$AO$341 -> 0 | C45: =[1]IFE!$AO$342 -> 0 | D45: =[1]IFE!$AO$350 -> 0 | E45: =[1]IFE!$AO$344 -> 0 | F45: =[1]IFE!$AO$343 -> 0 | G45: =[1]IFE!$AO$349 -> 0 | H45: =[1]IFE!$AO$345 -> 0 | I45: =[1]IFE!$AQ342 -> 0 | J45: =[1]IFE!$AO$346 -> 0 | K45: =[1]IFE!$AQ343 -> 0 | L45: =[1]IFE!$AO$347 -> 0 | M45: =D45*F45 -> 0 | N45: =[1]IFE!$AO$358*F45 -> 0 | O45: =[1]IFE!$AO$348*G44 -> 0
A46: =[1]IFE!$AO$351 -> 0 | C46: =[1]IFE!$AO$352 -> 0 | D46: =[1]IFE!$AO$360 -> 0 | E46: =[1]IFE!$AO$354 -> 0 | F46: =[1]IFE!$AO$353 -> 0 | G46: =[1]IFE!$AO$359 -> 0 | H46: =[1]IFE!$AO$355 -> 0 | I46: =[1]IFE!$AQ352 -> 0 | J46: =[1]IFE!$AO$356 -> 0 | K46: =[1]IFE!$AQ353 -> 0 | L46: =[1]IFE!$AO$357 -> 0 | M46: =D46*F46 -> 0 | N46: =[1]IFE!$AO$368*F46 -> 0 | O46: =[1]IFE!$AO$358*G45 -> 0
A47: =[1]IFE!$AO$361 -> 0 | C47: =[1]IFE!$AO$362 -> 0 | D47: =[1]IFE!$AO$370 -> 0 | E47: =[1]IFE!$AO$364 -> 0 | F47: =[1]IFE!$AO$363 -> 0 | G47: =[1]IFE!$AO$369 -> 0 | H47: =[1]IFE!$AO$365 -> 0 | I47: =[1]IFE!$AQ362 -> 0 | J47: =[1]IFE!$AO$366 -> 0 | K47: =[1]IFE!$AQ363 -> 0 | L47: =[1]IFE!$AO$367 -> 0 | M47: =D47*F47 -> 0 | N47: =[1]IFE!$AO$378*F47 -> 0 | O47: =[1]IFE!$AO$368*G46 -> 0
A48: =[1]IFE!$AO$371 -> 0 | C48: =[1]IFE!$AO$372 -> 0 | D48: =[1]IFE!$AO$380 -> 0 | E48: =[1]IFE!$AO$374 -> 0 | F48: =[1]IFE!$AO$373 -> 0 | G48: =[1]IFE!$AO$379 -> 0 | H48: =[1]IFE!$AO$375 -> 0 | I48: =[1]IFE!$AQ372 -> 0 | J48: =[1]IFE!$AO$376 -> 0 | K48: =[1]IFE!$AQ373 -> 0 | L48: =[1]IFE!$AO$377 -> 0 | M48: =D48*F48 -> 0 | N48: =[1]IFE!$AO$388*F48 -> 0 | O48: =[1]IFE!$AO$378*G47 -> 0
A49: =[1]IFE!$AO$381 -> 0 | C49: =[1]IFE!$AO$382 -> 0 | D49: =[1]IFE!$AO$390 -> 0 | E49: =[1]IFE!$AO$384 -> 0 | F49: =[1]IFE!$AO$383 -> 0 | G49: =[1]IFE!$AO$389 -> 0 | H49: =[1]IFE!$AO$385 -> 0 | I49: =[1]IFE!$AQ382 -> 0 | J49: =[1]IFE!$AO$386 -> 0 | K49: =[1]IFE!$AQ383 -> 0 | L49: =[1]IFE!$AO$387 -> 0 | M49: =D49*F49 -> 0 | N49: =[1]IFE!$AO$398*F49 -> 0 | O49: =[1]IFE!$AO$388*G48 -> 0
A50: =[1]IFE!$AO$391 -> 0 | C50: =[1]IFE!$AO$392 -> 0 | D50: =[1]IFE!$AO$400 -> 0 | E50: =[1]IFE!$AO$394 -> 0 | F50: =[1]IFE!$AO$393 -> 0 | G50: =[1]IFE!$AO$399 -> 0 | H50: =[1]IFE!$AO$395 -> 0 | I50: =[1]IFE!$AQ392 -> 0 | J50: =[1]IFE!$AO$396 -> 0 | K50: =[1]IFE!$AQ393 -> 0 | L50: =[1]IFE!$AO$397 -> 0 | M50: =D50*F50 -> 0 | N50: =[1]IFE!$AO$408*F50 -> 0 | O50: =[1]IFE!$AO$398*G49 -> 0
A51: =[1]IFE!$AO$401 -> 0 | C51: =[1]IFE!$AO$402 -> 0 | D51: =[1]IFE!$AO$410 -> 0 | E51: =[1]IFE!$AO$404 -> 0 | F51: =[1]IFE!$AO$403 -> 0 | G51: =[1]IFE!$AO$409 -> 0 | H51: =[1]IFE!$AO$405 -> 0 | I51: =[1]IFE!$AQ402 -> 0 | J51: =[1]IFE!$AO$406 -> 0 | K51: =[1]IFE!$AQ403 -> 0 | L51: =[1]IFE!$AO$407 -> 0 | M51: =D51*F51 -> 0 | N51: =[1]IFE!$AO$418*F51 -> 0 | O51: =[1]IFE!$AO$408*G50 -> 0
A52: =[1]IFE!$AO$411 -> 0 | C52: =[1]IFE!$AO$412 -> 0 | D52: =[1]IFE!$AO$420 -> 0 | E52: =[1]IFE!$AO$414 -> 0 | F52: =[1]IFE!$AO$413 -> 0 | G52: =[1]IFE!$AO$419 -> 0 | H52: =[1]IFE!$AO$415 -> 0 | I52: =[1]IFE!$AQ412 -> 0 | J52: =[1]IFE!$AO$416 -> 0 | K52: =[1]IFE!$AQ413 -> 0 | L52: =[1]IFE!$AO$417 -> 0 | M52: =D52*F52 -> 0 | N52: =[1]IFE!$AO$428*F52 -> 0 | O52: =[1]IFE!$AO$418*G51 -> 0
A53: =[1]IFE!$AO$421 -> 0 | C53: =[1]IFE!$AO$422 -> 0 | D53: =[1]IFE!$AO$430 -> 0 | E53: =[1]IFE!$AO$424 -> 0 | F53: =[1]IFE!$AO$423 -> 0 | G53: =[1]IFE!$AO$429 -> 0 | H53: =[1]IFE!$AO$425 -> 0 | I53: =[1]IFE!$AQ422 -> 0 | J53: =[1]IFE!$AO$426 -> 0 | K53: =[1]IFE!$AQ423 -> 0 | L53: =[1]IFE!$AO$427 -> 0 | M53: =D53*F53 -> 0 | N53: =[1]IFE!$AO$438*F53 -> 0 | O53: =[1]IFE!$AO$428*G52 -> 0
A54: =[1]IFE!$AO$431 -> 0 | C54: =[1]IFE!$AO$432 -> 0 | D54: =[1]IFE!$AO$440 -> 0 | E54: =[1]IFE!$AO$434 -> 0 | F54: =[1]IFE!$AO$433 -> 0 | G54: =[1]IFE!$AO$439 -> 0 | H54: =[1]IFE!$AO$435 -> 0 | I54: =[1]IFE!$AQ432 -> 0 | J54: =[1]IFE!$AO$436 -> 0 | K54: =[1]IFE!$AQ433 -> 0 | L54: =[1]IFE!$AO$437 -> 0 | M54: =D54*F54 -> 0 | N54: =[1]IFE!$AO$448*F54 -> 0 | O54: =[1]IFE!$AO$438*G53 -> 0
A55: =[1]IFE!$AO$441 -> 0 | C55: =[1]IFE!$AO$442 -> 0 | D55: =[1]IFE!$AO$450 -> 0 | E55: =[1]IFE!$AO$444 -> 0 | F55: =[1]IFE!$AO$443 -> 0 | G55: =[1]IFE!$AO$449 -> 0 | H55: =[1]IFE!$AO$445 -> 0 | I55: =[1]IFE!$AQ442 -> 0 | J55: =[1]IFE!$AO$446 -> 0 | K55: =[1]IFE!$AQ443 -> 0 | L55: =[1]IFE!$AO$447 -> 0 | M55: =D55*F55 -> 0 | N55: =[1]IFE!$AO$458*F55 -> 0 | O55: =[1]IFE!$AO$448*G54 -> 0
A56: =[1]IFE!$AO$451 -> 0 | C56: =[1]IFE!$AO$452 -> 0 | D56: =[1]IFE!$AO$460 -> 0 | E56: =[1]IFE!$AO$454 -> 0 | F56: =[1]IFE!$AO$453 -> 0 | G56: =[1]IFE!$AO$459 -> 0 | H56: =[1]IFE!$AO$455 -> 0 | I56: =[1]IFE!$AQ452 -> 0 | J56: =[1]IFE!$AO$456 -> 0 | K56: =[1]IFE!$AQ453 -> 0 | L56: =[1]IFE!$AO$457 -> 0 | M56: =D56*F56 -> 0 | N56: =[1]IFE!$AO$468*F56 -> 0 | O56: =[1]IFE!$AO$458*G55 -> 0
A57: =[1]IFE!$AO$461 -> 0 | C57: =[1]IFE!$AO$462 -> 0 | D57: =[1]IFE!$AO$470 -> 0 | E57: =[1]IFE!$AO$464 -> 0 | F57: =[1]IFE!$AO$463 -> 0 | G57: =[1]IFE!$AO$469 -> 0 | H57: =[1]IFE!$AO$465 -> 0 | I57: =[1]IFE!$AQ462 -> 0 | J57: =[1]IFE!$AO$466 -> 0 | K57: =[1]IFE!$AQ463 -> 0 | L57: =[1]IFE!$AO$467 -> 0 | M57: =D57*F57 -> 0 | N57: =[1]IFE!$AO$478*F57 -> 0 | O57: =[1]IFE!$AO$468*G56 -> 0
A58: =[1]IFE!$AO$471 -> 0 | C58: =[1]IFE!$AO$472 -> 0 | D58: =[1]IFE!$AO$480 -> 0 | E58: =[1]IFE!$AO$474 -> 0 | F58: =[1]IFE!$AO$473 -> 0 | G58: =[1]IFE!$AO$479 -> 0 | H58: =[1]IFE!$AO$475 -> 0 | I58: =[1]IFE!$AQ472 -> 0 | J58: =[1]IFE!$AO$476 -> 0 | K58: =[1]IFE!$AQ473 -> 0 | L58: =[1]IFE!$AO$477 -> 0 | M58: =D58*F58 -> 0 | N58: =[1]IFE!$AO$488*F58 -> 0 | O58: =[1]IFE!$AO$478*G57 -> 0
A59: =[1]IFE!$AO$481 -> 0 | C59: =[1]IFE!$AO$482 -> 0 | D59: =[1]IFE!$AO$490 -> 0 | E59: =[1]IFE!$AO$484 -> 0 | F59: =[1]IFE!$AO$483 -> 0 | G59: =[1]IFE!$AO$489 -> 0 | H59: =[1]IFE!$AO$485 -> 0 | I59: =[1]IFE!$AQ482 -> 0 | J59: =[1]IFE!$AO$486 -> 0 | K59: =[1]IFE!$AQ483 -> 0 | L59: =[1]IFE!$AO$487 -> 0 | M59: =D59*F59 -> 0 | N59: =[1]IFE!$AO$498*F59 -> 0 | O59: =[1]IFE!$AO$488*G58 -> 0
A60: =[1]IFE!$AO$491 -> 0 | C60: =[1]IFE!$AO$492 -> 0 | D60: =[1]IFE!$AO$500 -> 0 | E60: =[1]IFE!$AO$494 -> 0 | F60: =[1]IFE!$AO$493 -> 0 | G60: =[1]IFE!$AO$499 -> 0 | H60: =[1]IFE!$AO$495 -> 0 | I60: =[1]IFE!$AQ492 -> 0 | J60: =[1]IFE!$AO$496 -> 0 | K60: =[1]IFE!$AQ493 -> 0 | L60: =[1]IFE!$AO$497 -> 0 | M60: =D60*F60 -> 0 | N60: =[1]IFE!$AO$508*F60 -> 0 | O60: =[1]IFE!$AO$498*G59 -> 0
G61: WELLSITE CHEMICAL INVENTORY | N61: =[1]IFE!$AO$538*F73 -> 0 | O61: =[1]IFE!$AO$528*G72 -> 0
G62: Daily Report | N62: =[1]IFE!$AO$548*F74 -> 0 | O62: =[1]IFE!$AO$538*G73 -> 0
B63: Operator : | C63: =[1]IFE!$B$6 -> Cardon IV | I63: Date : | J63: =[1]IFE!$B$119 -> 39989 | N63: =[1]IFE!$AO$568*F76 -> 0 | O63: =[1]IFE!$AO$558*G75 -> 0
B64: Well Name : | C64: =[1]IFE!$B$8 -> Perla-1X | I64: Report No: | J64: =[1]IFE!$B$166 -> 9 | N64: =[1]IFE!$AO$578*F77 -> 0 | O64: =[1]IFE!$AO$568*G76 -> 0
B65: Location: | C65: =[1]IFE!$B$11 -> Offshore | I65: Page | J65: 2 | N65: =[1]IFE!$AO$588*F78 -> 0 | O65: =[1]IFE!$AO$578*G77 -> 0
E66: Cost Summary | N66: =[1]IFE!$AO$628*F82 -> 0 | O66: =[1]IFE!$AO$618*G81 -> 0
D67: Total Daily Cost: | F67: =$F$7 -> 5749.32 | J67: Total Daily Tax: | K67: =$K$7 -> 0
D68: Cumulative Cost: | F68: =$F$8 -> 89939.53
A69: Product | C69: Unit | D69: Unit | E69: Start | F69: Daily | G69: Cum | H69: Daily | I69: Cum | J69: Daily | K69: Cum. | L69: Final | M69: Daily
C70: Size | D70: Price | E70: Amt. | F70: Used | G70: Used | H70: Rec'd | I70: Rec'd | J70: Return | K70: Return | L70: Stock | M70: Cost
A71: =[1]IFE!$AO$501 -> 0 | C71: =[1]IFE!$AO$502 -> 0 | D71: =[1]IFE!$AO$510 -> 0 | E71: =[1]IFE!$AO$504 -> 0 | F71: =[1]IFE!$AO$503 -> 0 | G71: =[1]IFE!$AO$509 -> 0 | H71: =[1]IFE!$AO$505 -> 0 | I71: =[1]IFE!$AQ502 -> 0 | J71: =[1]IFE!$AO$506 -> 0 | K71: =[1]IFE!$AQ503 -> 0 | L71: =[1]IFE!$AO$507 -> 0 | M71: =D71*F71 -> 0
A72: =[1]IFE!$AO$511 -> 0 | C72: =[1]IFE!$AO$512 -> 0 | D72: =[1]IFE!$AO$520 -> 0 | E72: =[1]IFE!$AO$514 -> 0 | F72: =[1]IFE!$AO$513 -> 0 | G72: =[1]IFE!$AO$519 -> 0 | H72: =[1]IFE!$AO$515 -> 0 | I72: =[1]IFE!$AQ512 -> 0 | J72: =[1]IFE!$AO$516 -> 0 | K72: =[1]IFE!$AQ513 -> 0 | L72: =[1]IFE!$AO$517 -> 0 | M72: =D72*F72 -> 0
A73: =[1]IFE!$AO$521 -> 0 | C73: =[1]IFE!$AO$522 -> 0 | D73: =[1]IFE!$AO$530 -> 0 | E73: =[1]IFE!$AO$524 -> 0 | F73: =[1]IFE!$AO$523 -> 0 | G73: =[1]IFE!$AO$529 -> 0 | H73: =[1]IFE!$AO$525 -> 0 | I73: =[1]IFE!$AQ522 -> 0 | J73: =[1]IFE!$AO$526 -> 0 | K73: =[1]IFE!$AQ523 -> 0 | L73: =[1]IFE!$AO$527 -> 0 | M73: =D73*F73 -> 0
A74: =[1]IFE!$AO$531 -> 0 | C74: =[1]IFE!$AO$532 -> 0 | D74: =[1]IFE!$AO$540 -> 0 | E74: =[1]IFE!$AO$534 -> 0 | F74: =[1]IFE!$AO$533 -> 0 | G74: =[1]IFE!$AO$539 -> 0 | H74: =[1]IFE!$AO$535 -> 0 | I74: =[1]IFE!$AQ532 -> 0 | J74: =[1]IFE!$AO$536 -> 0 | K74: =[1]IFE!$AQ533 -> 0 | L74: =[1]IFE!$AO$537 -> 0 | M74: =D74*F74 -> 0
A75: =[1]IFE!$AO$541 -> 0 | C75: =[1]IFE!$AO$542 -> 0 | D75: =[1]IFE!$AO$550 -> 0 | E75: =[1]IFE!$AO$544 -> 0 | F75: =[1]IFE!$AO$543 -> 0 | G75: =[1]IFE!$AO$549 -> 0 | H75: =[1]IFE!$AO$545 -> 0 | I75: =[1]IFE!$AQ542 -> 0 | J75: =[1]IFE!$AO$546 -> 0 | K75: =[1]IFE!$AQ543 -> 0 | L75: =[1]IFE!$AO$547 -> 0 | M75: =D75*F75 -> 0
A76: =[1]IFE!$AO$551 -> 0 | C76: =[1]IFE!$AO$552 -> 0 | D76: =[1]IFE!$AO$560 -> 0 | E76: =[1]IFE!$AO$554 -> 0 | F76: =[1]IFE!$AO$553 -> 0 | G76: =[1]IFE!$AO$559 -> 0 | H76: =[1]IFE!$AO$555 -> 0 | I76: =[1]IFE!$AQ552 -> 0 | J76: =[1]IFE!$AO$556 -> 0 | K76: =[1]IFE!$AQ553 -> 0 | L76: =[1]IFE!$AO$557 -> 0 | M76: =D76*F76 -> 0
A77: =[1]IFE!$AO$561 -> 0 | C77: =[1]IFE!$AO$562 -> 0 | D77: =[1]IFE!$AO$570 -> 0 | E77: =[1]IFE!$AO$564 -> 0 | F77: =[1]IFE!$AO$563 -> 0 | G77: =[1]IFE!$AO$569 -> 0 | H77: =[1]IFE!$AO$565 -> 0 | I77: =[1]IFE!$AQ562 -> 0 | J77: =[1]IFE!$AO$566 -> 0 | K77: =[1]IFE!$AQ563 -> 0 | L77: =[1]IFE!$AO$567 -> 0 | M77: =D77*F77 -> 0
A78: =[1]IFE!$AO$571 -> 0 | C78: =[1]IFE!$AO$572 -> 0 | D78: =[1]IFE!$AO$580 -> 0 | E78: =[1]IFE!$AO$574 -> 0 | F78: =[1]IFE!$AO$573 -> 0 | G78: =[1]IFE!$AO$579 -> 0 | H78: =[1]IFE!$AO$575 -> 0 | I78: =[1]IFE!$AQ572 -> 0 | J78: =[1]IFE!$AO$576 -> 0 | K78: =[1]IFE!$AQ573 -> 0 | L78: =[1]IFE!$AO$577 -> 0 | M78: =D78*F78 -> 0
A79: =[1]IFE!$AO$581 -> 0 | C79: =[1]IFE!$AO$582 -> 0 | D79: =[1]IFE!$AO$590 -> 0 | E79: =[1]IFE!$AO$584 -> 0 | F79: =[1]IFE!$AO$583 -> 0 | G79: =[1]IFE!$AO$589 -> 0 | H79: =[1]IFE!$AO$585 -> 0 | I79: =[1]IFE!$AQ582 -> 0 | J79: =[1]IFE!$AO$586 -> 0 | K79: =[1]IFE!$AQ583 -> 0 | L79: =[1]IFE!$AO$587 -> 0 | M79: =D79*F79 -> 0
A80: =[1]IFE!$AO$591 -> 0 | C80: =[1]IFE!$AO$592 -> 0 | D80: =[1]IFE!$AO$600 -> 0 | E80: =[1]IFE!$AO$594 -> 0 | F80: =[1]IFE!$AO$593 -> 0 | G80: =[1]IFE!$AO$599 -> 0 | H80: =[1]IFE!$AO$595 -> 0 | I80: =[1]IFE!$AQ592 -> 0 | J80: =[1]IFE!$AO$596 -> 0 | K80: =[1]IFE!$AQ593 -> 0 | L80: =[1]IFE!$AO$597 -> 0 | M80: =D80*F80 -> 0
A81: =[1]IFE!$AO$601 -> 0 | C81: =[1]IFE!$AO$602 -> 0 | D81: =[1]IFE!$AO$610 -> 0 | E81: =[1]IFE!$AO$604 -> 0 | F81: =[1]IFE!$AO$603 -> 0 | G81: =[1]IFE!$AO$609 -> 0 | H81: =[1]IFE!$AO$605 -> 0 | I81: =[1]IFE!$AQ602 -> 0 | J81: =[1]IFE!$AO$606 -> 0 | K81: =[1]IFE!$AQ603 -> 0 | L81: =[1]IFE!$AO$607 -> 0 | M81: =D81*F81 -> 0
A82: =[1]IFE!$AO$611 -> 0 | C82: =[1]IFE!$AO$612 -> 0 | D82: =[1]IFE!$AO$620 -> 0 | E82: =[1]IFE!$AO$614 -> 0 | F82: =[1]IFE!$AO$613 -> 0 | G82: =[1]IFE!$AO$619 -> 0 | H82: =[1]IFE!$AO$615 -> 0 | I82: =[1]IFE!$AQ612 -> 0 | J82: =[1]IFE!$AO$616 -> 0 | K82: =[1]IFE!$AQ613 -> 0 | L82: =[1]IFE!$AO$617 -> 0 | M82: =D82*F82 -> 0
A83: =[1]IFE!$AO$621 -> 0 | C83: =[1]IFE!$AO$622 -> 0 | D83: =[1]IFE!$AO$630 -> 0 | E83: =[1]IFE!$AO$624 -> 0 | F83: =[1]IFE!$AO$623 -> 0 | G83: =[1]IFE!$AO$629 -> 0 | H83: =[1]IFE!$AO$625 -> 0 | I83: =[1]IFE!$AQ622 -> 0 | J83: =[1]IFE!$AO$626 -> 0 | K83: =[1]IFE!$AQ623 -> 0 | L83: =[1]IFE!$AO$627 -> 0 | M83: =D83*F83 -> 0
A84: =[1]IFE!$AO$631 -> 0 | C84: =[1]IFE!$AO$632 -> 0 | D84: =[1]IFE!$AO$640 -> 0 | E84: =[1]IFE!$AO$634 -> 0 | F84: =[1]IFE!$AO$633 -> 0 | G84: =[1]IFE!$AO$639 -> 0 | H84: =[1]IFE!$AO$635 -> 0 | I84: =[1]IFE!$AQ632 -> 0 | J84: =[1]IFE!$AO$636 -> 0 | K84: =[1]IFE!$AQ633 -> 0 | L84: =[1]IFE!$AO$637 -> 0 | M84: =D84*F84 -> 0
A85: =[1]IFE!$AO$641 -> 0 | C85: =[1]IFE!$AO$642 -> 0 | D85: =[1]IFE!$AO$650 -> 0 | E85: =[1]IFE!$AO$644 -> 0 | F85: =[1]IFE!$AO$643 -> 0 | G85: =[1]IFE!$AO$649 -> 0 | H85: =[1]IFE!$AO$645 -> 0 | I85: =[1]IFE!$AQ642 -> 0 | J85: =[1]IFE!$AO$646 -> 0 | K85: =[1]IFE!$AQ643 -> 0 | L85: =[1]IFE!$AO$647 -> 0 | M85: =D85*F85 -> 0
A86: =[1]IFE!$AO$651 -> 0 | C86: =[1]IFE!$AO$652 -> 0 | D86: =[1]IFE!$AO$660 -> 0 | E86: =[1]IFE!$AO$654 -> 0 | F86: =[1]IFE!$AO$653 -> 0 | G86: =[1]IFE!$AO$659 -> 0 | H86: =[1]IFE!$AO$655 -> 0 | I86: =[1]IFE!$AQ652 -> 0 | J86: =[1]IFE!$AO$656 -> 0 | K86: =[1]IFE!$AQ653 -> 0 | L86: =[1]IFE!$AO$657 -> 0 | M86: =D86*F86 -> 0
A87: =[1]IFE!$AO$661 -> 0 | C87: =[1]IFE!$AO$662 -> 0 | D87: =[1]IFE!$AO$670 -> 0 | E87: =[1]IFE!$AO$664 -> 0 | F87: =[1]IFE!$AO$663 -> 0 | G87: =[1]IFE!$AO$669 -> 0 | H87: =[1]IFE!$AO$665 -> 0 | I87: =[1]IFE!$AQ662 -> 0 | J87: =[1]IFE!$AO$666 -> 0 | K87: =[1]IFE!$AQ663 -> 0 | L87: =[1]IFE!$AO$667 -> 0 | M87: =D87*F87 -> 0
A88: =[1]IFE!$AO$671 -> 0 | C88: =[1]IFE!$AO$672 -> 0 | D88: =[1]IFE!$AO$680 -> 0 | E88: =[1]IFE!$AO$674 -> 0 | F88: =[1]IFE!$AO$673 -> 0 | G88: =[1]IFE!$AO$679 -> 0 | H88: =[1]IFE!$AO$675 -> 0 | I88: =[1]IFE!$AQ672 -> 0 | J88: =[1]IFE!$AO$676 -> 0 | K88: =[1]IFE!$AQ673 -> 0 | L88: =[1]IFE!$AO$677 -> 0 | M88: =D88*F88 -> 0
A89: =[1]IFE!$AO$681 -> 0 | C89: =[1]IFE!$AO$682 -> 0 | D89: =[1]IFE!$AO$690 -> 0 | E89: =[1]IFE!$AO$684 -> 0 | F89: =[1]IFE!$AO$683 -> 0 | G89: =[1]IFE!$AO$689 -> 0 | H89: =[1]IFE!$AO$685 -> 0 | I89: =[1]IFE!$AQ682 -> 0 | J89: =[1]IFE!$AO$686 -> 0 | K89: =[1]IFE!$AQ683 -> 0 | L89: =[1]IFE!$AO$687 -> 0 | M89: =D89*F89 -> 0
A90: =[1]IFE!AO691 -> 0 | C90: =[1]IFE!$AO$692 -> 0 | D90: =[1]IFE!$AO$700 -> 0 | E90: =[1]IFE!$AO$694 -> 0 | F90: =[1]IFE!$AO$693 -> 0 | G90: =[1]IFE!$AO$699 -> 0 | H90: =[1]IFE!$AO$695 -> 0 | I90: =[1]IFE!$AQ692 -> 0 | J90: =[1]IFE!$AO$696 -> 0 | K90: =[1]IFE!$AQ693 -> 0 | L90: =[1]IFE!$AO$697 -> 0 | M90: =D90*F90 -> 0
A91: =[1]IFE!AO701 -> 0 | C91: =[1]IFE!$AO$702 -> 0 | D91: =[1]IFE!$AO$710 -> 0 | E91: =[1]IFE!$AO$704 -> 0 | F91: =[1]IFE!$AO$703 -> 0 | G91: =[1]IFE!$AO$709 -> 0 | H91: =[1]IFE!$AO$705 -> 0 | I91: =[1]IFE!$AQ702 -> 0 | J91: =[1]IFE!$AO$706 -> 0 | K91: =[1]IFE!$AQ703 -> 0 | L91: =[1]IFE!$AO$707 -> 0 | M91: =D91*F91 -> 0
A92: =[1]IFE!AO711 -> 0 | C92: =[1]IFE!$AO$712 -> 0 | D92: =[1]IFE!$AO$720 -> 0 | E92: =[1]IFE!$AO$714 -> 0 | F92: =[1]IFE!$AO$713 -> 0 | G92: =[1]IFE!$AO$719 -> 0 | H92: =[1]IFE!$AO$715 -> 0 | I92: =[1]IFE!$AQ712 -> 0 | J92: =[1]IFE!$AO$716 -> 0 | K92: =[1]IFE!$AQ713 -> 0 | L92: =[1]IFE!$AO$717 -> 0 | M92: =D92*F92 -> 0
A93: =[1]IFE!AO721 -> 0 | C93: =[1]IFE!$AO$722 -> 0 | D93: =[1]IFE!$AO$730 -> 0 | E93: =[1]IFE!$AO$724 -> 0 | F93: =[1]IFE!$AO$723 -> 0 | G93: =[1]IFE!$AO$729 -> 0 | H93: =[1]IFE!$AO$725 -> 0 | I93: =[1]IFE!$AQ722 -> 0 | J93: =[1]IFE!$AO$726 -> 0 | K93: =[1]IFE!$AQ723 -> 0 | L93: =[1]IFE!$AO$727 -> 0 | M93: =D93*F93 -> 0
A94: =[1]IFE!AO731 -> 0 | C94: =[1]IFE!$AO$732 -> 0 | D94: =[1]IFE!$AO$740 -> 0 | E94: =[1]IFE!$AO$734 -> 0 | F94: =[1]IFE!$AO$733 -> 0 | G94: =[1]IFE!$AO$739 -> 0 | H94: =[1]IFE!$AO$735 -> 0 | I94: =[1]IFE!$AQ732 -> 0 | J94: =[1]IFE!$AO$736 -> 0 | K94: =[1]IFE!$AQ733 -> 0 | L94: =[1]IFE!$AO$737 -> 0 | M94: =D94*F94 -> 0
A95: =[1]IFE!AO741 -> 0 | C95: =[1]IFE!$AO$742 -> 0 | D95: =[1]IFE!$AO$750 -> 0 | E95: =[1]IFE!$AO$744 -> 0 | F95: =[1]IFE!$AO$743 -> 0 | G95: =[1]IFE!$AO$749 -> 0 | H95: =[1]IFE!$AO$745 -> 0 | I95: =[1]IFE!$AQ742 -> 0 | J95: =[1]IFE!$AO$746 -> 0 | K95: =[1]IFE!$AQ743 -> 0 | L95: =[1]IFE!$AO$747 -> 0 | M95: =D95*F95 -> 0
A96: =[1]IFE!AO751 -> 0 | C96: =[1]IFE!$AO$752 -> 0 | D96: =[1]IFE!$AO$760 -> 0 | E96: =[1]IFE!$AO$754 -> 0 | F96: =[1]IFE!$AO$753 -> 0 | G96: =[1]IFE!$AO$759 -> 0 | H96: =[1]IFE!$AO$755 -> 0 | I96: =[1]IFE!$AQ752 -> 0 | J96: =[1]IFE!$AO$756 -> 0 | K96: =[1]IFE!$AQ753 -> 0 | L96: =[1]IFE!$AO$757 -> 0 | M96: =D96*F96 -> 0
A97: =[1]IFE!AO761 -> 0 | C97: =[1]IFE!$AO$762 -> 0 | D97: =[1]IFE!$AO$770 -> 0 | E97: =[1]IFE!$AO$764 -> 0 | F97: =[1]IFE!$AO$763 -> 0 | G97: =[1]IFE!$AO$769 -> 0 | H97: =[1]IFE!$AO$765 -> 0 | I97: =[1]IFE!$AQ762 -> 0 | J97: =[1]IFE!$AO$766 -> 0 | K97: =[1]IFE!$AQ763 -> 0 | L97: =[1]IFE!$AO$767 -> 0 | M97: =D97*F97 -> 0
A98: =[1]IFE!AO771 -> 0 | C98: =[1]IFE!$AO$772 -> 0 | D98: =[1]IFE!$AO$780 -> 0 | E98: =[1]IFE!$AO$774 -> 0 | F98: =[1]IFE!$AO$773 -> 0 | G98: =[1]IFE!$AO$779 -> 0 | H98: =[1]IFE!$AO$775 -> 0 | I98: =[1]IFE!$AQ772 -> 0 | J98: =[1]IFE!$AO$776 -> 0 | K98: =[1]IFE!$AQ773 -> 0 | L98: =[1]IFE!$AO$777 -> 0 | M98: =D98*F98 -> 0
A99: =[1]IFE!AO781 -> 0 | C99: =[1]IFE!$AO$782 -> 0 | D99: =[1]IFE!$AO$790 -> 0 | E99: =[1]IFE!$AO$784 -> 0 | F99: =[1]IFE!$AO$783 -> 0 | G99: =[1]IFE!$AO$789 -> 0 | H99: =[1]IFE!$AO$785 -> 0 | I99: =[1]IFE!$AQ782 -> 0 | J99: =[1]IFE!$AO$786 -> 0 | K99: =[1]IFE!$AQ783 -> 0 | L99: =[1]IFE!$AO$787 -> 0 | M99: =D99*F99 -> 0
A100: =[1]IFE!AO791 -> 0 | C100: =[1]IFE!$AO$792 -> 0 | D100: =[1]IFE!$AO$800 -> 0 | E100: =[1]IFE!$AO$794 -> 0 | F100: =[1]IFE!$AO$793 -> 0 | G100: =[1]IFE!$AO$799 -> 0 | H100: =[1]IFE!$AO$795 -> 0 | I100: =[1]IFE!$AQ792 -> 0 | J100: =[1]IFE!$AO$796 -> 0 | K100: =[1]IFE!$AQ793 -> 0 | L100: =[1]IFE!$AO$797 -> 0 | M100: =D100*F100 -> 0
...

Sheet Chem. Inv (DF-Order by Name)
G1: WELLSITE CHEMICAL INVENTORY
G2: Daily Report
B3: Operator : | C3: Cardon IV | I3: Date : | J3: 39996
B4: Well Name : | C4: Perla-1X | I4: Report No: | J4: 16
B5: Location: | C5: Offshore | I5: Page | J5: 1
E6: Cost Summary
D7: Total Daily Cost: | F7: 10960.5 | J7: Total Daily Tax: | K7: 0
D8: Cumulative Cost: | F8: 160863.84
A9: Product | C9: Unit | D9: Unit | E9: Start | F9: Daily | G9: Cum | H9: Daily | I9: Cum | J9: Daily | K9: Cum. | L9: Final | M9: Daily | N9: Daily | O9: Cum.
C10: Size | D10: Price | E10: Amt. | F10: Used | G10: Used | H10: Rec'd | I10: Rec'd | J10: Return | K10: Return | L10: Stock | M10: Cost | N10: Cost | O10: Cost
A11: BENTONITE WYOMING | C11: 100. LB BG | D11: 28.72 | E11: 55 | F11: 0 | G11: 445 | H11: 0 | I11: 500 | J11: 0 | K11: 0 | L11: 55 | M11: 0 | N11: 0 | O11: 8210.25
A12: CALCIUM CARBONATE #6 | C12: 50. LB BG | D12: 18.45 | E12: 112 | F12: 0 | G12: 0 | H12: 0 | I12: 112 | J12: 0 | K12: 0 | L12: 112 | M12: 0
A13: CAUSTIC POTASH (POTASSIUM HYDROXIDE - KOH) | C13: 25. KG BG | D13: 113.32 | E13: 14 | F13: 0 | G13: 0 | H13: 0 | I13: 14 | J13: 0 | K13: 0 | L13: 14 | M13: 0
A14: CAUSTIC SODA | C14: 25. KG BG | D14: 64.72 | E14: 9 | F14: 7 | G14: 28 | H14: 0 | I14: 30 | J14: 0 | K14: 0 | L14: 2 | M14: 453.04
A15: CELL-U-SEAL FINE | C15: 30. LB BG | D15: 69.67 | E15: 114 | F15: 0 | G15: 0 | H15: 0 | I15: 114 | J15: 0 | K15: 0 | L15: 114 | M15: 0
A16: DEFOAM X | C16: 5. GA CN | D16: 387.61 | E16: 21 | F16: 0 | G16: 9 | H16: 0 | I16: 30 | J16: 0 | K16: 0 | L16: 21 | M16: 0 | N16: 0 | O16: 627.03
A17: DRIL-KLEEN | C17: 5. GA CN | D17: 322.21 | E17: 20 | F17: 0 | G17: 2 | H17: 0 | I17: 45 | J17: 0 | K17: 23 | L17: 20 | M17: 0 | N17: 0 | O17: 226.64
A18: DUO-VIS | C18: 25. KG BG | D18: 550.12 | E18: 10 | F18: 8 | G18: 56 | H18: 30 | I18: 88 | J18: 0 | K18: 0 | L18: 32 | M18: 4400.96 | N18: 11880 | O18: 83160
A19: ENGINEERING SERVICE | C19: 1. EA | D19: 1485 | E19: 0 | F19: 2 | G19: 27 | H19: 0 | I19: 0 | J19: 0 | K19: 0 | L19: 0 | M19: 2970 | N19: 57.44 | O19: 775.44
A20: G-SEAL PLUS | C20: 25. KG BG | D20: 178.41 | E20: 35 | F20: 0 | G20: 0 | H20: 0 | I20: 35 | J20: 0 | K20: 0 | L20: 35 | M20: 0 | N20: 0 | O20: 0
A21: LIME | C21: 20. KG BG | D21: 37.43 | E21: 89 | F21: 0 | G21: 0 | H21: 0 | I21: 89 | J21: 0 | K21: 0 | L21: 89 | M21: 0 | N21: 0 | O21: 0
A22: LOWA TECH 70/75 | C22: 50. LB BG | D22: 18.45 | E22: 112 | F22: 0 | G22: 0 | H22: 0 | I22: 224 | J22: 0 | K22: 112 | L22: 112 | M22: 0 | N22: 0 | O22: 0
A23: M-I BAR BULK | C23: 100. LB BG | D23: 20.25 | E23: 1903 | F23: 0 | G23: 2456 | H23: 0 | I23: 4359 | J23: 0 | K23: 0 | L23: 1903 | M23: 0 | N23: 0 | O23: 158952.32
A24: M-I PAC R | C24: 25. KG BG | D24: 184.5 | E24: 0 | F24: 0 | G24: 0 | H24: 23 | I24: 23 | J24: 0 | K24: 0 | L24: 23 | M24: 0 | N24: 0 | O24: 0
A25: PECAN NUT PLUG CSE | C25: 50. LB BG | D25: 65.29 | E25: 10 | F25: 0 | G25: 15 | H25: 0 | I25: 25 | J25: 0 | K25: 0 | L25: 10 | M25: 0 | N25: 0 | O25: 0
A26: PIPE-LAX | C26: 55. GA DM | D26: 2385.02 | E26: 20 | F26: 0 | G26: 0 | H26: 0 | I26: 20 | J26: 0 | K26: 0 | L26: 20 | M26: 0 | N26: 0 | O26: 2676.15
A27: POLYPAC R | C27: 50. LB BG | D27: 184.5 | E27: 7 | F27: 17 | G27: 80 | H27: 29 | I27: 99 | J27: 0 | K27: 0 | L27: 19 | M27: 3136.5 | N27: 313.65 | O27: 0
... A31: THINSMART | C31: 25. LB BG | D31: 119.83 | E31: 117 | F31: 0 | G31: 43 | H31: 0 | I31: 160 | J31: 0 | K31: 0 | L31: 117 | M31: 0 | N31: 0 | O31: 0
A32: 0 | C32: 0 | D32: 0 | E32: 0 | F32: 0 | G32: 0 | H32: 0 | I32: 0 | J32: 0 | K32: 0 | L32: 0 | M32: 0 | N32: 0 | O32: 0
A33: 0 | C33: 0 | D33: 0 | E33: 0 | F33: 0 | G33: 0 | H33: 0 | I33: 0 | J33: 0 | K33: 0 | L33: 0 | M33: 0 | N33: 0 | O33: 0
A34: 0 | C34: 0 | D34: 0 | E34: 0 | F34: 0 | G34: 0 | H34: 0 | I34: 0 | J34: 0 | K34: 0 | L34: 0 | M34: 0 | N34: 0 | O34: 0
A35: 0 | C35: 0 | D35: 0 | E35: 0 | F35: 0 | G35: 0 | H35: 0 | I35: 0 | J35: 0 | K35: 0 | L35: 0 | M35: 0 | N35: 0 | O35: 0
A36: 0 | C36: 0 | D36: 0 | E36: 0 | F36: 0 | G36: 0 | H36: 0 | I36: 0 | J36: 0 | K36: 0 | L36: 0 | M36: 0 | N36: 0 | O36: 0
A37: 0 | C37: 0 | D37: 0 | E37: 0 | F37: 0 | G37: 0 | H37: 0 | I37: 0 | J37: 0 | K37: 0 | L37: 0 | M37: 0 | N37: 0 | O37: 0
A38: 0 | C38: 0 | D38: 0 | E38: 0 | F38: 0 | G38: 0 | H38: 0 | I38: 0 | J38: 0 | K38: 0 | L38: 0 | M38: 0 | N38: 0 | O38: 0
A39: 0 | C39: 0 | D39: 0 | E39: 0 | F39: 0 | G39: 0 | H39: 0 | I39: 0 | J39: 0 | K39: 0 | L39: 0 | M39: 0 | N39: 0 | O39: 0
A40: 0 | C40: 0 | D40: 0 | E40: 0 | F40: 0 | G40: 0 | H40: 0 | I40: 0 | J40: 0 | K40: 0 | L40: 0 | M40: 0 | N40: 0 | O40: 0
A41: 0 | C41: 0 | D41: 0 | E41: 0 | F41: 0 | G41: 0 | H41: 0 | I41: 0 | J41: 0 | K41: 0 | L41: 0 | M41: 0 | N41: 0 | O41: 0
A42: 0 | C42: 0 | D42: 0 | E42: 0 | F42: 0 | G42: 0 | H42: 0 | I42: 0 | J42: 0 | K42: 0 | L42: 0 | M42: 0 | N42: 0 | O42: 0
A43: 0 | C43: 0 | D43: 0 | E43: 0 | F43: 0 | G43: 0 | H43: 0 | I43: 0 | J43: 0 | K43: 0 | L43: 0 | M43: 0 | N43: 0 | O43: 0
... A60: 0 | C60: 0 | D60: 0 | E60: 0 | F60: 0 | G60: 0 | H60: 0 | I60: 0 | J60: 0 | K60: 0 | L60: 0 | M60: 0 | N60: 0 | O60: 0
G61: WELLSITE CHEMICAL INVENTORY | N61: 0 | O61: 0
G62: Daily Report | N62: 0 | O62: 0
B63: Operator : | C63: Cardon IV | I63: Date : | J63: 39996 | N63: 0 | O63: 0
B64: Well Name : | C64: Perla-1X | I64: Report No: | J64: 16 | N64: 0 | O64: 0
B65: Location: | C65: Offshore | I65: Page | J65: 2 | N65: 0 | O65: 0
E66: Cost Summary | N66: 0 | O66: 0
D67: Total Daily Cost: | F67: 10960.5 | J67: Total Daily Tax: | K67: 0
D68: Cumulative Cost: | F68: 160863.84
A69: Product | C69: Unit | D69: Unit | E69: Start | F69: Daily | G69: Cum | H69: Daily | I69: Cum | J69: Daily | K69: Cum. | L69: Final | M69: Daily
C70: Size | D70: Price | E70: Amt. | F70: Used | G70: Used | H70: Rec'd | I70: Rec'd | J70: Return | K70: Return | L70: Stock | M70: Cost
A71: 0 | C71: 0 | D71: 0 | E71: 0 | F71: 0 | G71: 0 | H71: 0 | I71: 0 | J71: 0 | K71: 0 | L71: 0 | M71: 0
A72: 0 | C72: 0 | D72: 0 | E72: 0 | F72: 0 | G72: 0 | H72: 0 | I72: 0 | J72: 0 | K72: 0 | L72: 0 | M72: 0
A73: 0 | C73: 0 | D73: 0 | E73: 0 | F73: 0 | G73: 0 | H73: 0 | I73: 0 | J73: 0 | K73: 0 | L73: 0 | M73: 0
A74: 0 | C74: 0 | D74: 0 | E74: 0 | F74: 0 | G74: 0 | H74: 0 | I74: 0 | J74: 0 | K74: 0 | L74: 0 | M74: 0
A75: 0 | C75: 0 | D75: 0 | E75: 0 | F75: 0 | G75: 0 | H75: 0 | I75: 0 | J75: 0 | K75: 0 | L75: 0 | M75: 0
A76: 0 | C76: 0 | D76: 0 | E76: 0 | F76: 0 | G76: 0 | H76: 0 | I76: 0 | J76: 0 | K76: 0 | L76: 0 | M76: 0
A77: 0 | C77: 0 | D77: 0 | E77: 0 | F77: 0 | G77: 0 | H77: 0 | I77: 0 | J77: 0 | K77: 0 | L77: 0 | M77: 0
A78: 0 | C78: 0 | D78: 0 | E78: 0 | F78: 0 | G78: 0 | H78: 0 | I78: 0 | J78: 0 | K78: 0 | L78: 0 | M78: 0
A79: 0 | C79: 0 | D79: 0 | E79: 0 | F79: 0 | G79: 0 | H79: 0 | I79: 0 | J79: 0 | K79: 0 | L79: 0 | M79: 0
A80: 0 | C80: 0 | D80: 0 | E80: 0 | F80: 0 | G80: 0 | H80: 0 | I80: 0 | J80: 0 | K80: 0 | L80: 0 | M80: 0
A81: 0 | C81: 0 | D81: 0 | E81: 0 | F81: 0 | G81: 0 | H81: 0 | I81: 0 | J81: 0 | K81: 0 | L81: 0 | M81: 0
A82: 0 | C82: 0 | D82: 0 | E82: 0 | F82: 0 | G82: 0 | H82: 0 | I82: 0 | J82: 0 | K82: 0 | L82: 0 | M82: 0
... A120: 0 | C120: 0 | D120: 0 | E120: 0 | F120: 0 | G120: 0 | H120: 0 | I120: 0 | J120: 0 | K120: 0 | L120: 0 | M120: 0
G121: WELLSITE CHEMICAL INVENTORY
G122: Daily Report
B123: Operator : | C123: Cardon IV | I123: Date : | J123: 39996
B124: Well Name : | C124: Perla-1X | I124: Report No: | J124: 16
B125: Location: | C125: Offshore | I125: Page | J125: 3
E126: Cost Summary
D127: Total Daily Cost: | F127: 10960.5 | J127: Total Daily Tax: | K127: 0
D128: Cumulative Cost: | F128: 160863.84
A129: Product | C129: Unit | D129: Unit | E129: Start | F129: Daily | G129: Cum | H129: Daily | I129: Cum | J129: Daily | K129: Cum. | L129: Final | M129: Daily
C130: Size | D130: Price | E130: Amt. | F130: Used | G130: Used | H130: Rec'd | I130: Rec'd | J130: Return | K130: Return | L130: Stock | M130: Cost
A131: 0 | C131: 0 | D131: 0 | E131: 0 | F131: 0 | G131: 0 | H131: 0 | I131: 0 | J131: 0 | K131: 0 | L131: 0 | M131: 0
A132: 0 | C132: 0 | D132: 0 | E132: 0 | F132: 0 | G132: 0 | H132: 0 | I132: 0 | J132: 0 | K132: 0 | L132: 0 | M132: 0
A133: 0 | C133: 0 | D133: 0 | E133: 0 | F133: 0 | G133: 0 | H133: 0 | I133: 0 | J133: 0 | K133: 0 | L133: 0 | M133: 0
A134: 0 | C134: 0 | D134: 0 | E134: 0 | F134: 0 | G134: 0 | H134: 0 | I134: 0 | J134: 0 | K134: 0 | L134: 0 | M134: 0
A135: 0 | C135: 0 | D135: 0 | E135: 0 | F135: 0 | G135: 0 | H135: 0 | I135: 0 | J135: 0 | K135: 0 | L135: 0 | M135: 0
A136: 0 | C136: 0 | D136: 0 | E136: 0 | F136: 0 | G136: 0 | H136: 0 | I136: 0 | J136: 0 | K136: 0 | L136: 0 | M136: 0
A137: 0 | C137: 0 | D137: 0 | E137: 0 | F137: 0 | G137: 0 | H137: 0 | I137: 0 | J137: 0 | K137: 0 | L137: 0 | M137: 0
A138: 0 | C138: 0 | D138: 0 | E138: 0 | F138: 0 | G138: 0 | H138: 0 | I138: 0 | J138: 0 | K138: 0 | L138: 0 | M138: 0
A139: 0 | C139: 0 | D139: 0 | E139: 0 | F139: 0 | G139: 0 | H139: 0 | I139: 0 | J139: 0 | K139: 0 | L139: 0 | M139: 0
A140: 0 | C140: 0 | D140: 0 | E140: 0 | F140: 0 | G140: 0 | H140: 0 | I140: 0 | J140: 0 | K140: 0 | L140: 0 | M140: 0
A141: 0 | C141: 0 | D141: 0 | E141: 0 | F141: 0 | G141: 0 | H141: 0 | I141: 0 | J141: 0 | K141: 0 | L141: 0 | M141: 0
A142: 0 | C142: 0 | D142: 0 | E142: 0 | F142: 0 | G142: 0 | H142: 0 | I142: 0 | J142: 0 | K142: 0 | L142: 0 | M142: 0
... A170: 0 | C170: 0 | D170: 0 | E170: 0 | F170: 0 | G170: 0 | H170: 0 | I170: 0 | J170: 0 | K170: 0 | L170: 0 | M170: 0

Sheet Chem. Inv (Full)
G1: WELLSITE CHEMICAL INVENTORY
G2: Daily Report
B3: Operator : | C3: =[1]IFE!$B$6 -> Cardon IV | I3: Date : | J3: =[1]IFE!$B$119 -> 39989
B4: Well Name : | C4: =[1]IFE!$B$8 -> Perla-1X | I4: Report No: | J4: =[1]IFE!$B$166 -> 9
B5: Location: | C5: =[1]IFE!$B$11 -> Offshore | I5: Page | J5: 1
E6: Cost Summary
D7: Total Daily Cost: | F7: =[1]IFE!$K$7+[1]IFE!$K$8+[1]IFE!$O$7+[1]IFE!$O$8+[1]IFE!$L$7+[1]IFE!$P$7 -> 5749.32 | J7: Total Daily Tax: | K7: =F7-R15 -> 0
D8: Cumulative Cost: | F8: =[1]IFE!$K$20+[1]IFE!$K$21+[1]IFE!$O$20+[1]IFE!$O$21+[1]IFE!$L$20+[1]IFE!$P$20 -> 89939.53
A9: Product | C9: Unit | D9: Unit | E9: Start | F9: Daily | G9: Cum | H9: Daily | I9: Cum | J9: Daily | K9: Cum. | L9: Final | M9: Daily | N9: Daily | O9: Cum.
C10: Size | D10: Price | E10: Amt. | F10: Used | G10: Used | H10: Rec'd | I10: Rec'd | J10: Return | K10: Return | L10: Stock | M10: Cost | N10: Cost | O10: Cost
A11: =[1]IFE!$A4701 -> BENTONITE WYOMING | C11: =[1]IFE!$B4701 -> 100. LB BG | D11: =[1]IFE!$J4701 -> 28.72 | E11: =[1]IFE!$D4701 -> 58 | F11: =[1]IFE!$C4701+[1]IFE!$P4701 -> 1 | G11: =[1]IFE!$H4701+[1]IFE!$R4701 -> 443 | H11: =[1]IFE!$E4701 -> 0 | I11: =[1]IFE!$K4701 -> 500 | J11: =[1]IFE!$F4701 -> 0 | K11: =[1]IFE!$L4701 -> 0 | L11: =[1]IFE!$G4701 -> 57 | M11: =F11*[1]IFE!$J4701 -> 28.72 | N11: =[1]IFE!$AO$48*F11 -> 18.45 | O11: =[1]IFE!$AO$48*G11 -> 8173.35
A12: =[1]IFE!$A4702 -> CALCIUM CARBONATE #6 | C12: =[1]IFE!$B4702 -> 50. LB BG | D12: =[1]IFE!$J4702 -> 18.45 | E12: =[1]IFE!$D4702 -> 112 | F12: =[1]IFE!$C4702+[1]IFE!$P4702 -> 0 | G12: =[1]IFE!$H4702+[1]IFE!$R4702 -> 0 | H12: =[1]IFE!$E4702 -> 0 | I12: =[1]IFE!$K4702 -> 112 | J12: =[1]IFE!$F4702 -> 0 | K12: =[1]IFE!$L4702 -> 0 | L12: =[1]IFE!$G4702 -> 112 | M12: =F12*[1]IFE!$J4702 -> 0
A13: =[1]IFE!$A4703 -> CAUSTIC POTASH (POTASSIUM HYDROXIDE - KOH) | C13: =[1]IFE!$B4703 -> 25. KG BG | D13: =[1]IFE!$J4703 -> 113.32 | E13: =[1]IFE!$D4703 -> 14 | F13: =[1]IFE!$C4703+[1]IFE!$P4703 -> 0 | G13: =[1]IFE!$H4703+[1]IFE!$R4703 -> 0 | H13: =[1]IFE!$E4703 -> 0 | I13: =[1]IFE!$K4703 -> 14 | J13: =[1]IFE!$F4703 -> 0 | K13: =[1]IFE!$L4703 -> 0 | L13: =[1]IFE!$G4703 -> 14 | M13: =F13*[1]IFE!$J4703 -> 0
A14: =[1]IFE!$A4704 -> CAUSTIC SODA | C14: =[1]IFE!$B4704 -> 25. KG BG | D14: =[1]IFE!$J4704 -> 64.72 | E14: =[1]IFE!$D4704 -> 21 | F14: =[1]IFE!$C4704+[1]IFE!$P4704 -> 0 | G14: =[1]IFE!$H4704+[1]IFE!$R4704 -> 9 | H14: =[1]IFE!$E4704 -> 0 | I14: =[1]IFE!$K4704 -> 30 | J14: =[1]IFE!$F4704 -> 0 | K14: =[1]IFE!$L4704 -> 0 | L14: =[1]IFE!$G4704 -> 21 | M14: =F14*[1]IFE!$J4704 -> 0 | Q14: Before Taxes (Include Not Print Products)
A15: =[1]IFE!$A4705 -> CELL-U-SEAL FINE | C15: =[1]IFE!$B4705 -> 30. LB BG | D15: =[1]IFE!$J4705 -> 69.67 | E15: =[1]IFE!$D4705 -> 114 | F15: =[1]IFE!$C4705+[1]IFE!$P4705 -> 0 | G15: =[1]IFE!$H4705+[1]IFE!$R4705 -> 0 | H15: =[1]IFE!$E4705 -> 0 | I15: =[1]IFE!$K4705 -> 114 | J15: =[1]IFE!$F4705 -> 0 | K15: =[1]IFE!$L4705 -> 0 | L15: =[1]IFE!$G4705 -> 114 | M15: =F15*[1]IFE!$J4705 -> 0 | R15: =SUMPRODUCT([1]IFE!$C$4701:$C$4840,[1]IFE!$N$4701:$N$4840)+SUMPRODUCT([1]IFE!$P$4701:$P$4840,[1]IFE!$N$4701:$N$4840) -> 5749.32
A16: =[1]IFE!$A4706 -> DRIL-KLEEN | C16: =[1]IFE!$B4706 -> 5. GA CN | D16: =[1]IFE!$J4706 -> 322.21 | E16: =[1]IFE!$D4706 -> 45 | F16: =[1]IFE!$C4706+[1]IFE!$P4706 -> 0 | G16: =[1]IFE!$H4706+[1]IFE!$R4706 -> 0 | H16: =[1]IFE!$E4706 -> 0 | I16: =[1]IFE!$K4706 -> 45 | J16: =[1]IFE!$F4706 -> 0 | K16: =[1]IFE!$L4706 -> 0 | L16: =[1]IFE!$G4706 -> 45 | M16: =F16*[1]IFE!$J4706 -> 0 | N16: =[1]IFE!$AO$58*F16 -> 0 | O16: =[1]IFE!$AO$58*G16 -> 0
A17: =[1]IFE!$A4707 -> DUO-VIS | C17: =[1]IFE!$B4707 -> 50. LB BG | D17: =[1]IFE!$J4707 -> 550.12 | E17: =[1]IFE!$D4707 -> 0 | F17: =[1]IFE!$C4707+[1]IFE!$P4707 -> 0 | G17: =[1]IFE!$H4707+[1]IFE!$R4707 -> 0 | H17: =[1]IFE!$E4707 -> 0 | I17: =[1]IFE!$K4707 -> 0 | J17: =[1]IFE!$F4707 -> 0 | K17: =[1]IFE!$L4707 -> 0 | L17: =[1]IFE!$G4707 -> 0 | M17: =F17*[1]IFE!$J4707 -> 0 | N17: =[1]IFE!$AO$68*F17 -> 0 | O17: =[1]IFE!$AO$68*G17 -> 0
A18: =[1]IFE!$A4708 -> DUO-VIS | C18: =[1]IFE!$B4708 -> 25. KG BG | D18: =[1]IFE!$J4708 -> 550.12 | E18: =[1]IFE!$D4708 -> 56 | F18: =[1]IFE!$C4708+[1]IFE!$P4708 -> 5 | G18: =[1]IFE!$H4708+[1]IFE!$R4708 -> 7 | H18: =[1]IFE!$E4708 -> 0 | I18: =[1]IFE!$K4708 -> 58 | J18: =[1]IFE!$F4708 -> 0 | K18: =[1]IFE!$L4708 -> 0 | L18: =[1]IFE!$G4708 -> 51 | M18: =F18*[1]IFE!$J4708 -> 2750.6 | N18: =[1]IFE!$AO$78*F18 -> 7425 | O18: =[1]IFE!$AO$78*G18 -> 10395
A19: =[1]IFE!$A4709 -> ENGINEERING SERVICE | C19: =[1]IFE!$B4709 -> 1. EA | D19: =[1]IFE!$J4709 -> 1485 | E19: =[1]IFE!$D4709 -> 0 | F19: =[1]IFE!$C4709+[1]IFE!$P4709 -> 2 | G19: =[1]IFE!$H4709+[1]IFE!$R4709 -> 13 | H19: =[1]IFE!$E4709 -> 0 | I19: =[1]IFE!$K4709 -> 0 | J19: =[1]IFE!$F4709 -> 0 | K19: =[1]IFE!$L4709 -> 0 | L19: =[1]IFE!$G4709 -> 2 | M19: =F19*[1]IFE!$J4709 -> 2970 | N19: =[1]IFE!$AO$88*F19 -> 57.44 | O19: =[1]IFE!$AO$88*G19 -> 373.36
A20: =[1]IFE!$A4710 -> G-SEAL PLUS | C20: =[1]IFE!$B4710 -> 25. KG BG | D20: =[1]IFE!$J4710 -> 178.41 | E20: =[1]IFE!$D4710 -> 35 | F20: =[1]IFE!$C4710+[1]IFE!$P4710 -> 0 | G20: =[1]IFE!$H4710+[1]IFE!$R4710 -> 0 | H20: =[1]IFE!$E4710 -> 0 | I20: =[1]IFE!$K4710 -> 35 | J20: =[1]IFE!$F4710 -> 0 | K20: =[1]IFE!$L4710 -> 0 | L20: =[1]IFE!$G4710 -> 35 | M20: =F20*[1]IFE!$J4710 -> 0 | N20: =[1]IFE!$AO$98*F20 -> 0 | O20: =[1]IFE!$AO$98*G20 -> 0
A21: =[1]IFE!$A4711 -> LIME | C21: =[1]IFE!$B4711 -> 20. KG BG | D21: =[1]IFE!$J4711 -> 37.43 | E21: =[1]IFE!$D4711 -> 39 | F21: =[1]IFE!$C4711+[1]IFE!$P4711 -> 0 | G21: =[1]IFE!$H4711+[1]IFE!$R4711 -> 0 | H21: =[1]IFE!$E4711 -> 0 | I21: =[1]IFE!$K4711 -> 39 | J21: =[1]IFE!$F4711 -> 0 | K21: =[1]IFE!$L4711 -> 0 | L21: =[1]IFE!$G4711 -> 39 | M21: =F21*[1]IFE!$J4711 -> 0 | N21: =[1]IFE!$AO$108*F21 -> 0 | O21: =[1]IFE!$AO$108*G21 -> 0
A22: =[1]IFE!$A4712 -> LOWA TECH 70/75 | C22: =[1]IFE!$B4712 -> 50. LB BG | D22: =[1]IFE!$J4712 -> 18.45 | E22: =[1]IFE!$D4712 -> 112 | F22: =[1]IFE!$C4712+[1]IFE!$P4712 -> 0 | G22: =[1]IFE!$H4712+[1]IFE!$R4712 -> 0 | H22: =[1]IFE!$E4712 -> 0 | I22: =[1]IFE!$K4712 -> 224 | J22: =[1]IFE!$F4712 -> 0 | K22: =[1]IFE!$L4712 -> 112 | L22: =[1]IFE!$G4712 -> 112 | M22: =F22*[1]IFE!$J4712 -> 0 | N22: =[1]IFE!$AO$118*F22 -> 0 | O22: =[1]IFE!$AO$118*G22 -> 0
A23: =[1]IFE!$A4713 -> M-I BAR BULK | C23: =[1]IFE!$B4713 -> 100. LB BG | D23: =[1]IFE!$J4713 -> 20.25 | E23: =[1]IFE!$D4713 -> 1153 | F23: =[1]IFE!$C4713+[1]IFE!$P4713 -> 0 | G23: =[1]IFE!$H4713+[1]IFE!$R4713 -> 2206 | H23: =[1]IFE!$E4713 -> 0 | I23: =[1]IFE!$K4713 -> 3359 | J23: =[1]IFE!$F4713 -> 0 | K23: =[1]IFE!$L4713 -> 0 | L23: =[1]IFE!$G4713 -> 1153 | M23: =F23*[1]IFE!$J4713 -> 0 | N23: =[1]IFE!$AO$128*F23 -> 0 | O23: =[1]IFE!$AO$128*G23 -> 264344.98
A24: =[1]IFE!$A4714 -> PECAN NUT PLUG CSE | C24: =[1]IFE!$B4714 -> 50. LB BG | D24: =[1]IFE!$J4714 -> 65.29 | E24: =[1]IFE!$D4714 -> 25 | F24: =[1]IFE!$C4714+[1]IFE!$P4714 -> 0 | G24: =[1]IFE!$H4714+[1]IFE!$R4714 -> 0 | H24: =[1]IFE!$E4714 -> 0 | I24: =[1]IFE!$K4714 -> 25 | J24: =[1]IFE!$F4714 -> 0 | K24: =[1]IFE!$L4714 -> 0 | L24: =[1]IFE!$G4714 -> 25 | M24: =F24*[1]IFE!$J4714 -> 0 | N24: =[1]IFE!$AO$138*F24 -> 0 | O24: =[1]IFE!$AO$138*G24 -> 0
A25: =[1]IFE!$A4715 -> PIPE-LAX | C25: =[1]IFE!$B4715 -> 55. GA DM | D25: =[1]IFE!$J4715 -> 2385.02 | E25: =[1]IFE!$D4715 -> 20 | F25: =[1]IFE!$C4715+[1]IFE!$P4715 -> 0 | G25: =[1]IFE!$H4715+[1]IFE!$R4715 -> 0 | H25: =[1]IFE!$E4715 -> 0 | I25: =[1]IFE!$K4715 -> 20 | J25: =[1]IFE!$F4715 -> 0 | K25: =[1]IFE!$L4715 -> 0 | L25: =[1]IFE!$G4715 -> 20 | M25: =F25*[1]IFE!$J4715 -> 0 | N25: =[1]IFE!$AO$148*F25 -> 0 | O25: =[1]IFE!$AO$148*G24 -> 0
A26: =[1]IFE!$A4716 -> POLYPAC R | C26: =[1]IFE!$B4716 -> 50. LB BG | D26: =[1]IFE!$J4716 -> 184.5 | E26: =[1]IFE!$D4716 -> 52 | F26: =[1]IFE!$C4716+[1]IFE!$P4716 -> 0 | G26: =[1]IFE!$H4716+[1]IFE!$R4716 -> 18 | H26: =[1]IFE!$E4716 -> 0 | I26: =[1]IFE!$K4716 -> 70 | J26: =[1]IFE!$F4716 -> 0 | K26: =[1]IFE!$L4716 -> 0 | L26: =[1]IFE!$G4716 -> 52 | M26: =F26*[1]IFE!$J4716 -> 0 | N26: =[1]IFE!$AO$158*F26 -> 0 | O26: =[1]IFE!$AO$158*G25 -> 0
A27: =[1]IFE!$A4717 -> SODA ASH | C27: =[1]IFE!$B4717 -> 50. KG BG | D27: =[1]IFE!$J4717 -> 55.51 | E27: =[1]IFE!$D4717 -> 10 | F27: =[1]IFE!$C4717+[1]IFE!$P4717 -> 0 | G27: =[1]IFE!$H4717+[1]IFE!$R4717 -> 6 | H27: =[1]IFE!$E4717 -> 0 | I27: =[1]IFE!$K4717 -> 16 | J27: =[1]IFE!$F4717 -> 0 | K27: =[1]IFE!$L4717 -> 0 | L27: =[1]IFE!$G4717 -> 10 | M27: =F27*[1]IFE!$J4717 -> 0 | N27: =[1]IFE!$AO$168*F27 -> 0 | O27: =[1]IFE!$AO$168*G26 -> 3211.38
A28: =[1]IFE!$A4718 -> SODIUM BICARBONATE | C28: =[1]IFE!$B4718 -> 50. LB BG | D28: =[1]IFE!$J4718 -> 52.87 | E28: =[1]IFE!$D4718 -> 27 | F28: =[1]IFE!$C4718+[1]IFE!$P4718 -> 0 | G28: =[1]IFE!$H4718+[1]IFE!$R4718 -> 0 | H28: =[1]IFE!$E4718 -> 0 | I28: =[1]IFE!$K4718 -> 27 | J28: =[1]IFE!$F4718 -> 0 | K28: =[1]IFE!$L4718 -> 0 | L28: =[1]IFE!$G4718 -> 27 | M28: =F28*[1]IFE!$J4718 -> 0 | N28: =[1]IFE!$AO$178*F28 -> 0 | O28: =[1]IFE!$AO$178*G27 -> 110.7
A29: =[1]IFE!$A4719 -> THINSMART | C29: =[1]IFE!$B4719 -> 25. LB BG | D29: =[1]IFE!$J4719 -> 119.83 | E29: =[1]IFE!$D4719 -> 117 | F29: =[1]IFE!$C4719+[1]IFE!$P4719 -> 0 | G29: =[1]IFE!$H4719+[1]IFE!$R4719 -> 43 | H29: =[1]IFE!$E4719 -> 0 | I29: =[1]IFE!$K4719 -> 160 | J29: =[1]IFE!$F4719 -> 0 | K29: =[1]IFE!$L4719 -> 0 | L29: =[1]IFE!$G4719 -> 117 | M29: =F29*[1]IFE!$J4719 -> 0 | N29: =[1]IFE!$AO$198*F29 -> 0 | O29: =[1]IFE!$AO$188*G28 -> 0
A30: =[1]IFE!$A4720 -> 0 | C30: =[1]IFE!$B4720 -> 0 | D30: =[1]IFE!$J4720 -> 0 | E30: =[1]IFE!$D4720 -> 0 | F30: =[1]IFE!$C4720+[1]IFE!$P4720 -> 0 | G30: =[1]IFE!$H4720+[1]IFE!$R4720 -> 0 | H30: =[1]IFE!$E4720 -> 0 | I30: =[1]IFE!$K4720 -> 0 | J30: =[1]IFE!$F4720 -> 0 | K30: =[1]IFE!$L4720 -> 0 | L30: =[1]IFE!$G4720 -> 0 | M30: =F30*[1]IFE!$J4720 -> 0 | N30: =[1]IFE!$AO$208*F30 -> 0 | O30: =[1]IFE!$AO$198*G29 -> 0
A31: =[1]IFE!$A4721 -> 0 | C31: =[1]IFE!$B4721 -> 0 | D31: =[1]IFE!$J4721 -> 0 | E31: =[1]IFE!$D4721 -> 0 | F31: =[1]IFE!$C4721+[1]IFE!$P4721 -> 0 | G31: =[1]IFE!$H4721+[1]IFE!$R4721 -> 0 | H31: =[1]IFE!$E4721 -> 0 | I31: =[1]IFE!$K4721 -> 0 | J31: =[1]IFE!$F4721 -> 0 | K31: =[1]IFE!$L4721 -> 0 | L31: =[1]IFE!$G4721 -> 0 | M31: =F31*[1]IFE!$J4721 -> 0 | N31: =[1]IFE!$AO$218*F31 -> 0 | O31: =[1]IFE!$AO$208*G30 -> 0
A32: =[1]IFE!$A4722 -> 0 | C32: =[1]IFE!$B4722 -> 0 | D32: =[1]IFE!$J4722 -> 0 | E32: =[1]IFE!$D4722 -> 0 | F32: =[1]IFE!$C4722+[1]IFE!$P4722 -> 0 | G32: =[1]IFE!$H4722+[1]IFE!$R4722 -> 0 | H32: =[1]IFE!$E4722 -> 0 | I32: =[1]IFE!$K4722 -> 0 | J32: =[1]IFE!$F4722 -> 0 | K32: =[1]IFE!$L4722 -> 0 | L32: =[1]IFE!$G4722 -> 0 | M32: =F32*[1]IFE!$J4722 -> 0 | N32: =[1]IFE!$AO$228*F32 -> 0 | O32: =[1]IFE!$AO$218*G31 -> 0
A33: =[1]IFE!$A4723 -> 0 | C33: =[1]IFE!$B4723 -> 0 | D33: =[1]IFE!$J4723 -> 0 | E33: =[1]IFE!$D4723 -> 0 | F33: =[1]IFE!$C4723+[1]IFE!$P4723 -> 0 | G33: =[1]IFE!$H4723+[1]IFE!$R4723 -> 0 | H33: =[1]IFE!$E4723 -> 0 | I33: =[1]IFE!$K4723 -> 0 | J33: =[1]IFE!$F4723 -> 0 | K33: =[1]IFE!$L4723 -> 0 | L33: =[1]IFE!$G4723 -> 0 | M33: =F33*[1]IFE!$J4723 -> 0 | N33: =[1]IFE!$AO$238*F33 -> 0 | O33: =[1]IFE!$AO$228*G32 -> 0
A34: =[1]IFE!$A4724 -> 0 | C34: =[1]IFE!$B4724 -> 0 | D34: =[1]IFE!$J4724 -> 0 | E34: =[1]IFE!$D4724 -> 0 | F34: =[1]IFE!$C4724+[1]IFE!$P4724 -> 0 | G34: =[1]IFE!$H4724+[1]IFE!$R4724 -> 0 | H34: =[1]IFE!$E4724 -> 0 | I34: =[1]IFE!$K4724 -> 0 | J34: =[1]IFE!$F4724 -> 0 | K34: =[1]IFE!$L4724 -> 0 | L34: =[1]IFE!$G4724 -> 0 | M34: =F34*[1]IFE!$J4724 -> 0 | N34: =[1]IFE!$AO$248*F34 -> 0 | O34: =[1]IFE!$AO$238*G33 -> 0
A35: =[1]IFE!$A4725 -> 0 | C35: =[1]IFE!$B4725 -> 0 | D35: =[1]IFE!$J4725 -> 0 | E35: =[1]IFE!$D4725 -> 0 | F35: =[1]IFE!$C4725+[1]IFE!$P4725 -> 0 | G35: =[1]IFE!$H4725+[1]IFE!$R4725 -> 0 | H35: =[1]IFE!$E4725 -> 0 | I35: =[1]IFE!$K4725 -> 0 | J35: =[1]IFE!$F4725 -> 0 | K35: =[1]IFE!$L4725 -> 0 | L35: =[1]IFE!$G4725 -> 0 | M35: =F35*[1]IFE!$J4725 -> 0 | N35: =[1]IFE!$AO$258*F35 -> 0 | O35: =[1]IFE!$AO$248*G34 -> 0
A36: =[1]IFE!$A4726 -> 0 | C36: =[1]IFE!$B4726 -> 0 | D36: =[1]IFE!$J4726 -> 0 | E36: =[1]IFE!$D4726 -> 0 | F36: =[1]IFE!$C4726+[1]IFE!$P4726 -> 0 | G36: =[1]IFE!$H4726+[1]IFE!$R4726 -> 0 | H36: =[1]IFE!$E4726 -> 0 | I36: =[1]IFE!$K4726 -> 0 | J36: =[1]IFE!$F4726 -> 0 | K36: =[1]IFE!$L4726 -> 0 | L36: =[1]IFE!$G4726 -> 0 | M36: =F36*[1]IFE!$J4726 -> 0 | N36: =[1]IFE!$AO$268*F36 -> 0 | O36: =[1]IFE!$AO$258*G35 -> 0
A37: =[1]IFE!$A4727 -> 0 | C37: =[1]IFE!$B4727 -> 0 | D37: =[1]IFE!$J4727 -> 0 | E37: =[1]IFE!$D4727 -> 0 | F37: =[1]IFE!$C4727+[1]IFE!$P4727 -> 0 | G37: =[1]IFE!$H4727+[1]IFE!$R4727 -> 0 | H37: =[1]IFE!$E4727 -> 0 | I37: =[1]IFE!$K4727 -> 0 | J37: =[1]IFE!$F4727 -> 0 | K37: =[1]IFE!$L4727 -> 0 | L37: =[1]IFE!$G4727 -> 0 | M37: =F37*[1]IFE!$J4727 -> 0 | N37: =[1]IFE!$AO$278*F37 -> 0 | O37: =[1]IFE!$AO$268*G36 -> 0
A38: =[1]IFE!$A4728 -> 0 | C38: =[1]IFE!$B4728 -> 0 | D38: =[1]IFE!$J4728 -> 0 | E38: =[1]IFE!$D4728 -> 0 | F38: =[1]IFE!$C4728+[1]IFE!$P4728 -> 0 | G38: =[1]IFE!$H4728+[1]IFE!$R4728 -> 0 | H38: =[1]IFE!$E4728 -> 0 | I38: =[1]IFE!$K4728 -> 0 | J38: =[1]IFE!$F4728 -> 0 | K38: =[1]IFE!$L4728 -> 0 | L38: =[1]IFE!$G4728 -> 0 | M38: =F38*[1]IFE!$J4728 -> 0 | N38: =[1]IFE!$AO$288*F38 -> 0 | O38: =[1]IFE!$AO$278*G37 -> 0
A39: =[1]IFE!$A4729 -> 0 | C39: =[1]IFE!$B4729 -> 0 | D39: =[1]IFE!$J4729 -> 0 | E39: =[1]IFE!$D4729 -> 0 | F39: =[1]IFE!$C4729+[1]IFE!$P4729 -> 0 | G39: =[1]IFE!$H4729+[1]IFE!$R4729 -> 0 | H39: =[1]IFE!$E4729 -> 0 | I39: =[1]IFE!$K4729 -> 0 | J39: =[1]IFE!$F4729 -> 0 | K39: =[1]IFE!$L4729 -> 0 | L39: =[1]IFE!$G4729 -> 0 | M39: =F39*[1]IFE!$J4729 -> 0 | N39: =[1]IFE!$AO$298*F39 -> 0 | O39: =[1]IFE!$AO$288*G38 -> 0
A40: =[1]IFE!$A4730 -> 0 | C40: =[1]IFE!$B4730 -> 0 | D40: =[1]IFE!$J4730 -> 0 | E40: =[1]IFE!$D4730 -> 0 | F40: =[1]IFE!$C4730+[1]IFE!$P4730 -> 0 | G40: =[1]IFE!$H4730+[1]IFE!$R4730 -> 0 | H40: =[1]IFE!$E4730 -> 0 | I40: =[1]IFE!$K4730 -> 0 | J40: =[1]IFE!$F4730 -> 0 | K40: =[1]IFE!$L4730 -> 0 | L40: =[1]IFE!$G4730 -> 0 | M40: =F40*[1]IFE!$J4730 -> 0 | N40: =[1]IFE!$AO$308*F40 -> 0 | O40: =[1]IFE!$AO$298*G39 -> 0
A41: =[1]IFE!$A4731 -> 0 | C41: =[1]IFE!$B4731 -> 0 | D41: =[1]IFE!$J4731 -> 0 | E41: =[1]IFE!$D4731 -> 0 | F41: =[1]IFE!$C4731+[1]IFE!$P4731 -> 0 | G41: =[1]IFE!$H4731+[1]IFE!$R4731 -> 0 | H41: =[1]IFE!$E4731 -> 0 | I41: =[1]IFE!$K4731 -> 0 | J41: =[1]IFE!$F4731 -> 0 | K41: =[1]IFE!$L4731 -> 0 | L41: =[1]IFE!$G4731 -> 0 | M41: =F41*[1]IFE!$J4731 -> 0 | N41: =[1]IFE!$AO$318*F41 -> 0 | O41: =[1]IFE!$AO$308*G40 -> 0
A42: =[1]IFE!$A4732 -> 0 | C42: =[1]IFE!$B4732 -> 0 | D42: =[1]IFE!$J4732 -> 0 | E42: =[1]IFE!$D4732 -> 0 | F42: =[1]IFE!$C4732+[1]IFE!$P4732 -> 0 | G42: =[1]IFE!$H4732+[1]IFE!$R4732 -> 0 | H42: =[1]IFE!$E4732 -> 0 | I42: =[1]IFE!$K4732 -> 0 | J42: =[1]IFE!$F4732 -> 0 | K42: =[1]IFE!$L4732 -> 0 | L42: =[1]IFE!$G4732 -> 0 | M42: =F42*[1]IFE!$J4732 -> 0 | N42: =[1]IFE!$AO$328*F42 -> 0 | O42: =[1]IFE!$AO$318*G41 -> 0
A43: =[1]IFE!$A4733 -> 0 | C43: =[1]IFE!$B4733 -> 0 | D43: =[1]IFE!$J4733 -> 0 | E43: =[1]IFE!$D4733 -> 0 | F43: =[1]IFE!$C4733+[1]IFE!$P4733 -> 0 | G43: =[1]IFE!$H4733+[1]IFE!$R4733 -> 0 | H43: =[1]IFE!$E4733 -> 0 | I43: =[1]IFE!$K4733 -> 0 | J43: =[1]IFE!$F4733 -> 0 | K43: =[1]IFE!$L4733 -> 0 | L43: =[1]IFE!$G4733 -> 0 | M43: =F43*[1]IFE!$J4733 -> 0 | N43: =[1]IFE!$AO$338*F43 -> 0 | O43: =[1]IFE!$AO$328*G42 -> 0
A44: =[1]IFE!$A4734 -> 0 | C44: =[1]IFE!$B4734 -> 0 | D44: =[1]IFE!$J4734 -> 0 | E44: =[1]IFE!$D4734 -> 0 | F44: =[1]IFE!$C4734+[1]IFE!$P4734 -> 0 | G44: =[1]IFE!$H4734+[1]IFE!$R4734 -> 0 | H44: =[1]IFE!$E4734 -> 0 | I44: =[1]IFE!$K4734 -> 0 | J44: =[1]IFE!$F4734 -> 0 | K44: =[1]IFE!$L4734 -> 0 | L44: =[1]IFE!$G4734 -> 0 | M44: =F44*[1]IFE!$J4734 -> 0 | N44: =[1]IFE!$AO$348*F44 -> 0 | O44: =[1]IFE!$AO$338*G43 -> 0
A45: =[1]IFE!$A4735 -> 0 | C45: =[1]IFE!$B4735 -> 0 | D45: =[1]IFE!$J4735 -> 0 | E45: =[1]IFE!$D4735 -> 0 | F45: =[1]IFE!$C4735+[1]IFE!$P4735 -> 0 | G45: =[1]IFE!$H4735+[1]IFE!$R4735 -> 0 | H45: =[1]IFE!$E4735 -> 0 | I45: =[1]IFE!$K4735 -> 0 | J45: =[1]IFE!$F4735 -> 0 | K45: =[1]IFE!$L4735 -> 0 | L45: =[1]IFE!$G4735 -> 0 | M45: =F45*[1]IFE!$J4735 -> 0 | N45: =[1]IFE!$AO$358*F45 -> 0 | O45: =[1]IFE!$AO$348*G44 -> 0
A46: =[1]IFE!$A4736 -> 0 | C46: =[1]IFE!$B4736 -> 0 | D46: =[1]IFE!$J4736 -> 0 | E46: =[1]IFE!$D4736 -> 0 | F46: =[1]IFE!$C4736+[1]IFE!$P4736 -> 0 | G46: =[1]IFE!$H4736+[1]IFE!$R4736 -> 0 | H46: =[1]IFE!$E4736 -> 0 | I46: =[1]IFE!$K4736 -> 0 | J46: =[1]IFE!$F4736 -> 0 | K46: =[1]IFE!$L4736 -> 0 | L46: =[1]IFE!$G4736 -> 0 | M46: =F46*[1]IFE!$J4736 -> 0 | N46: =[1]IFE!$AO$368*F46 -> 0 | O46: =[1]IFE!$AO$358*G45 -> 0
A47: =[1]IFE!$A4737 -> 0 | C47: =[1]IFE!$B4737 -> 0 | D47: =[1]IFE!$J4737 -> 0 | E47: =[1]IFE!$D4737 -> 0 | F47: =[1]IFE!$C4737+[1]IFE!$P4737 -> 0 | G47: =[1]IFE!$H4737+[1]IFE!$R4737 -> 0 | H47: =[1]IFE!$E4737 -> 0 | I47: =[1]IFE!$K4737 -> 0 | J47: =[1]IFE!$F4737 -> 0 | K47: =[1]IFE!$L4737 -> 0 | L47: =[1]IFE!$G4737 -> 0 | M47: =F47*[1]IFE!$J4737 -> 0 | N47: =[1]IFE!$AO$378*F47 -> 0 | O47: =[1]IFE!$AO$368*G46 -> 0
A48: =[1]IFE!$A4738 -> 0 | C48: =[1]IFE!$B4738 -> 0 | D48: =[1]IFE!$J4738 -> 0 | E48: =[1]IFE!$D4738 -> 0 | F48: =[1]IFE!$C4738+[1]IFE!$P4738 -> 0 | G48: =[1]IFE!$H4738+[1]IFE!$R4738 -> 0 | H48: =[1]IFE!$E4738 -> 0 | I48: =[1]IFE!$K4738 -> 0 | J48: =[1]IFE!$F4738 -> 0 | K48: =[1]IFE!$L4738 -> 0 | L48: =[1]IFE!$G4738 -> 0 | M48: =F48*[1]IFE!$J4738 -> 0 | N48: =[1]IFE!$AO$388*F48 -> 0 | O48: =[1]IFE!$AO$378*G47 -> 0
A49: =[1]IFE!$A4739 -> 0 | C49: =[1]IFE!$B4739 -> 0 | D49: =[1]IFE!$J4739 -> 0 | E49: =[1]IFE!$D4739 -> 0 | F49: =[1]IFE!$C4739+[1]IFE!$P4739 -> 0 | G49: =[1]IFE!$H4739+[1]IFE!$R4739 -> 0 | H49: =[1]IFE!$E4739 -> 0 | I49: =[1]IFE!$K4739 -> 0 | J49: =[1]IFE!$F4739 -> 0 | K49: =[1]IFE!$L4739 -> 0 | L49: =[1]IFE!$G4739 -> 0 | M49: =F49*[1]IFE!$J4739 -> 0 | N49: =[1]IFE!$AO$398*F49 -> 0 | O49: =[1]IFE!$AO$388*G48 -> 0
A50: =[1]IFE!$A4740 -> 0 | C50: =[1]IFE!$B4740 -> 0 | D50: =[1]IFE!$J4740 -> 0 | E50: =[1]IFE!$D4740 -> 0 | F50: =[1]IFE!$C4740+[1]IFE!$P4740 -> 0 | G50: =[1]IFE!$H4740+[1]IFE!$R4740 -> 0 | H50: =[1]IFE!$E4740 -> 0 | I50: =[1]IFE!$K4740 -> 0 | J50: =[1]IFE!$F4740 -> 0 | K50: =[1]IFE!$L4740 -> 0 | L50: =[1]IFE!$G4740 -> 0 | M50: =F50*[1]IFE!$J4740 -> 0 | N50: =[1]IFE!$AO$408*F50 -> 0 | O50: =[1]IFE!$AO$398*G49 -> 0
A51: =[1]IFE!$A4741 -> 0 | C51: =[1]IFE!$B4741 -> 0 | D51: =[1]IFE!$J4741 -> 0 | E51: =[1]IFE!$D4741 -> 0 | F51: =[1]IFE!$C4741+[1]IFE!$P4741 -> 0 | G51: =[1]IFE!$H4741+[1]IFE!$R4741 -> 0 | H51: =[1]IFE!$E4741 -> 0 | I51: =[1]IFE!$K4741 -> 0 | J51: =[1]IFE!$F4741 -> 0 | K51: =[1]IFE!$L4741 -> 0 | L51: =[1]IFE!$G4741 -> 0 | M51: =F51*[1]IFE!$J4741 -> 0 | N51: =[1]IFE!$AO$418*F51 -> 0 | O51: =[1]IFE!$AO$408*G50 -> 0
A52: =[1]IFE!$A4742 -> 0 | C52: =[1]IFE!$B4742 -> 0 | D52: =[1]IFE!$J4742 -> 0 | E52: =[1]IFE!$D4742 -> 0 | F52: =[1]IFE!$C4742+[1]IFE!$P4742 -> 0 | G52: =[1]IFE!$H4742+[1]IFE!$R4742 -> 0 | H52: =[1]IFE!$E4742 -> 0 | I52: =[1]IFE!$K4742 -> 0 | J52: =[1]IFE!$F4742 -> 0 | K52: =[1]IFE!$L4742 -> 0 | L52: =[1]IFE!$G4742 -> 0 | M52: =F52*[1]IFE!$J4742 -> 0 | N52: =[1]IFE!$AO$428*F52 -> 0 | O52: =[1]IFE!$AO$418*G51 -> 0
A53: =[1]IFE!$A4743 -> 0 | C53: =[1]IFE!$B4743 -> 0 | D53: =[1]IFE!$J4743 -> 0 | E53: =[1]IFE!$D4743 -> 0 | F53: =[1]IFE!$C4743+[1]IFE!$P4743 -> 0 | G53: =[1]IFE!$H4743+[1]IFE!$R4743 -> 0 | H53: =[1]IFE!$E4743 -> 0 | I53: =[1]IFE!$K4743 -> 0 | J53: =[1]IFE!$F4743 -> 0 | K53: =[1]IFE!$L4743 -> 0 | L53: =[1]IFE!$G4743 -> 0 | M53: =F53*[1]IFE!$J4743 -> 0 | N53: =[1]IFE!$AO$438*F53 -> 0 | O53: =[1]IFE!$AO$428*G52 -> 0
A54: =[1]IFE!$A4744 -> 0 | C54: =[1]IFE!$B4744 -> 0 | D54: =[1]IFE!$J4744 -> 0 | E54: =[1]IFE!$D4744 -> 0 | F54: =[1]IFE!$C4744+[1]IFE!$P4744 -> 0 | G54: =[1]IFE!$H4744+[1]IFE!$R4744 -> 0 | H54: =[1]IFE!$E4744 -> 0 | I54: =[1]IFE!$K4744 -> 0 | J54: =[1]IFE!$F4744 -> 0 | K54: =[1]IFE!$L4744 -> 0 | L54: =[1]IFE!$G4744 -> 0 | M54: =F54*[1]IFE!$J4744 -> 0 | N54: =[1]IFE!$AO$448*F54 -> 0 | O54: =[1]IFE!$AO$438*G53 -> 0
A55: =[1]IFE!$A4745 -> 0 | C55: =[1]IFE!$B4745 -> 0 | D55: =[1]IFE!$J4745 -> 0 | E55: =[1]IFE!$D4745 -> 0 | F55: =[1]IFE!$C4745+[1]IFE!$P4745 -> 0 | G55: =[1]IFE!$H4745+[1]IFE!$R4745 -> 0 | H55: =[1]IFE!$E4745 -> 0 | I55: =[1]IFE!$K4745 -> 0 | J55: =[1]IFE!$F4745 -> 0 | K55: =[1]IFE!$L4745 -> 0 | L55: =[1]IFE!$G4745 -> 0 | M55: =F55*[1]IFE!$J4745 -> 0 | N55: =[1]IFE!$AO$458*F55 -> 0 | O55: =[1]IFE!$AO$448*G54 -> 0
A56: =[1]IFE!$A4746 -> 0 | C56: =[1]IFE!$B4746 -> 0 | D56: =[1]IFE!$J4746 -> 0 | E56: =[1]IFE!$D4746 -> 0 | F56: =[1]IFE!$C4746+[1]IFE!$P4746 -> 0 | G56: =[1]IFE!$H4746+[1]IFE!$R4746 -> 0 | H56: =[1]IFE!$E4746 -> 0 | I56: =[1]IFE!$K4746 -> 0 | J56: =[1]IFE!$F4746 -> 0 | K56: =[1]IFE!$L4746 -> 0 | L56: =[1]IFE!$G4746 -> 0 | M56: =F56*[1]IFE!$J4746 -> 0 | N56: =[1]IFE!$AO$468*F56 -> 0 | O56: =[1]IFE!$AO$458*G55 -> 0
A57: =[1]IFE!$A4747 -> 0 | C57: =[1]IFE!$B4747 -> 0 | D57: =[1]IFE!$J4747 -> 0 | E57: =[1]IFE!$D4747 -> 0 | F57: =[1]IFE!$C4747+[1]IFE!$P4747 -> 0 | G57: =[1]IFE!$H4747+[1]IFE!$R4747 -> 0 | H57: =[1]IFE!$E4747 -> 0 | I57: =[1]IFE!$K4747 -> 0 | J57: =[1]IFE!$F4747 -> 0 | K57: =[1]IFE!$L4747 -> 0 | L57: =[1]IFE!$G4747 -> 0 | M57: =F57*[1]IFE!$J4747 -> 0 | N57: =[1]IFE!$AO$478*F57 -> 0 | O57: =[1]IFE!$AO$468*G56 -> 0
A58: =[1]IFE!$A4748 -> 0 | C58: =[1]IFE!$B4748 -> 0 | D58: =[1]IFE!$J4748 -> 0 | E58: =[1]IFE!$D4748 -> 0 | F58: =[1]IFE!$C4748+[1]IFE!$P4748 -> 0 | G58: =[1]IFE!$H4748+[1]IFE!$R4748 -> 0 | H58: =[1]IFE!$E4748 -> 0 | I58: =[1]IFE!$K4748 -> 0 | J58: =[1]IFE!$F4748 -> 0 | K58: =[1]IFE!$L4748 -> 0 | L58: =[1]IFE!$G4748 -> 0 | M58: =F58*[1]IFE!$J4748 -> 0 | N58: =[1]IFE!$AO$488*F58 -> 0 | O58: =[1]IFE!$AO$478*G57 -> 0
A59: =[1]IFE!$A4749 -> 0 | C59: =[1]IFE!$B4749 -> 0 | D59: =[1]IFE!$J4749 -> 0 | E59: =[1]IFE!$D4749 -> 0 | F59: =[1]IFE!$C4749+[1]IFE!$P4749 -> 0 | G59: =[1]IFE!$H4749+[1]IFE!$R4749 -> 0 | H59: =[1]IFE!$E4749 -> 0 | I59: =[1]IFE!$K4749 -> 0 | J59: =[1]IFE!$F4749 -> 0 | K59: =[1]IFE!$L4749 -> 0 | L59: =[1]IFE!$G4749 -> 0 | M59: =F59*[1]IFE!$J4749 -> 0 | N59: =[1]IFE!$AO$498*F59 -> 0 | O59: =[1]IFE!$AO$488*G58 -> 0
A60: =[1]IFE!$A4750 -> 0 | C60: =[1]IFE!$B4750 -> 0 | D60: =[1]IFE!$J4750 -> 0 | E60: =[1]IFE!$D4750 -> 0 | F60: =[1]IFE!$C4750+[1]IFE!$P4750 -> 0 | G60: =[1]IFE!$H4750+[1]IFE!$R4750 -> 0 | H60: =[1]IFE!$E4750 -> 0 | I60: =[1]IFE!$K4750 -> 0 | J60: =[1]IFE!$F4750 -> 0 | K60: =[1]IFE!$L4750 -> 0 | L60: =[1]IFE!$G4750 -> 0 | M60: =F60*[1]IFE!$J4750 -> 0 | N60: =[1]IFE!$AO$508*F60 -> 0 | O60: =[1]IFE!$AO$498*G59 -> 0
G61: WELLSITE CHEMICAL INVENTORY | N61: =[1]IFE!$AO$538*F73 -> 0 | O61: =[1]IFE!$AO$528*G72 -> 0
G62: Daily Report | N62: =[1]IFE!$AO$548*F74 -> 0 | O62: =[1]IFE!$AO$538*G73 -> 0
B63: Operator : | C63: =[1]IFE!$B$6 -> Cardon IV | I63: Date : | J63: =[1]IFE!$B$119 -> 39989 | N63: =[1]IFE!$AO$568*F76 -> 0 | O63: =[1]IFE!$AO$558*G75 -> 0
B64: Well Name : | C64: =[1]IFE!$B$8 -> Perla-1X | I64: Report No: | J64: =[1]IFE!$B$166 -> 9 | N64: =[1]IFE!$AO$578*F77 -> 0 | O64: =[1]IFE!$AO$568*G76 -> 0
B65: Location: | C65: =[1]IFE!$B$11 -> Offshore | I65: Page | J65: 2 | N65: =[1]IFE!$AO$588*F78 -> 0 | O65: =[1]IFE!$AO$578*G77 -> 0
E66: Cost Summary | N66: =[1]IFE!$AO$628*F82 -> 0 | O66: =[1]IFE!$AO$618*G81 -> 0
D67: Total Daily Cost: | F67: =$F7 -> 5749.32 | J67: Total Daily Tax: | K67: =$K$7 -> 0
D68: Cumulative Cost: | F68: =$F$8 -> 89939.53
A69: Product | C69: Unit | D69: Unit | E69: Start | F69: Daily | G69: Cum | H69: Daily | I69: Cum | J69: Daily | K69: Cum. | L69: Final | M69: Daily
C70: Size | D70: Price | E70: Amt. | F70: Used | G70: Used | H70: Rec'd | I70: Rec'd | J70: Return | K70: Return | L70: Stock | M70: Cost
A71: =[1]IFE!$A4751 -> 0 | C71: =[1]IFE!$B4751 -> 0 | D71: =[1]IFE!$J4751 -> 0 | E71: =[1]IFE!$D4751 -> 0 | F71: =[1]IFE!$C4751+[1]IFE!$P4751 -> 0 | G71: =[1]IFE!$H4751+[1]IFE!$R4751 -> 0 | H71: =[1]IFE!$E4751 -> 0 | I71: =[1]IFE!$K4751 -> 0 | J71: =[1]IFE!$F4751 -> 0 | K71: =[1]IFE!$L4751 -> 0 | L71: =[1]IFE!$G4751 -> 0 | M71: =F71*[1]IFE!$J4751 -> 0
A72: =[1]IFE!$A4752 -> 0 | C72: =[1]IFE!$B4752 -> 0 | D72: =[1]IFE!$J4752 -> 0 | E72: =[1]IFE!$D4752 -> 0 | F72: =[1]IFE!$C4752+[1]IFE!$P4752 -> 0 | G72: =[1]IFE!$H4752+[1]IFE!$R4752 -> 0 | H72: =[1]IFE!$E4752 -> 0 | I72: =[1]IFE!$K4752 -> 0 | J72: =[1]IFE!$F4752 -> 0 | K72: =[1]IFE!$L4752 -> 0 | L72: =[1]IFE!$G4752 -> 0 | M72: =F72*[1]IFE!$J4752 -> 0
A73: =[1]IFE!$A4753 -> 0 | C73: =[1]IFE!$B4753 -> 0 | D73: =[1]IFE!$J4753 -> 0 | E73: =[1]IFE!$D4753 -> 0 | F73: =[1]IFE!$C4753+[1]IFE!$P4753 -> 0 | G73: =[1]IFE!$H4753+[1]IFE!$R4753 -> 0 | H73: =[1]IFE!$E4753 -> 0 | I73: =[1]IFE!$K4753 -> 0 | J73: =[1]IFE!$F4753 -> 0 | K73: =[1]IFE!$L4753 -> 0 | L73: =[1]IFE!$G4753 -> 0 | M73: =F73*[1]IFE!$J4753 -> 0
A74: =[1]IFE!$A4754 -> 0 | C74: =[1]IFE!$B4754 -> 0 | D74: =[1]IFE!$J4754 -> 0 | E74: =[1]IFE!$D4754 -> 0 | F74: =[1]IFE!$C4754+[1]IFE!$P4754 -> 0 | G74: =[1]IFE!$H4754+[1]IFE!$R4754 -> 0 | H74: =[1]IFE!$E4754 -> 0 | I74: =[1]IFE!$K4754 -> 0 | J74: =[1]IFE!$F4754 -> 0 | K74: =[1]IFE!$L4754 -> 0 | L74: =[1]IFE!$G4754 -> 0 | M74: =F74*[1]IFE!$J4754 -> 0
A75: =[1]IFE!$A4755 -> 0 | C75: =[1]IFE!$B4755 -> 0 | D75: =[1]IFE!$J4755 -> 0 | E75: =[1]IFE!$D4755 -> 0 | F75: =[1]IFE!$C4755+[1]IFE!$P4755 -> 0 | G75: =[1]IFE!$H4755+[1]IFE!$R4755 -> 0 | H75: =[1]IFE!$E4755 -> 0 | I75: =[1]IFE!$K4755 -> 0 | J75: =[1]IFE!$F4755 -> 0 | K75: =[1]IFE!$L4755 -> 0 | L75: =[1]IFE!$G4755 -> 0 | M75: =F75*[1]IFE!$J4755 -> 0
A76: =[1]IFE!$A4756 -> 0 | C76: =[1]IFE!$B4756 -> 0 | D76: =[1]IFE!$J4756 -> 0 | E76: =[1]IFE!$D4756 -> 0 | F76: =[1]IFE!$C4756+[1]IFE!$P4756 -> 0 | G76: =[1]IFE!$H4756+[1]IFE!$R4756 -> 0 | H76: =[1]IFE!$E4756 -> 0 | I76: =[1]IFE!$K4756 -> 0 | J76: =[1]IFE!$F4756 -> 0 | K76: =[1]IFE!$L4756 -> 0 | L76: =[1]IFE!$G4756 -> 0 | M76: =F76*[1]IFE!$J4756 -> 0
A77: =[1]IFE!$A4757 -> 0 | C77: =[1]IFE!$B4757 -> 0 | D77: =[1]IFE!$J4757 -> 0 | E77: =[1]IFE!$D4757 -> 0 | F77: =[1]IFE!$C4757+[1]IFE!$P4757 -> 0 | G77: =[1]IFE!$H4757+[1]IFE!$R4757 -> 0 | H77: =[1]IFE!$E4757 -> 0 | I77: =[1]IFE!$K4757 -> 0 | J77: =[1]IFE!$F4757 -> 0 | K77: =[1]IFE!$L4757 -> 0 | L77: =[1]IFE!$G4757 -> 0 | M77: =F77*[1]IFE!$J4757 -> 0
A78: =[1]IFE!$A4758 -> 0 | C78: =[1]IFE!$B4758 -> 0 | D78: =[1]IFE!$J4758 -> 0 | E78: =[1]IFE!$D4758 -> 0 | F78: =[1]IFE!$C4758+[1]IFE!$P4758 -> 0 | G78: =[1]IFE!$H4758+[1]IFE!$R4758 -> 0 | H78: =[1]IFE!$E4758 -> 0 | I78: =[1]IFE!$K4758 -> 0 | J78: =[1]IFE!$F4758 -> 0 | K78: =[1]IFE!$L4758 -> 0 | L78: =[1]IFE!$G4758 -> 0 | M78: =F78*[1]IFE!$J4758 -> 0
A79: =[1]IFE!$A4759 -> 0 | C79: =[1]IFE!$B4759 -> 0 | D79: =[1]IFE!$J4759 -> 0 | E79: =[1]IFE!$D4759 -> 0 | F79: =[1]IFE!$C4759+[1]IFE!$P4759 -> 0 | G79: =[1]IFE!$H4759+[1]IFE!$R4759 -> 0 | H79: =[1]IFE!$E4759 -> 0 | I79: =[1]IFE!$K4759 -> 0 | J79: =[1]IFE!$F4759 -> 0 | K79: =[1]IFE!$L4759 -> 0 | L79: =[1]IFE!$G4759 -> 0 | M79: =F79*[1]IFE!$J4759 -> 0
A80: =[1]IFE!$A4760 -> 0 | C80: =[1]IFE!$B4760 -> 0 | D80: =[1]IFE!$J4760 -> 0 | E80: =[1]IFE!$D4760 -> 0 | F80: =[1]IFE!$C4760+[1]IFE!$P4760 -> 0 | G80: =[1]IFE!$H4760+[1]IFE!$R4760 -> 0 | H80: =[1]IFE!$E4760 -> 0 | I80: =[1]IFE!$K4760 -> 0 | J80: =[1]IFE!$F4760 -> 0 | K80: =[1]IFE!$L4760 -> 0 | L80: =[1]IFE!$G4760 -> 0 | M80: =F80*[1]IFE!$J4760 -> 0
A81: =[1]IFE!$A4761 -> 0 | C81: =[1]IFE!$B4761 -> 0 | D81: =[1]IFE!$J4761 -> 0 | E81: =[1]IFE!$D4761 -> 0 | F81: =[1]IFE!$C4761+[1]IFE!$P4761 -> 0 | G81: =[1]IFE!$H4761+[1]IFE!$R4761 -> 0 | H81: =[1]IFE!$E4761 -> 0 | I81: =[1]IFE!$K4761 -> 0 | J81: =[1]IFE!$F4761 -> 0 | K81: =[1]IFE!$L4761 -> 0 | L81: =[1]IFE!$G4761 -> 0 | M81: =F81*[1]IFE!$J4761 -> 0
A82: =[1]IFE!$A4762 -> 0 | C82: =[1]IFE!$B4762 -> 0 | D82: =[1]IFE!$J4762 -> 0 | E82: =[1]IFE!$D4762 -> 0 | F82: =[1]IFE!$C4762+[1]IFE!$P4762 -> 0 | G82: =[1]IFE!$H4762+[1]IFE!$R4762 -> 0 | H82: =[1]IFE!$E4762 -> 0 | I82: =[1]IFE!$K4762 -> 0 | J82: =[1]IFE!$F4762 -> 0 | K82: =[1]IFE!$L4762 -> 0 | L82: =[1]IFE!$G4762 -> 0 | M82: =F82*[1]IFE!$J4762 -> 0
... A120: =[1]IFE!$A4800 -> 0 | C120: =[1]IFE!$B4800 -> 0 | D120: =[1]IFE!$J4800 -> 0 | E120: =[1]IFE!$D4800 -> 0 | F120: =[1]IFE!$C4800+[1]IFE!$P4800 -> 0 | G120: =[1]IFE!$H4800+[1]IFE!$R4800 -> 0 | H120: =[1]IFE!$E4800 -> 0 | I120: =[1]IFE!$K4800 -> 0 | J120: =[1]IFE!$F4800 -> 0 | K120: =[1]IFE!$L4800 -> 0 | L120: =[1]IFE!$G4800 -> 0 | M120: =F120*[1]IFE!$J4800 -> 0
G121: WELLSITE CHEMICAL INVENTORY
G122: Daily Report
B123: Operator : | C123: =[1]IFE!$B$6 -> Cardon IV | I123: Date : | J123: =[1]IFE!$B$119 -> 39989
B124: Well Name : | C124: =[1]IFE!$B$8 -> Perla-1X | I124: Report No: | J124: =[1]IFE!$B$166 -> 9
B125: Location: | C125: =[1]IFE!$B$11 -> Offshore | I125: Page | J125: 3
E126: Cost Summary
D127: Total Daily Cost: | F127: =$F$7 -> 5749.32 | J127: Total Daily Tax: | K127: =$K$7 -> 0
D128: Cumulative Cost: | F128: =$F$8 -> 89939.53
A129: Product | C129: Unit | D129: Unit | E129: Start | F129: Daily | G129: Cum | H129: Daily | I129: Cum | J129: Daily | K129: Cum. | L129: Final | M129: Daily
C130: Size | D130: Price | E130: Amt. | F130: Used | G130: Used | H130: Rec'd | I130: Rec'd | J130: Return | K130: Return | L130: Stock | M130: Cost
A131: =[1]IFE!$A4801 -> 0 | C131: =[1]IFE!$B4801 -> 0 | D131: =[1]IFE!$J4801 -> 0 | E131: =[1]IFE!$D4801 -> 0 | F131: =[1]IFE!$C4801+[1]IFE!$P4801 -> 0 | G131: =[1]IFE!$H4801+[1]IFE!$R4801 -> 0 | H131: =[1]IFE!$E4801 -> 0 | I131: =[1]IFE!$K4801 -> 0 | J131: =[1]IFE!$F4801 -> 0 | K131: =[1]IFE!$L4801 -> 0 | L131: =[1]IFE!$G4801 -> 0 | M131: =F131*[1]IFE!$J4801 -> 0
A132: =[1]IFE!$A4802 -> 0 | C132: =[1]IFE!$B4802 -> 0 | D132: =[1]IFE!$J4802 -> 0 | E132: =[1]IFE!$D4802 -> 0 | F132: =[1]IFE!$C4802+[1]IFE!$P4802 -> 0 | G132: =[1]IFE!$H4802+[1]IFE!$R4802 -> 0 | H132: =[1]IFE!$E4802 -> 0 | I132: =[1]IFE!$K4802 -> 0 | J132: =[1]IFE!$F4802 -> 0 | K132: =[1]IFE!$L4802 -> 0 | L132: =[1]IFE!$G4802 -> 0 | M132: =F132*[1]IFE!$J4802 -> 0
A133: =[1]IFE!$A4803 -> 0 | C133: =[1]IFE!$B4803 -> 0 | D133: =[1]IFE!$J4803 -> 0 | E133: =[1]IFE!$D4803 -> 0 | F133: =[1]IFE!$C4803+[1]IFE!$P4803 -> 0 | G133: =[1]IFE!$H4803+[1]IFE!$R4803 -> 0 | H133: =[1]IFE!$E4803 -> 0 | I133: =[1]IFE!$K4803 -> 0 | J133: =[1]IFE!$F4803 -> 0 | K133: =[1]IFE!$L4803 -> 0 | L133: =[1]IFE!$G4803 -> 0 | M133: =F133*[1]IFE!$J4803 -> 0
A134: =[1]IFE!$A4804 -> 0 | C134: =[1]IFE!$B4804 -> 0 | D134: =[1]IFE!$J4804 -> 0 | E134: =[1]IFE!$D4804 -> 0 | F134: =[1]IFE!$C4804+[1]IFE!$P4804 -> 0 | G134: =[1]IFE!$H4804+[1]IFE!$R4804 -> 0 | H134: =[1]IFE!$E4804 -> 0 | I134: =[1]IFE!$K4804 -> 0 | J134: =[1]IFE!$F4804 -> 0 | K134: =[1]IFE!$L4804 -> 0 | L134: =[1]IFE!$G4804 -> 0 | M134: =F134*[1]IFE!$J4804 -> 0
A135: =[1]IFE!$A4805 -> 0 | C135: =[1]IFE!$B4805 -> 0 | D135: =[1]IFE!$J4805 -> 0 | E135: =[1]IFE!$D4805 -> 0 | F135: =[1]IFE!$C4805+[1]IFE!$P4805 -> 0 | G135: =[1]IFE!$H4805+[1]IFE!$R4805 -> 0 | H135: =[1]IFE!$E4805 -> 0 | I135: =[1]IFE!$K4805 -> 0 | J135: =[1]IFE!$F4805 -> 0 | K135: =[1]IFE!$L4805 -> 0 | L135: =[1]IFE!$G4805 -> 0 | M135: =F135*[1]IFE!$J4805 -> 0
A136: =[1]IFE!$A4806 -> 0 | C136: =[1]IFE!$B4806 -> 0 | D136: =[1]IFE!$J4806 -> 0 | E136: =[1]IFE!$D4806 -> 0 | F136: =[1]IFE!$C4806+[1]IFE!$P4806 -> 0 | G136: =[1]IFE!$H4806+[1]IFE!$R4806 -> 0 | H136: =[1]IFE!$E4806 -> 0 | I136: =[1]IFE!$K4806 -> 0 | J136: =[1]IFE!$F4806 -> 0 | K136: =[1]IFE!$L4806 -> 0 | L136: =[1]IFE!$G4806 -> 0 | M136: =F136*[1]IFE!$J4806 -> 0
A137: =[1]IFE!$A4807 -> 0 | C137: =[1]IFE!$B4807 -> 0 | D137: =[1]IFE!$J4807 -> 0 | E137: =[1]IFE!$D4807 -> 0 | F137: =[1]IFE!$C4807+[1]IFE!$P4807 -> 0 | G137: =[1]IFE!$H4807+[1]IFE!$R4807 -> 0 | H137: =[1]IFE!$E4807 -> 0 | I137: =[1]IFE!$K4807 -> 0 | J137: =[1]IFE!$F4807 -> 0 | K137: =[1]IFE!$L4807 -> 0 | L137: =[1]IFE!$G4807 -> 0 | M137: =F137*[1]IFE!$J4807 -> 0
...

Sheet Equipment
I2: ="Equipment Usage and Cost" -> Equipment Usage and Cost
A3: Operator : | B3: =[1]IFE!$B$6 -> Cardon IV | E3: Well Name : | F3: =[1]IFE!$B$8 -> Perla-1X | I3: Date : | J3: =[1]IFE!$B$119 -> 39989
A4: Report For : | B4: =[1]IFE!$B$125 -> Gerrit Ham / Jhony Quintero | E4: Field/Area : | F4: =[1]IFE!$B$9 -> Golfo de Venezuela | I4: Spud Date : | J4: =[1]IFE!$B$5 -> 39981
A5: Contractor: | B5: =[1]IFE!$B$15 -> Ensco | E5: Location : | F5: =[1]IFE!$B$11 -> Offshore | I5: Mud Type : | J5: =[1]IFE!$B$124 -> Agua de mar / HI VIS
A6: Report For : | B6: =[1]IFE!$B$126 -> Ricky Otwell | I6: Activity : | J6: =[1]IFE!$B$123 -> Bajando Tuberia
E8: Unit Cost | G8: (F)ull or | H8: Used | I8: Code | J8: Daily Rental
A9: Equipment Description | E9: Full | F9: Stand-by | G9: (S)tand-by | H9: Today | J9: ="Cost (" & [1]IFE!$B$28 &")" -> Cost ($)
A10: =WorkArea!C6 -> DERRICK SHEKER 1 | E10: =WorkArea!E6 -> 0 | F10: =WorkArea!F6 -> 0 | G10: =IF(A10>"",O10,"") -> F | H10: =WorkArea!Q6 -> 0 | I10: =WorkArea!K6 -> 0 | J10: =IF(G10="F",E10*H10,F10*H10) -> 0 | O10: =IF(WorkArea!R6=1,"F","S") -> F
A11: =WorkArea!C7 -> DERRICK SHAKER 2 | E11: =WorkArea!E7 -> 0 | F11: =WorkArea!F7 -> 0 | G11: =IF(A11>"",O11,"") -> F | H11: =WorkArea!Q7 -> 0 | I11: =WorkArea!K7 -> 0 | J11: =IF(G11="F",E11*H11,F11*H11) -> 0 | O11: =IF(WorkArea!R7=1,"F","S") -> F
A12: =WorkArea!C8 -> DERRICK SHAKER 3 | E12: =WorkArea!E8 -> 0 | F12: =WorkArea!F8 -> 0 | G12: =IF(A12>"",O12,"") -> F | H12: =WorkArea!Q8 -> 0 | I12: =WorkArea!K8 -> 0 | J12: =IF(G12="F",E12*H12,F12*H12) -> 0 | O12: =IF(WorkArea!R8=1,"F","S") -> F
A13: =WorkArea!C9 -> MOD 312 / 10T2 w/o pump | E13: =WorkArea!E9 -> 0 | F13: =WorkArea!F9 -> 0 | G13: =IF(A13>"",O13,"") -> F | H13: =WorkArea!Q9 -> 0 | I13: =WorkArea!K9 -> 0 | J13: =IF(G13="F",E13*H13,F13*H13) -> 0 | O13: =IF(WorkArea!R9=1,"F","S") -> F
A14: =WorkArea!C10 -> 0 | E14: =WorkArea!E10 -> 0 | F14: =WorkArea!F10 -> 0 | G14: =IF(A14>"",O14,"") | H14: =WorkArea!Q10 -> 0 | I14: =WorkArea!K10 -> 0 | J14: =IF(G14="F",E14*H14,F14*H14) -> 0 | O14: =IF(WorkArea!R10=1,"F","S") -> S
A15: =WorkArea!C11 -> 0 | E15: =WorkArea!E11 -> 0 | F15: =WorkArea!F11 -> 0 | G15: =IF(A15>"",O15,"") | H15: =WorkArea!Q11 -> 0 | I15: =WorkArea!K11 -> 0 | J15: =IF(G15="F",E15*H15,F15*H15) -> 0 | O15: =IF(WorkArea!R11=1,"F","S") -> S
A16: =WorkArea!C12 -> 0 | E16: =WorkArea!E12 -> 0 | F16: =WorkArea!F12 -> 0 | G16: =IF(A16>"",O16,"") | H16: =WorkArea!Q12 -> 0 | I16: =WorkArea!K12 -> 0 | J16: =IF(G16="F",E16*H16,F16*H16) -> 0 | O16: =IF(WorkArea!R12=1,"F","S") -> S
A17: =WorkArea!C13 -> 0 | E17: =WorkArea!E13 -> 0 | F17: =WorkArea!F13 -> 0 | G17: =IF(A17>"",O17,"") | H17: =WorkArea!Q13 -> 0 | I17: =WorkArea!K13 -> 0 | J17: =IF(G17="F",E17*H17,F17*H17) -> 0 | O17: =IF(WorkArea!R13=1,"F","S") -> S
A18: =WorkArea!C14 -> 0 | E18: =WorkArea!E14 -> 0 | F18: =WorkArea!F14 -> 0 | G18: =IF(A18>"",O18,"") | H18: =WorkArea!Q14 -> 0 | I18: =WorkArea!K14 -> 0 | J18: =IF(G18="F",E18*H18,F18*H18) -> 0 | O18: =IF(WorkArea!R14=1,"F","S") -> S
A19: =WorkArea!C15 -> 0 | E19: =WorkArea!E15 -> 0 | F19: =WorkArea!F15 -> 0 | G19: =IF(A19>"",O19,"") | H19: =WorkArea!Q15 -> 0 | I19: =WorkArea!K15 -> 0 | J19: =IF(G19="F",E19*H19,F19*H19) -> 0 | O19: =IF(WorkArea!R15=1,"F","S") -> S
A20: =WorkArea!C16 -> 0 | E20: =WorkArea!E16 -> 0 | F20: =WorkArea!F16 -> 0 | G20: =IF(A20>"",O20,"") | H20: =WorkArea!Q16 -> 0 | I20: =WorkArea!K16 -> 0 | J20: =IF(G20="F",E20*H20,F20*H20) -> 0 | O20: =IF(WorkArea!R16=1,"F","S") -> S
A21: =WorkArea!C17 -> 0 | E21: =WorkArea!E17 -> 0 | F21: =WorkArea!F17 -> 0 | G21: =IF(A21>"",O21,"") | H21: =WorkArea!Q17 -> 0 | I21: =WorkArea!K17 -> 0 | J21: =IF(G21="F",E21*H21,F21*H21) -> 0 | O21: =IF(WorkArea!R17=1,"F","S") -> S
... A45: =WorkArea!C41 -> 0 | E45: =WorkArea!E41 -> 0 | F45: =WorkArea!F41 -> 0 | G45: =IF(A45>"",O45,"") | H45: =WorkArea!Q41 -> 0 | I45: =WorkArea!K41 -> 0 | J45: =IF(G45="F",E45*H45,F45*H45) -> 0 | O45: =IF(WorkArea!R41=1,"F","S") -> S
A47: Drilling Fluids Equipment | E47: =SUMIF(I10:I45,"=0",J10:L45) -> 0
A48: Other Solids Removal Equipment | E48: =O48+P48 -> 0 | O48: =SUMIF($I$10:$I$45,2,$J$10:$L$45) -> 0 | P48: =SUMIF($I$10:$I$45,"=1",$J$10:$L$45) -> 0
A49: Additional Equipment | E49: =SUMIF(I10:I45,"=3",J10:L45) -> 0
A50: Total | E50: =SUM(E47:E49) -> 0

Sheet Screen Inventory
I1: ="Screen Inventory and Usage" -> Screen Inventory and Usage
A3: Operator : | B3: =[1]IFE!$B$6 -> Cardon IV | G3: Well Name : | H3: =[1]IFE!$B$8 -> Perla-1X | L3: Date : | M3: =[1]IFE!$B$119 -> 39989
A4: Report For : | B4: =[1]IFE!$B$125 -> Gerrit Ham / Jhony Quintero | G4: Field/Area : | H4: =[1]IFE!$B$9 -> Golfo de Venezuela | L4: Spud Date : | M4: =[1]IFE!$B$5 -> 39981
A5: Contractor: | B5: =[1]IFE!$B$15 -> Ensco | G5: Location : | H5: =[1]IFE!$B$11 -> Offshore | L5: Mud Type : | M5: =[1]IFE!$B$124 -> Agua de mar / HI VIS
A6: Report For : | B6: =[1]IFE!$B$126 -> Ricky Otwell | L6: Activity : | M6: =[1]IFE!$B$123 -> Bajando Tuberia
A8: Screen Name | C8: Mesh | D8: Start | F8: Received | G8: Return | H8: Installed Today | J8: Final | L8: Unit | M8: Daily | N8: Used
C9: Size | D9: New | E9: Used | H9: New | I9: Used | J9: New | K9: Used | L9: Cost | M9: Cost | N9: for Well
A10: =[1]IFE!$N550 -> Derrick 100 | C10: =[1]IFE!$B$550 -> 0 | D10: =[1]IFE!$D$550 -> 0 | E10: =[1]IFE!$L$550 -> 0 | F10: =[1]IFE!$E$550 -> 0 | G10: =D10+F10-H10-J10 -> 0 | H10: =[1]IFE!$F$550 -> 0 | I10: =[1]IFE!$M$550 -> 0 | J10: =[1]IFE!$G$550 -> 0 | K10: =[1]IFE!$K$550 -> 0 | L10: =[1]IFE!$C550 -> 0 | M10: =[1]IFE!$I550 -> 0 | N10: =[1]IFE!$H550 -> 0
A11: =[1]IFE!$N551 -> 0 | C11: =[1]IFE!$B$551 -> 0 | D11: =[1]IFE!$D$551 -> 0 | E11: =[1]IFE!$L$551 -> 0 | F11: =[1]IFE!$E$551 -> 0 | G11: =D11+F11-H11-J11 -> 0 | H11: =[1]IFE!$F$551 -> 0 | I11: =[1]IFE!$M$551 -> 0 | J11: =[1]IFE!$G$551 -> 0 | K11: =[1]IFE!$K$551 -> 0 | L11: =[1]IFE!$C551 -> 0 | M11: =[1]IFE!$I551 -> 0 | N11: =[1]IFE!$H551 -> 0
A12: =[1]IFE!$N552 -> 0 | C12: =[1]IFE!$B$552 -> 0 | D12: =[1]IFE!$D$552 -> 0 | E12: =[1]IFE!$L$552 -> 0 | F12: =[1]IFE!$E$552 -> 0 | G12: =D12+F12-H12-J12 -> 0 | H12: =[1]IFE!$F$552 -> 0 | I12: =[1]IFE!$M$552 -> 0 | J12: =[1]IFE!$G$552 -> 0 | K12: =[1]IFE!$K$552 -> 0 | L12: =[1]IFE!$C552 -> 0 | M12: =[1]IFE!$I552 -> 0 | N12: =[1]IFE!$H552 -> 0
A13: =[1]IFE!$N553 -> 0 | C13: =[1]IFE!$B$553 -> 0 | D13: =[1]IFE!$D$553 -> 0 | E13: =[1]IFE!$L$553 -> 0 | F13: =[1]IFE!$E$553 -> 0 | G13: =D13+F13-H13-J13 -> 0 | H13: =[1]IFE!$F$553 -> 0 | I13: =[1]IFE!$M$553 -> 0 | J13: =[1]IFE!$G$553 -> 0 | K13: =[1]IFE!$K$553 -> 0 | L13: =[1]IFE!$C553 -> 0 | M13: =[1]IFE!$I553 -> 0 | N13: =[1]IFE!$H553 -> 0
A14: =[1]IFE!$N554 -> 0 | C14: =[1]IFE!$B$554 -> 0 | D14: =[1]IFE!$D$554 -> 0 | E14: =[1]IFE!$L$554 -> 0 | F14: =[1]IFE!$E$554 -> 0 | G14: =D14+F14-H14-J14 -> 0 | H14: =[1]IFE!$F$554 -> 0 | I14: =[1]IFE!$M$554 -> 0 | J14: =[1]IFE!$G$554 -> 0 | K14: =[1]IFE!$K$554 -> 0 | L14: =[1]IFE!$C554 -> 0 | M14: =[1]IFE!$I554 -> 0 | N14: =[1]IFE!$H554 -> 0
A15: =[1]IFE!$N555 -> 0 | C15: =[1]IFE!$B$555 -> 0 | D15: =[1]IFE!$D$555 -> 0 | E15: =[1]IFE!$L$555 -> 0 | F15: =[1]IFE!$E$555 -> 0 | G15: =D15+F15-H15-J15 -> 0 | H15: =[1]IFE!$F$555 -> 0 | I15: =[1]IFE!$M$555 -> 0 | J15: =[1]IFE!$G$555 -> 0 | K15: =[1]IFE!$K$555 -> 0 | L15: =[1]IFE!$C555 -> 0 | M15: =[1]IFE!$I555 -> 0 | N15: =[1]IFE!$H555 -> 0
A16: =[1]IFE!$N556 -> 0 | C16: =[1]IFE!$B$556 -> 0 | D16: =[1]IFE!$D$556 -> 0 | E16: =[1]IFE!$L$556 -> 0 | F16: =[1]IFE!$E$556 -> 0 | G16: =D16+F16-H16-J16 -> 0 | H16: =[1]IFE!$F$556 -> 0 | I16: =[1]IFE!$M$556 -> 0 | J16: =[1]IFE!$G$556 -> 0 | K16: =[1]IFE!$K$556 -> 0 | L16: =[1]IFE!$C556 -> 0 | M16: =[1]IFE!$I556 -> 0 | N16: =[1]IFE!$H556 -> 0
A17: =[1]IFE!$N557 -> 0 | C17: =[1]IFE!$B$557 -> 0 | D17: =[1]IFE!$D$557 -> 0 | E17: =[1]IFE!$L$557 -> 0 | F17: =[1]IFE!$E$557 -> 0 | G17: =D17+F17-H17-J17 -> 0 | H17: =[1]IFE!$F$557 -> 0 | I17: =[1]IFE!$M$557 -> 0 | J17: =[1]IFE!$G$557 -> 0 | K17: =[1]IFE!$K$557 -> 0 | L17: =[1]IFE!$C557 -> 0 | M17: =[1]IFE!$I557 -> 0 | N17: =[1]IFE!$H557 -> 0
A18: =[1]IFE!$N558 -> 0 | C18: =[1]IFE!$B$558 -> 0 | D18: =[1]IFE!$D$558 -> 0 | E18: =[1]IFE!$L$558 -> 0 | F18: =[1]IFE!$E$558 -> 0 | G18: =D18+F18-H18-J18 -> 0 | H18: =[1]IFE!$F$558 -> 0 | I18: =[1]IFE!$M$558 -> 0 | J18: =[1]IFE!$G$558 -> 0 | K18: =[1]IFE!$K$558 -> 0 | L18: =[1]IFE!$C558 -> 0 | M18: =[1]IFE!$I558 -> 0 | N18: =[1]IFE!$H558 -> 0
A19: =[1]IFE!$N559 -> 0 | C19: =[1]IFE!$B$559 -> 0 | D19: =[1]IFE!$D$559 -> 0 | E19: =[1]IFE!$L$559 -> 0 | F19: =[1]IFE!$E$559 -> 0 | G19: =D19+F19-H19-J19 -> 0 | H19: =[1]IFE!$F$559 -> 0 | I19: =[1]IFE!$M$559 -> 0 | J19: =[1]IFE!$G$559 -> 0 | K19: =[1]IFE!$K$559 -> 0 | L19: =[1]IFE!$C559 -> 0 | M19: =[1]IFE!$I559 -> 0 | N19: =[1]IFE!$H559 -> 0
A20: =[1]IFE!$N560 -> 0 | C20: =[1]IFE!$B$560 -> 0 | D20: =[1]IFE!$D$560 -> 0 | E20: =[1]IFE!$L$560 -> 0 | F20: =[1]IFE!$E$560 -> 0 | G20: =D20+F20-H20-J20 -> 0 | H20: =[1]IFE!$F$560 -> 0 | I20: =[1]IFE!$M$560 -> 0 | J20: =[1]IFE!$G$560 -> 0 | K20: =[1]IFE!$K$560 -> 0 | L20: =[1]IFE!$C560 -> 0 | M20: =[1]IFE!$I560 -> 0 | N20: =[1]IFE!$H560 -> 0
A21: =[1]IFE!$N561 -> 0 | C21: =[1]IFE!$B$561 -> 0 | D21: =[1]IFE!$D$561 -> 0 | E21: =[1]IFE!$L$561 -> 0 | F21: =[1]IFE!$E$561 -> 0 | G21: =D21+F21-H21-J21 -> 0 | H21: =[1]IFE!$F$561 -> 0 | I21: =[1]IFE!$M$561 -> 0 | J21: =[1]IFE!$G$561 -> 0 | K21: =[1]IFE!$K$561 -> 0 | L21: =[1]IFE!$C561 -> 0 | M21: =[1]IFE!$I561 -> 0 | N21: =[1]IFE!$H561 -> 0
A22: =[1]IFE!$N562 -> 0 | C22: =[1]IFE!$B$562 -> 0 | D22: =[1]IFE!$D$562 -> 0 | E22: =[1]IFE!$L$562 -> 0 | F22: =[1]IFE!$E$562 -> 0 | G22: =D22+F22-H22-J22 -> 0 | H22: =[1]IFE!$F$562 -> 0 | I22: =[1]IFE!$M$552 -> 0 | J22: =[1]IFE!$G$562 -> 0 | K22: =[1]IFE!$K$562 -> 0 | L22: =[1]IFE!$C562 -> 0 | M22: =[1]IFE!$I562 -> 0 | N22: =[1]IFE!$H562 -> 0
A23: =[1]IFE!$N563 -> 0 | C23: =[1]IFE!$B$563 -> 0 | D23: =[1]IFE!$D$563 -> 0 | E23: =[1]IFE!$L$563 -> 0 | F23: =[1]IFE!$E$563 -> 0 | G23: =D23+F23-H23-J23 -> 0 | H23: =[1]IFE!$F$563 -> 0 | I23: =[1]IFE!$M$563 -> 0 | J23: =[1]IFE!$G$563 -> 0 | K23: =[1]IFE!$K$563 -> 0 | L23: =[1]IFE!$C563 -> 0 | M23: =[1]IFE!$I563 -> 0 | N23: =[1]IFE!$H563 -> 0
A24: =[1]IFE!$N564 -> 0 | C24: =[1]IFE!$B$564 -> 0 | D24: =[1]IFE!$D$564 -> 0 | E24: =[1]IFE!$L$564 -> 0 | F24: =[1]IFE!$E$564 -> 0 | G24: =D24+F24-H24-J24 -> 0 | H24: =[1]IFE!$F$564 -> 0 | I24: =[1]IFE!$M$564 -> 0 | J24: =[1]IFE!$G$564 -> 0 | K24: =[1]IFE!$K$564 -> 0 | L24: =[1]IFE!$C564 -> 0 | M24: =[1]IFE!$I564 -> 0 | N24: =[1]IFE!$H564 -> 0
A25: =[1]IFE!$N565 -> 0 | C25: =[1]IFE!$B$565 -> 0 | D25: =[1]IFE!$D$565 -> 0 | E25: =[1]IFE!$L$565 -> 0 | F25: =[1]IFE!$E$565 -> 0 | G25: =D25+F25-H25-J25 -> 0 | H25: =[1]IFE!$F$565 -> 0 | I25: =[1]IFE!$M$565 -> 0 | J25: =[1]IFE!$G$565 -> 0 | K25: =[1]IFE!$K$565 -> 0 | L25: =[1]IFE!$C565 -> 0 | M25: =[1]IFE!$I565 -> 0 | N25: =[1]IFE!$H565 -> 0
A26: =[1]IFE!$N566 -> 0 | C26: =[1]IFE!$B$566 -> 0 | D26: =[1]IFE!$D$566 -> 0 | E26: =[1]IFE!$L$566 -> 0 | F26: =[1]IFE!$E$566 -> 0 | G26: =D26+F26-H26-J26 -> 0 | H26: =[1]IFE!$F$566 -> 0 | I26: =[1]IFE!$M$566 -> 0 | J26: =[1]IFE!$G$566 -> 0 | K26: =[1]IFE!$K$566 -> 0 | L26: =[1]IFE!$C566 -> 0 | M26: =[1]IFE!$I566 -> 0 | N26: =[1]IFE!$H566 -> 0
A27: =[1]IFE!$N567 -> 0 | C27: =[1]IFE!$B$567 -> 0 | D27: =[1]IFE!$D$567 -> 0 | E27: =[1]IFE!$L$567 -> 0 | F27: =[1]IFE!$E$567 -> 0 | G27: =D27+F27-H27-J27 -> 0 | H27: =[1]IFE!$F$567 -> 0 | I27: =[1]IFE!$M$567 -> 0 | J27: =[1]IFE!$G$567 -> 0 | K27: =[1]IFE!$K$567 -> 0 | L27: =[1]IFE!$C567 -> 0 | M27: =[1]IFE!$I567 -> 0 | N27: =[1]IFE!$H567 -> 0
A28: =[1]IFE!$N568 -> 0 | C28: =[1]IFE!$B$568 -> 0 | D28: =[1]IFE!$D$568 -> 0 | E28: =[1]IFE!$L$568 -> 0 | F28: =[1]IFE!$E$568 -> 0 | G28: =D28+F28-H28-J28 -> 0 | H28: =[1]IFE!$F$568 -> 0 | I28: =[1]IFE!$M$568 -> 0 | J28: =[1]IFE!$G$568 -> 0 | K28: =[1]IFE!$K$568 -> 0 | L28: =[1]IFE!$C568 -> 0 | M28: =[1]IFE!$I568 -> 0 | N28: =[1]IFE!$H568 -> 0
A29: =[1]IFE!$N569 -> 0 | C29: =[1]IFE!$B$569 -> 0 | D29: =[1]IFE!$D$569 -> 0 | E29: =[1]IFE!$L$569 -> 0 | F29: =[1]IFE!$E$569 -> 0 | G29: =D29+F29-H29-J29 -> 0 | H29: =[1]IFE!$F$569 -> 0 | I29: =[1]IFE!$M$569 -> 0 | J29: =[1]IFE!$G$569 -> 0 | K29: =[1]IFE!$K$569 -> 0 | L29: =[1]IFE!$C569 -> 0 | M29: =[1]IFE!$I569 -> 0 | N29: =[1]IFE!$H569 -> 0
A30: =[1]IFE!$N570 -> 0 | C30: =[1]IFE!$B$570 -> 0 | D30: =[1]IFE!$D$570 -> 0 | E30: =[1]IFE!$L$570 -> 0 | F30: =[1]IFE!$E$570 -> 0 | G30: =D30+F30-H30-J30 -> 0 | H30: =[1]IFE!$F$570 -> 0 | I30: =[1]IFE!$M$570 -> 0 | J30: =[1]IFE!$G$570 -> 0 | K30: =[1]IFE!$K$570 -> 0 | L30: =[1]IFE!$C570 -> 0 | M30: =[1]IFE!$I570 -> 0 | N30: =[1]IFE!$H570 -> 0
A31: =[1]IFE!$N571 -> 0 | C31: =[1]IFE!$B$571 -> 0 | D31: =[1]IFE!$D$571 -> 0 | E31: =[1]IFE!$L$571 -> 0 | F31: =[1]IFE!$E$571 -> 0 | G31: =D31+F31-H31-J31 -> 0 | H31: =[1]IFE!$F$571 -> 0 | I31: =[1]IFE!$M$571 -> 0 | J31: =[1]IFE!$G$571 -> 0 | K31: =[1]IFE!$K$571 -> 0 | L31: =[1]IFE!$C571 -> 0 | M31: =[1]IFE!$I571 -> 0 | N31: =[1]IFE!$H571 -> 0
A32: =[1]IFE!$N572 -> 0 | C32: =[1]IFE!$B$572 -> 0 | D32: =[1]IFE!$D$572 -> 0 | E32: =[1]IFE!$L$572 -> 0 | F32: =[1]IFE!$E$572 -> 0 | G32: =D32+F32-H32-J32 -> 0 | H32: =[1]IFE!$F$572 -> 0 | I32: =[1]IFE!$M$572 -> 0 | J32: =[1]IFE!$G$572 -> 0 | K32: =[1]IFE!$K$572 -> 0 | L32: =[1]IFE!$C572 -> 0 | M32: =[1]IFE!$I572 -> 0 | N32: =[1]IFE!$H572 -> 0
A33: =[1]IFE!$N573 -> 0 | C33: =[1]IFE!$B$573 -> 0 | D33: =[1]IFE!$D$573 -> 0 | E33: =[1]IFE!$L$573 -> 0 | F33: =[1]IFE!$E$573 -> 0 | G33: =D33+F33-H33-J33 -> 0 | H33: =[1]IFE!$F$573 -> 0 | I33: =[1]IFE!$M$573 -> 0 | J33: =[1]IFE!$G$573 -> 0 | K33: =[1]IFE!$K$573 -> 0 | L33: =[1]IFE!$C573 -> 0 | M33: =[1]IFE!$I573 -> 0 | N33: =[1]IFE!$H573 -> 0
A34: =[1]IFE!$N574 -> 0 | C34: =[1]IFE!$B$574 -> 0 | D34: =[1]IFE!$D$574 -> 0 | E34: =[1]IFE!$L$574 -> 0 | F34: =[1]IFE!$E$574 -> 0 | G34: =D34+F34-H34-J34 -> 0 | H34: =[1]IFE!$F$574 -> 0 | I34: =[1]IFE!$M$574 -> 0 | J34: =[1]IFE!$G$574 -> 0 | K34: =[1]IFE!$K$574 -> 0 | L34: =[1]IFE!$C574 -> 0 | M34: =[1]IFE!$I574 -> 0 | N34: =[1]IFE!$H574 -> 0
A35: =[1]IFE!$N575 -> 0 | C35: =[1]IFE!$B$575 -> 0 | D35: =[1]IFE!$D$575 -> 0 | E35: =[1]IFE!$L$575 -> 0 | F35: =[1]IFE!$E$575 -> 0 | G35: =D35+F35-H35-J35 -> 0 | H35: =[1]IFE!$F$575 -> 0 | I35: =[1]IFE!$M$575 -> 0 | J35: =[1]IFE!$G$575 -> 0 | K35: =[1]IFE!$K$575 -> 0 | L35: =[1]IFE!$C575 -> 0 | M35: =[1]IFE!$I575 -> 0 | N35: =[1]IFE!$H575 -> 0
A36: =[1]IFE!$N576 -> 0 | C36: =[1]IFE!$B$576 -> 0 | D36: =[1]IFE!$D$576 -> 0 | E36: =[1]IFE!$L$576 -> 0 | F36: =[1]IFE!$E$576 -> 0 | G36: =D36+F36-H36-J36 -> 0 | H36: =[1]IFE!$F$576 -> 0 | I36: =[1]IFE!$M$576 -> 0 | J36: =[1]IFE!$G$576 -> 0 | K36: =[1]IFE!$K$576 -> 0 | L36: =[1]IFE!$C576 -> 0 | M36: =[1]IFE!$I576 -> 0 | N36: =[1]IFE!$H576 -> 0
A37: =[1]IFE!$N577 -> 0 | C37: =[1]IFE!$B$577 -> 0 | D37: =[1]IFE!$D$577 -> 0 | E37: =[1]IFE!$L$577 -> 0 | F37: =[1]IFE!$E$577 -> 0 | G37: =D37+F37-H37-J37 -> 0 | H37: =[1]IFE!$F$577 -> 0 | I37: =[1]IFE!$M$577 -> 0 | J37: =[1]IFE!$G$577 -> 0 | K37: =[1]IFE!$K$577 -> 0 | L37: =[1]IFE!$C577 -> 0 | M37: =[1]IFE!$I577 -> 0 | N37: =[1]IFE!$H577 -> 0
A38: =[1]IFE!$N578 -> 0 | C38: =[1]IFE!$B$578 -> 0 | D38: =[1]IFE!$D$578 -> 0 | E38: =[1]IFE!$L$578 -> 0 | F38: =[1]IFE!$E$578 -> 0 | G38: =D38+F38-H38-J38 -> 0 | H38: =[1]IFE!$F$578 -> 0 | I38: =[1]IFE!$M$578 -> 0 | J38: =[1]IFE!$G$578 -> 0 | K38: =[1]IFE!$K$578 -> 0 | L38: =[1]IFE!$C578 -> 0 | M38: =[1]IFE!$I578 -> 0 | N38: =[1]IFE!$H578 -> 0
A39: =[1]IFE!$N579 -> 0 | C39: =[1]IFE!$B$579 -> 0 | D39: =[1]IFE!$D$579 -> 0 | E39: =[1]IFE!$L$579 -> 0 | F39: =[1]IFE!$E$579 -> 0 | G39: =D39+F39-H39-J39 -> 0 | H39: =[1]IFE!$F$579 -> 0 | I39: =[1]IFE!$M$579 -> 0 | J39: =[1]IFE!$G$579 -> 0 | K39: =[1]IFE!$K$579 -> 0 | L39: =[1]IFE!$C579 -> 0 | M39: =[1]IFE!$I579 -> 0 | N39: =[1]IFE!$H579 -> 0
N40: =[1]IFE!$H580 -> 0
N41: =[1]IFE!$H581 -> 0
N42: =[1]IFE!$H582 -> 0
N43: =[1]IFE!$H583 -> 0
N44: =[1]IFE!$H584 -> 0
N45: =[1]IFE!$H585 -> 0
N46: =[1]IFE!$H586 -> 0
N47: =[1]IFE!$H587 -> 0
N48: =[1]IFE!$H588 -> 0
A49: TOTALS | D49: =SUM(D10:D48) -> 0 | E49: =SUM(E10:E48) -> 0 | F49: =SUM(F10:F48) -> 0 | G49: =SUM(G10:G48) -> 0 | H49: =SUM(H10:H48) -> 0 | I49: =SUM(I10:I48) -> 0 | J49: =SUM(J10:J48) -> 0 | K49: =SUM(K10:K48) -> 0 | M49: =SUM(M10:M48) -> 0 | N49: =SUM(N10:N48) -> 0
A51: Daily Cost: | B51: =SUM(M49) -> 0
A52: Cumulative Cost: | B52: =SUM([1]IFE!$J$550:$J$579) -> 0

Sheet WorkArea
A1: DO NOT UPDATE OR MODIFY THIS WORKSHEET!! | AX1: mt conv factor | AZ1: 2204.62
A4: wm items | B4: drilling fluids items | E4: Full Price | F4: SB | G4: Tax | H4: Discount | I4: SwacoP | J4: EqType | K4: Price Cat | Q4: Used | R4: ChargeCode
A5: 0 | B5: 4
A6: 1 | B6: 1 | C6: DERRICK SHEKER 1 | E6: 0 | F6: 0 | H6: 0 | J6: 5 | K6: 0 | O6: 1 | Q6: 0 | R6: 1 | S6: 0 | U6: 0 | V6: 7 | W6: 79 | AK6: 0 | AL6: 0 | AM6: 0 | AN6: 0 | AO6: 0 | AP6: 0 | AQ6: 0 | AR6: 0 | AS6: 0 | AT6: 0
A7: 2 | B7: 2 | C7: DERRICK SHAKER 2 | E7: 0 | F7: 0 | H7: 0 | J7: 5 | K7: 0 | O7: 2 | Q7: 0 | R7: 1 | S7: 0 | U7: 0 | V7: 7 | W7: 79 | AK7: 0 | AL7: 0 | AM7: 0 | AN7: 0 | AO7: 0 | AP7: 0 | AQ7: 0 | AR7: 0 | AS7: 0 | AT7: 0
A8: 3 | B8: 3 | C8: DERRICK SHAKER 3 | E8: 0 | F8: 0 | H8: 0 | J8: 5 | K8: 0 | O8: 3 | Q8: 0 | R8: 1 | S8: 0 | U8: 0 | V8: 24 | W8: 120 | AK8: 0 | AL8: 0 | AM8: 0 | AN8: 0 | AO8: 0 | AP8: 0 | AQ8: 0 | AR8: 0 | AS8: 0 | AT8: 0
A9: 4 | B9: 4 | C9: MOD 312 / 10T2 w/o pump | E9: 0 | F9: 0 | H9: 0 | J9: 4 | K9: 0 | O9: 4 | Q9: 0 | R9: 1 | S9: 0 | U9: 0 | V9: 24 | W9: 104 | AR9: 0 | AS9: 0 | AT9: 0
